Workbook

Sheet README
A1: ZapWise reference database
A3: Purpose | B3: Numbers behind the ZapWise migration estimate. Edit here, then run export_assets.py to refresh the app JSON.
A4: Compiled | B4: 2026-10-14
A5: Blue text | B5: Typed values. Change these when you have a better measurement or source.
A6: Black text | B6: Formulas. Do not overwrite.
A7: Status VERIFIED | B7: Number read on the cited page.
A8: Status SECONDARY | B8: Distributor page, Wikipedia or a similar secondary page.
A9: Status DERIVED | B9: Computed from verified inputs; the note shows how.
A10: Status ASSUMPTION | B10: A modelling choice. It must be stated in the report and tested where possible.
A11: Status UNVERIFIED | B11: Commonly cited but not confirmed on a primary page. Replace before the final submission if you can.
A12: Sources | B12: The Sources sheet numbers every reference (S01...). Other sheets cite those numbers.
A13: Checklist | B13: Student_Checklist lists the measurements that would replace the weakest assumptions.
A14: Sheets | B14: Sources, Polymers, Substances, Groups, Alt_References, Contents, Measured, Containers, FoodClasses, KpfModel, ModelParams, BodyWeights, Products, RecipeSteps, WattTables, Literature, Validation, Models, Student_Checklist

Sheet Sources
A1: ID | B1: Citation | C1: URL | D1: Type | E1: Accessed
A2: S01 | B2: Simoneau C. (ed.) et al. (2010). Applicability of generally recognised diffusion models for the estimation of specific migration in support of EU Directive 2002/72/EC. JRC59476, EUR 24514 EN. | C2: https://publications.jrc.ec.europa.eu/repository/bitstream/JRC59476/reqno_jrc59476_mathmod_v10_cs_2010_09_24_final.pdf%5B1%5D.pdf | D2: report | E2: 2026-10-14
A3: S02 | B3: Haldimann M. et al. (2013). Exposure to antimony from polyethylene terephthalate (PET) trays used in ready-to-eat meals. Food Addit Contam A 30(3):587-598. doi:10.1080/19440049.2012.751631 | C3: https://pmc.ncbi.nlm.nih.gov/articles/PMC3613973/ | D3: paper | E3: 2026-10-14
A4: S03 | B4: Liu J-M. et al. (2020). Phthalate esters in commercial disposable lunch boxes (title to confirm). Food Sci Nutr. doi:10.1002/fsn3.1863 | C4: https://pmc.ncbi.nlm.nih.gov/articles/PMC7590312 | D4: paper | E4: 2026-10-14
A5: S04 | B5: Lan M., Li H., Ying G. (2022). Phthalate esters in PP food containers and their migration (title to confirm). J South China Normal Univ (Nat Sci) 54(2):52-62. doi:10.6054/j.jscnun.2022026 | C5: https://doi.org/10.6054/j.jscnun.2022026 | D5: paper | E5: 2026-10-14
A6: S05 | B6: Moreira M.A., Andre L.C., Cardeal Z.L. (2014). Analysis of phthalate migration to food simulants in plastic containers during microwave operations. IJERPH 11(1):507-526. doi:10.3390/ijerph110100507 | C6: https://www.mdpi.com/1660-4601/11/1/507/html | D6: paper | E6: 2026-10-14
A7: S06 | B7: Review of antimony in PET bottles (2023, title to confirm). Molecules 28(20):7166. | C7: https://www.mdpi.com/1420-3049/28/20/7166 | D7: paper | E7: 2026-10-14
A8: S07 | B8: EFSA CEP Panel (2019). Update of the risk assessment of DBP, BBP, DEHP, DINP and DIDP for use in food contact materials. EFSA Journal 17(12):5838. | C8: https://doaj.org/article/cad5a51311ba4452b9b5807ddfb881a9 | D8: agency | E8: 2026-10-14
A9: S08 | B9: Commission Regulation (EU) 2023/1442 amending Annex I to Regulation (EU) No 10/2011 (phthalates, group restriction 36). | C9: https://eur-lex.europa.eu/legal-content/EN/TXT/HTML/?uri=CELEX:32023R1442 | D9: regulation | E9: 2026-10-14
A10: S09 | B10: WHO (2022). Antimony in drinking-water, chemical fact sheet (TDI 6 ug/kg bw/day, 2003 assessment). | C10: https://cdn.who.int/media/docs/default-source/wash-documents/water-safety-and-quality/chemical-fact-sheets-2022/antimony-fact-sheet-2022.pdf | D10: agency | E10: 2026-10-14
A11: S10 | B11: US EPA IRIS. Di(2-ethylhexyl)phthalate (DEHP), oral RfD 0.02 mg/kg-day (1987). | C11: https://iris.epa.gov/ChemicalLanding/&substance_nmbr=14 | D11: agency | E11: 2026-10-14
A12: S11 | B12: EFSA Scientific Committee (2012). Default values for body weight (adult 70 kg, toddler 12 kg, infant 5 kg). | C12: https://www.efsa.europa.eu/en/press/news/120307a | D12: agency | E12: 2026-10-14
... A83: S82 | B83: BfR (2019). Do not use 'bamboo ware' tableware for hot drinks and meals. Press release, 25 November 2019 (melamine-formaldehyde resin with bamboo fibre filler; not for heating food in the microwave). | C83: https://www.bfr.bund.de/en/press-release/do-not-use-bamboo-ware-tableware-for-hot-drinks-and-meals/ | D83: agency | E83: 2026-10-14

Sheet Polymers
A1: Key | B1: Polymer | C1: A_P' | D1: tau (K) | E1: T max valid (C) | F1: Density (g/cm3) | G1: Density status | H1: Density source | I1: Piringer source | J1: Status | K1: Huang 2017 material | L1: Huang b | M1: Huang tau (K) | N1: Partition material (Huang and Jolliet 2019)
A2: LDPE | B2: Low-density polyethylene | C2: 11.5 | D2: 0 | E2: 80 | F2: 0.92 | G2: SECONDARY | H2: S21 | I2: S01 | J2: VERIFIED | K2: Polyethylene (PE, LDPE, LLDPE) | L2: -1.65 | M2: 0 | N2: Low-density polyethylene (LDPE)
A3: LLDPE | B3: Linear low-density polyethylene | C3: 11.5 | D3: 0 | E3: 100 | F3: 0.92 | G3: SECONDARY | H3: S21 | I3: S01 | J3: VERIFIED | K3: Polyethylene (PE, LDPE, LLDPE) | L3: -1.65 | M3: 0 | N3: Linear low-density polyethylene (LLDPE)
A4: HDPE | B4: High-density polyethylene | C4: 14.5 | D4: 1577 | E4: 90 | F4: 0.95 | G4: ASSUMPTION | I4: S01 | J4: VERIFIED | K4: High density polyethylene (HDPE) | L4: 5.11 | M4: -2391 | N4: High-density polyethylene (HDPE)
A5: PP | B5: Polypropylene (homo and random) | C5: 13.1 | D5: 1577 | E5: 120 | F5: 0.9 | G5: VERIFIED | H5: S18 | I5: S01 | J5: VERIFIED | K5: PP homopolymer | L5: 4.53 | M5: -2391 | N5: Polypropylene (PP) homopolymer
A6: PP_RUBBER | B6: Polypropylene (rubber-modified) | C6: 11.5 | D6: 0 | E6: 100 | F6: 0.9 | G6: VERIFIED | H6: S18 | I6: S01 | J6: VERIFIED | K6: PP copolymer | L6: 4.79 | M6: -2391 | N6: Ethylene-propylene copolymer
A7: PS | B7: Polystyrene (GPPS) | C7: -1 | D7: 0 | E7: 70 | F7: 1.05 | G7: SECONDARY | H7: S21 | I7: S01 | J7: VERIFIED | K7: General polystyrene (PS) | L7: 2.04 | M7: -2391 | N7: Polystyrene (PS)
A8: HIPS | B8: High-impact polystyrene | C8: 1 | D8: 0 | E8: 70 | F8: 1.05 | G8: SECONDARY | H8: S21 | I8: S01 | J8: VERIFIED | K8: High-impact polystyrene (HIPS) | L8: -7.11 | M8: 0 | N8: Polystyrene (PS)
A9: PET_HI | B9: PET above Tg (about 70 C) | C9: 6.4 | D9: 1577 | E9: 175 | F9: 1.35 | G9: VERIFIED | H9: S02 | I9: S01;S41 | J9: VERIFIED | K9: Polyethylene terephthalate (PET) | L9: 0 | M9: -2391 | N9: Polyethylene terephthalate (PET)
A10: PET_LO | B10: PET below Tg | C10: 3.1 | D10: 1577 | E10: 70 | F10: 1.35 | G10: VERIFIED | H10: S02 | I10: S01;S41 | J10: VERIFIED | K10: Polyethylene terephthalate (PET) | L10: 0 | M10: -2391 | N10: Polyethylene terephthalate (PET)
A11: PEN | B11: Polyethylene naphthalate | C11: 5 | D11: 1577 | E11: 175 | I11: S01 | J11: VERIFIED | K11: Polyethylene naphthalate (PEN) | L11: -1.16 | M11: -2391 | N11: Polyethylene terephthalate (PET)
A12: PA6 | B12: Polyamide 6 | C12: 0 | D12: 0 | E12: 100 | I12: S01 | J12: VERIFIED | K12: Polyamide (PA) | L12: -5.4 | M12: 0 | N12: Nylon 6
A13: PA66 | B13: Polyamide 6,6 | C13: 2 | D13: 0 | E13: 100 | I13: S01 | J13: VERIFIED | K13: Polyamide (PA) | L13: -5.4 | M13: 0 | N13: Nylon 6
A14: PVC_RIGID | B14: Rigid PVC | C14: -1 | D14: 0 | E14: 70 | I14: S01 | J14: VERIFIED | K14: Rigid polymers | L14: -11.9 | M14: 1676 | N14: Polyvinyl chloride (PVC)
A16: Two diffusion coefficients per polymer. The engine works between them on a log scale (ModelParams d_weight_*).
A17: Piringer upper bound (cm2/s): D_P = 1e4 * exp(A_P' - tau/T - 0.1351*Mr^(2/3) + 0.003*Mr - 10454/T) [S01]
A18: Huang 2017 QPPR, realistic (m2/s): log10 D = 6.39 -2.49 log10 MW + b + (tau -3486)/T; x 1e4 for cm2/s [S78]
A19: Example: DEHP (Mr 390.57) in PP at 100 C
A20: Piringer (cm2/s) | F20: =10000*EXP(INDEX(C2:C14,MATCH("PP",A2:A14,0))-INDEX(D2:D14,MATCH("PP",A2:A14,0))/373.15-0.1351*390.57^(2/3)+0.003*390.57-10454/373.15) -> 1.1500359e-07 | G20: cm2/s
A21: Huang 2017 (cm2/s) | F21: =10000*10^(6.39-2.49*LOG10(390.57)+INDEX(L2:L14,MATCH("PP",A2:A14,0))+(INDEX(M2:M14,MATCH("PP",A2:A14,0))-3486)/373.15) -> 5.2116024e-08 | G21: cm2/s
A22: Piringer / Huang | F22: =F20/F21 -> 2.2066839

Sheet Substances
A1: Key | B1: Name | C1: CAS | D1: MW (g/mol) | E1: log Kow | F1: Group | G1: RPF (DEHP-eq) | H1: Diffusion model | I1: D0 (cm2/s) | J1: Ea (kJ/mol) | K1: Diffusible fraction | L1: Status | M1: Sources | N1: Note
A2: DEHP | B2: Di(2-ethylhexyl) phthalate | C2: 117-81-7 | D2: 390.57 | E2: 7.5 | F2: phthalate_dehp_eq | G2: 1 | H2: piringer | K2: 1 | L2: VERIFIED | M2: S13;S08 | N2: log Kow 7.14 also reported (ECHA via Health Canada). Sets the partition coefficient through the Huang and Jolliet 2019 regression [S76].
A3: DBP | B3: Dibutyl phthalate | C3: 84-74-2 | D3: 278.3 | E3: 4.46 | F3: phthalate_dehp_eq | G3: 5 | H3: piringer | K3: 1 | L3: VERIFIED | M3: S14;S08 | N3: RPF 5 from the DEHP-equivalent formula of group restriction 36.
A4: DIBP | B4: Diisobutyl phthalate | C4: 84-69-5 | D4: 278.3 | E4: 4.11 | F4: phthalate_dehp_eq | G4: 4 | H4: piringer | K4: 1 | L4: RPF VERIFIED; MW DERIVED (isomer of DBP, C16H22O4); log Kow UNVERIFIED (commonly cited 4.11) | M4: S08 | N4: log Kow sets the partition coefficient through the Huang and Jolliet 2019 regression [S76]. Confirm 4.11 on PubChem or ECHA.
A5: BBP | B5: Benzyl butyl phthalate | C5: 85-68-7 | D5: 312.3 | E5: 4.91 | F5: phthalate_dehp_eq | G5: 0.1 | H5: piringer | K5: 1 | L5: VERIFIED | M5: S14;S08 | N5: Not detected in microwaved PP containers [S05]; kept for completeness.
A6: SB | B6: Antimony (catalyst residue in PET) | C6: 7440-36-0 | D6: 121.76 | F6: antimony | G6: 1 | H6: arrhenius | I6: 360000000000000 | J6: 188 | K6: 0.62 | L6: VERIFIED (D0, Ea, diffusible fraction) | M6: S02 | N6: Fitted by Haldimann 2013 on CPET at 120-150 C; use at 100-125 C is a short extrapolation. Piringer is not designed for metal species.
A7: I168 | B7: Irgafos 168 (phosphite antioxidant in PP) | C7: 31570-04-4 | D7: 646.94 | E7: 15.5 | F7: antioxidant_i168 | G7: 1 | H7: piringer | K7: 1 | L7: MW SECONDARY; log Kow ESTIMATED (XlogP3-AA 15.5) | M7: S53;S54;S80 | N7: No measured log Kow exists for this very hydrophobic additive. The engine caps log Kow at the highest value measured in the partition data for the food's EtOH-eq band, so the estimate only matters for fatty foods. The FDA ADI also covers its oxidised phosphate.
A9: Antimony D(100 C) from Haldimann 2013 Arrhenius fit (cm2/s): | I9: =I6*EXP(-J6*1000/(8.314462618*373.15)) -> 1.7378834e-12

Sheet Groups
A1: Key | B1: Label (en) | C1: Label (ko) | D1: TDI | E1: Unit | F1: Agency | G1: Year | H1: Daily allowance, 70 kg adult (ug) | I1: Status | J1: Sources | K1: Basis
A2: phthalate_dehp_eq | B2: Phthalates | C2: 프탈레이트(DEHP 당량) | D2: 50 | E2: ug/kg bw/day | F2: EFSA | G2: 2019 | H2: =D2*70 -> 3500 | I2: VERIFIED | J2: S07;S08 | K2: Group TDI, reduction in fetal testosterone; DEHP-eq = 1 DEHP + 5 DBP + 4 DIBP + 0.1 BBP (Reg. 2023/1442 group 36). Temporary TDI.
A3: antimony | B3: Antimony | C3: 안티모니 | D3: 6 | E3: ug/kg bw/day | F3: WHO | G3: 2003 | H3: =D3*70 -> 420 | I3: VERIFIED | J3: S09 | K3: NOAEL 6.0 mg/kg bw/day (90-day rat study) / UF 1000.
A4: antioxidant_i168 | B4: Irgafos 168 (antioxidant) | C4: 산화방지제 Irgafos 168 | D4: 1000 | E4: ug/kg bw/day (ADI) | F4: US FDA | G4: 2021 | H4: =D4*70 -> 70000 | I4: VERIFIED | J4: S53 | K4: NOEL 2000 ppm in a 2-year rat study, safety factor 100; covers Irgafos 168 and its phosphate.
A5: lead | B5: Lead | C5: 납(EFSA 기준점) | D5: 0.5 | E5: ug/kg bw/day (BMDL01) | F5: EFSA | G5: 2010 | H5: =D5*70 -> 35 | I5: VERIFIED | J5: S52 | K5: No safe intake exists for lead, so EFSA withdrew the tolerable weekly intake and uses a benchmark dose (developmental neurotoxicity in children, BMDL01). The % shown is of this reference point, not of a safe limit.

Sheet Alt_References
A1: Substance | B1: Agency | C1: Value | D1: Unit | E1: Year | F1: Status | G1: Sources
A2: DEHP | B2: US EPA IRIS | C2: 20 | D2: ug/kg bw/day (oral RfD) | E2: 1987 | F2: VERIFIED | G2: S10
A3: DBP | B3: EFSA | C3: 10 | D3: ug/kg bw/day (individual t-TDI) | E3: 2019 | F3: VERIFIED | G3: S07
A4: BBP | B4: EFSA | C4: 500 | D4: ug/kg bw/day (individual t-TDI) | E4: 2019 | F4: VERIFIED | G4: S07
A5: DINP | B5: EFSA | C5: 150 | D5: ug/kg bw/day (individual t-TDI) | E5: 2019 | F5: VERIFIED | G5: S07
A6: BPA | B6: EFSA | C6: 0.0002 | D6: ug/kg bw/day (0.2 ng/kg bw/day) | E6: 2023 | F6: VERIFIED | G6: S12

Sheet Contents
A1: Material | B1: Substance | C1: Low (mg/kg) | D1: High (mg/kg) | E1: Central (mg/kg) | F1: Distribution | G1: Status | H1: Sources | I1: Note
A2: PP | B2: DBP | C2: 0 | D2: 2.83 | E2: =(C2+D2)/2 -> 1.415 | F2: uniform | G2: VERIFIED (range of reported values) | H2: S03;S04 | I2: Liu 2020 1.39-2.83 mg/kg; Lan 2022 ND-0.995 mg/kg (unit printed mg/g in abstract, read as ug/g). Not an intended PP additive.
A3: PP | B3: DIBP | C3: 0.237 | D3: 1.84 | E3: =(C3+D3)/2 -> 1.0385 | F3: uniform | G3: VERIFIED (range of reported values) | H3: S03;S04 | I3: Lan 2022 0.237-1.676 (100% detected); Liu 2020 0.53-1.84 mg/kg.
A4: PP | B4: DEHP | C4: 0 | D4: 2.302 | E4: =(C4+D4)/2 -> 1.151 | F4: uniform | G4: VERIFIED (unit UNVERIFIED) | H4: S04 | I4: Lan 2022 ND-2.302, detection rate 78%.
A5: CPET | B5: SB | C5: 100 | D5: 400 | E5: =(C5+D5)/2 -> 250 | F5: uniform | G5: VERIFIED | H5: S06;S02 | I5: PET range 100-400 mg/kg (review). The one CPET tray measured by Haldimann 2013 had 290-318 mg/kg, inside this range.
A6: PET_COAT | B6: SB | C6: 100 | D6: 400 | E6: =(C6+D6)/2 -> 250 | F6: uniform | G6: ASSUMPTION | H6: S06 | I6: No measurement for PET-coated board; the PET range is applied to the coating layer.
A7: PP | B7: I168 | C7: 166.47 | D7: 845.27 | E7: =(C7+D7)/2 -> 505.87 | F7: uniform | G7: VERIFIED for PP films; ASSUMPTION for rigid PP | H7: S54 | I7: Six PP food packaging films. Rigid PP containers also carry phosphite antioxidants; no rigid-container value was found.
A8: PP_FILM | B8: I168 | C8: 166.47 | D8: 845.27 | E8: =(C8+D8)/2 -> 505.87 | F8: uniform | G8: VERIFIED | H8: S54 | I8: PP film sealant layer of steam bags and pouches.

Sheet Measured
A1: Container | B1: Substance | C1: Group | D1: Low | E1: Middle | F1: High | G1: Unit | H1: Basis | I1: Conditions | J1: Status | K1: Sources
A2: paper_cup | B2: Lead (Pb) | C2: lead | D2: 0.583 | E2: 1.38 | F2: 22.9 | G2: ug/kg | H2: per_kg_food | I2: 20 PE-lined paper cups, 200 mL ultrapure water at 95-100 C, 15 min. Value per litre of water applied per kg of soup or noodles. | J2: VERIFIED | K2: S51
A4: Used when a container has status measured: intake = value x food mass (per_kg_food) or value (per_item); range = low to high.

Sheet Containers
A1: Key | B1: Label (en) | C1: Label (ko) | D1: Status | E1: Content key | F1: Polymer | G1: Density (g/cm3) | H1: Thickness (cm) | I1: Thickness low | J1: Thickness high | K1: Contact area at 300 g (cm2) | L1: Form | M1: Max use (C) | N1: Max use (F) | O1: Reason (en) | P1: Reason (ko) | Q1: Sources | R1: Notes | S1: Contact mode
A2: cpet_tray | B2: Black oven tray (#1) | C2: 검은 오븐 겸용 트레이(CPET) | D2: ok | E2: CPET | F2: PET_HI | G2: 1.35 | H2: 0.031 | I2: 0.025 | J2: 0.06 | K2: 290 | L2: tray | M2: 204 | N2: =IF(M2="","",M2*9/5+32) -> 399.2 | Q2: S02;S16;S17 | R2: Thickness and density of the tray measured by Haldimann 2013. Max use 400 F (Sabert). | S2: wall
A3: pp_container | B3: Microwave-safe plastic (#5) | C3: 전자레인지용 플라스틱 용기(PP 5번) | D3: ok | E3: PP | F3: PP | G3: 0.9 | H3: 0.05 | I3: 0.03 | J3: 0.06 | K3: 250 | L3: bowl | M3: 104 | N3: =IF(M3="","",M3*9/5+32) -> 219.2 | Q3: S18;S19 | R3: Thickness 0.3-0.6 mm is UNVERIFIED; measure with calipers. Max use 220 F per Inline Plastics 2023 (240 F in 2020 catalog). | S3: wall
A4: pet_board_tray | B4: Coated paper tray | C4: PET 코팅 종이 트레이(오븐 겸용) | D4: ok | E4: PET_COAT | F4: PET_HI | G4: 1.35 | H4: 0.0029 | I4: 0.002 | J4: 0.004 | K4: 290 | L4: tray | M4: 220 | N4: =IF(M4="","",M4*9/5+32) -> 428 | Q4: S60;S06 | R4: PET coating 40 g/m2, about 29 um, usable to 220 C (Holmen). Ovenable paperboard trays carry a PET coating; antimony content of the coating is assumed equal to PET (ASSUMPTION). | S4: wall
A5: paperboard_tray | B5: Paper plate or fiber tray | C5: 종이·압착 섬유 트레이(코팅 미확인) | D5: info | K5: 290 | L5: tray | M5: 204 | N5: =IF(M5="","",M5*9/5+32) -> 399.2 | O5: The old worry was PFAS coatings, which US food packaging dropped in 2024. | P5: 코팅 없는 종이·섬유 트레이의 주요 우려 물질은 기름 방지용 PFAS였다. 미국에서는 2024년 2월부터 PFAS 기름 방지제가 식품 포장용으로 팔리지 않고, 캘리포니아는 총 유기 플루오린을 100 ppm 미만으로 제한한다. 현재 미국 제품에는 없어야 하므로 숫자는 보여 주지 않는다. | Q5: S63;S75;S62 | R5: Detail: The main chemical concern for uncoated or fibre trays was PFAS grease-proofing. PFAS grease-proofing agents are no longer sold for US food packaging (FDA, Feb 2024) and California limits total organic fluorine to 100 ppm. No number is shown because current US trays should not contain them. If the tray is marked PET or dual-ovenable, use pet_board_tray. | S5: wall
A6: paper_cup | B6: Paper cup or bowl | C6: 종이 컵·그릇(PE 코팅) | D6: measured | F6: LDPE | G6: 0.92 | H6: 0.00163 | K6: 210 | L6: cup | M6: 70 | N6: =IF(M6="","",M6*9/5+32) -> 158 | O6: It's lined with a thin plastic film. Lab tests found traces of lead in hot water from these cups. | P6: 측정값 기반 추정이다. PE 코팅 종이컵 20종에 끓는 물을 붓고 15분 둔 실험에서 납이 나왔다(중앙값 1.38, 범위 0.58~22.9 µg/L). | Q6: S51;S52;S59 | R6: Detail: Estimated from measured migration: 20 PE-lined paper cups filled with near-boiling water for 15 min released lead (median 1.38, range 0.58-22.9 ug/L). PE coating 15 g/m2 (about 16 um). No additive content of the PE layer itself was found, so the diffusion model is not used. Fast-food paper cups showed no fluorine (PFAS) in a US survey. | S6: wall
A7: steam_bag | B7: Steam bag | C7: 스팀 백(PP 실런트 필름) | D7: ok | E7: PP_FILM | F7: PP | G7: 0.9 | H7: 0.0064 | I7: 0.0032 | J7: 0.0095 | K7: 400 | L7: bag | M7: 120 | N7: =IF(M7="","",M7*9/5+32) -> 248 | Q7: S55;S54 | R7: Patent structure PET 12 um / adhesive / PE or PP skin / PP core 19-63.5 um / PP-PE sealant 12.7-31.8 um (food side). PP layers on the food side total 32-95 um. Patent bag of frozen vegetables reached 95-102 C in 4 min. | S7: steam
A8: pouch | B8: Microwave pouch | C8: 전자레인지 파우치(CPP 실런트) | D8: ok | E8: PP_FILM | F8: PP | G8: 0.9 | H8: 0.0075 | I8: 0.006 | J8: 0.00875 | K8: 300 | L8: bag | M8: 120 | N8: =IF(M8="","",M8*9/5+32) -> 248 | Q8: S56;S57;S54;S58 | R8: Microwavable retort pouches use PET (often AlOx or SiOx coated) / nylon / CPP 60-87.5 um on the food side. Retorted pouches were already heated to 121-135 C in the factory; a study found 4,4'-MDA (aromatic amine from adhesive) at 2.7-3.1 ug/kg after retort in two brands, above the EU 2 ug/kg limit. | S8: wall
A9: takeout_tub | B9: Take-out tub | C9: 배달·마가린 용기 | D9: block | E9: PP | F9: PP | G9: 0.9 | H9: 0.05 | I9: 0.03 | J9: 0.06 | K9: 250 | L9: bowl | M9: 104 | N9: =IF(M9="","",M9*9/5+32) -> 219.2 | O9: Not made for heat. It can warp or melt. | P9: FSIS는 배달 용기와 마가린 통이 전자레인지에서 휘거나 녹을 수 있다고 안내한다. | Q9: S22 | R9: Detail: FSIS says take-out and margarine tubs can warp or melt in the microwave. | S9: wall
A10: pet_clamshell | B10: Clear clamshell (#1) | C10: 투명 뚜껑 일체형 용기(PET 1번) | D10: block | F10: PET_LO | G10: 1.33 | K10: 250 | L10: tray | M10: 60 | N10: =IF(M10="","",M10*9/5+32) -> 140 | O10: It softens around 150°F, cooler than reheated food. | P10: APET는 65~69 °C 부근에서 물러지므로 재가열 온도를 견디지 못한다. | Q10: S20;S19 | S10: wall
A11: eps_foam | B11: Foam tray or cup | C11: 스티로폼 용기(EPS) | D11: block | F11: PS | K11: 250 | L11: tray | M11: 70 | N11: =IF(M11="","",M11*9/5+32) -> 158 | O11: Not made for heat. It can warp or melt. | P11: FSIS는 스티로폼 트레이가 고온에서 안정하지 않으므로 쓰지 말라고 안내한다. | Q11: S22;S01 | R11: Piringer PS parameters are valid only up to 70 C. | S11: wall
A12: ps_rigid | B12: Clear hard plastic (#6) | C12: 투명 PS 용기(6번) | D12: block | F12: PS | G12: 1.05 | K12: 250 | L12: tray | M12: 77 | N12: =IF(M12="","",M12*9/5+32) -> 170.6 | O12: It's only made for up to 170°F. Reheated food gets hotter. | P12: OPS의 사용 온도 상한은 170 °F(77 °C)이다. | Q12: S19 | S12: wall
A13: metal | B13: Metal or foil | C13: 금속·호일 용기 | D13: block | L13: tray | N13: =IF(M13="","",M13*9/5+32) | O13: Metal can spark in the microwave. | P13: 금속은 전자레인지에서 불꽃이 튈 수 있다. 접시에 옮겨 담는다. | Q13: S44;S45 | R13: Detail: Metal can spark in a microwave. Move the food to a plate. | S13: wall
A14: melamine | B14: Melamine or bamboo dish | C14: 멜라민·대나무 섬유 식기 | D14: block | L14: bowl | N14: =IF(M14="","",M14*9/5+32) | O14: Not for hot food or the microwave. Heat can make it release chemicals. | P14: 대나무 섬유 식기는 멜라민-폼알데하이드 수지에 대나무 섬유를 섞은 것이다. 뜨거운 음식으로 멜라민과 폼알데하이드가 나올 수 있어 BfR은 전자레인지 가열에 쓰지 말라고 권고한다 [S82]. 접시에 옮겨 담는다. | Q14: S82 | R14: Detail: 'Bamboo' tableware is melamine-formaldehyde resin with bamboo fibre; hot food can draw melamine and formaldehyde out of it, and BfR advises against heating food in it in the microwave [S82]. Move the food to a plate. Added after a bamboo-fibre bowl turned up in the store photos (2026-10-14). | S14: wall
A15: glass | B15: Glass dish | C15: 유리 그릇 | D15: inert | L15: bowl | N15: =IF(M15="","",M15*9/5+32) | O15: No plastic touches your food. | P15: 음식이 플라스틱에 닿지 않는다. | Q15: S22 | R15: FSIS: use cookware made for microwave use. | S15: wall
A16: ceramic | B16: Plate or bowl | C16: 도자기 접시·그릇 | D16: inert | L16: plate | N16: =IF(M16="","",M16*9/5+32) | O16: No plastic touches your food. Skip plates with gold or silver trim. | P16: 음식이 플라스틱에 닿지 않는다. 금테 접시는 피한다. | Q16: S22;S44 | S16: wall
A17: stove_pot | B17: Pot on the stove | C17: 냄비(가스레인지) | D17: inert | L17: pot | N17: =IF(M17="","",M17*9/5+32) | O17: The food comes out of the package, so no plastic gets heated. | P17: 가열 전에 음식을 포장에서 꺼낸다. | S17: wall
A18: popcorn_bag | B18: Popcorn bag | C18: 전자레인지 팝콘 봉투 | D18: info | L18: bag | N18: =IF(M18="","",M18*9/5+32) | O18: US popcorn bags no longer use PFAS coatings. | P18: 예전 팝콘 봉투에는 기름 방지용 PFAS가 쓰였다. FDA 연구에서 봉투 속 PFOA가 6~290 µg/kg이었고, 튀긴 뒤 기름에서 플루오로텔로머 코팅 물질이 2.1 mg/kg 나왔다. Conagra는 2022년 Act II 봉투에서 PFAS를 뺐다고 밝혔고, 미국에서는 2024년부터 PFAS 기름 방지제가 팔리지 않는다. 현재 봉투에는 숫자를 보여 주지 않는다. | Q18: S64;S65;S63 | R18: Detail: Older popcorn bags used PFAS grease-proofing: an FDA study found PFOA at 6-290 ug/kg in bags and a fluorotelomer coating chemical at 2.1 mg/kg in oil after popping. Conagra says it removed PFAS from Act II bags in 2022, and PFAS grease-proofing agents are no longer sold in the US (2024). No number is shown for current bags. Susceptor (metallised PET) reaches over 200 C; models for 100 C do not apply. | S18: wall
A19: susceptor_sleeve | B19: Crisping sleeve | C19: 크리스핑 슬리브(서셉터) | D19: info | L19: sleeve | N19: =IF(M19="","",M19*9/5+32) | O19: These get much hotter than boiling, so I can't estimate them. | P19: Hot Pockets는 2024년에 크리스핑 슬리브를 없앴다. 1992년 영국 연구에서 서셉터 위에서 조리한 피자에서 에폭시 접착제 성분 BADGE가 0.1~0.7 mg/kg 나왔다. 서셉터는 100 °C보다 훨씬 뜨거워지므로 앱은 이를 모델로 계산하지 않는다. | Q19: S66;S67 | R19: Detail: Hot Pockets removed crisping sleeves in 2024. A 1992 UK study found the epoxy adhesive component BADGE at 0.1-0.7 mg/kg in pizza cooked on susceptors. Susceptors run far hotter than 100 C, so the app does not model them. BADGE TDI 0.15 mg/kg bw/day (EFSA 2004) is UNVERIFIED in this build, so no percentage is computed. | S19: wall

Sheet FoodClasses
A1: Class | B1: Fat fraction min | C1: Fat fraction max | D1: Partition rule | E1: EtOH-eq low (%) | F1: EtOH-eq high (%) | G1: Contact T cap low (C) | H1: Contact T cap high (C) | I1: Status | J1: Sources | K1: Note
A2: lean | B2: 0 | C2: 0.03 | D2: EtOH-eq uniform 10-60 %; log Kpf from the Huang and Jolliet 2019 regression | E2: 10 | F2: 60 | G2: 100 | H2: 100 | I2: ASSUMPTION (EtOH-eq range anchored to simulant A and dataset assignments) | J2: S81;S76 | K2: Watery foods. EU simulant A (10 % ethanol) for aqueous food; the partition dataset assigns fruit juices 40 % and milk with 1.5-3 % fat 60 %. Contact temperature capped at boiling.
A3: medium | B3: 0.03 | C3: 0.1 | D3: EtOH-eq uniform 50-80 %; log Kpf from the Huang and Jolliet 2019 regression | E3: 50 | F3: 80 | G3: 100 | H3: 110 | I3: ASSUMPTION | J3: S81;S76;S28 | K3: Sauces, cheese, emulsions. EU simulant D1 (50 % ethanol) covers oil-in-water emulsions and dairy; the upper end allows for free fat in cheese sauces.
A4: fatty | B4: 0.1 | C4: 1 | D4: EtOH-eq uniform 80-100 %; log Kpf from the Huang and Jolliet 2019 regression | E4: 80 | F4: 100 | G4: 105 | H4: 125 | I4: ASSUMPTION (EtOH-eq anchored to the 95 % ethanol substitute for oil) | J4: S81;S76;S29;S30 | K4: Fat-rich foods. EU rules accept 95 % ethanol as a substitute test for vegetable oil (D2). Fat-rich foods heat faster than water and oil can pass 100 C; HK CFS tested fatty food at 120 C.
A6: EtOH-eq is the ethanol share (v/v) of a water-ethanol mixture that dissolves migrants like the food does. It feeds the partition regression on the KpfModel sheet [S76, S77]. Antimony (inorganic) uses K = 1 [S01].

Sheet KpfModel
A1: Coefficient | B1: Value | C1: Term
A2: b0 | B2: -1.36 | C2: Intercept
A3: b_kow | B3: 1.06 | C3: log Kow
A4: b_etoh | B4: -0.014 | C4: EtOH-eq (%)
A5: b_kow_etoh | B5: -0.0066 | C5: log Kow x EtOH-eq
A6: b_invt | B6: 866 | C6: (1/T - 1/298.15), T in K
A8: Material offsets (log10 units)
A9: Material | B9: Offset
A10: Average HDPE/LDPE | B10: 0.15
A11: Carbohydrates | B11: -0.55
A12: Ethylene-propylene copolymer | B12: -0.11
A13: Ethylene-vinyl acetate copolymer (EVA) | B13: 0.58
A14: High-density polyethylene (HDPE) | B14: 0.035
A15: Ionomer (Surlyn 1652, 1702) | B15: -0.027
A16: Linear low-density polyethylene (LLDPE) | B16: -1.21
A17: Low-density polyethylene (LDPE) | B17: 0
A18: Nylon 6 | B18: -0.92
A19: Poly 2-hydroxyethylmethacrylate | B19: 0.39
A20: Polycaprolactone related polymers | B20: 0.85
A21: Polydimethylsiloxane (PDMS) | B21: 0.01
... A28: Starch, Cellulose | B28: -1.83
A30: Applicability domain: highest measured log Kow per EtOH-eq band (the engine caps log Kow here)
A31: EtOH-eq from (%) | B31: EtOH-eq to (%) | C31: log Kow min | D31: log Kow max | E31: Rows
A32: 0 | B32: 20 | C32: 0.38 | D32: 8.91 | E32: 881
A33: 20 | B33: 60 | C33: 0.35 | D33: 10.16 | E33: 421
A34: 60 | B34: 90 | C34: 1.36 | D34: 11.15 | E34: 263
A35: 90 | B35: 100 | C35: 0.32 | D35: 18.104941 | E35: 316
A37: Example: DEHP (log Kow 7.5) in PP homopolymer, lean food (EtOH-eq 35 %), 100 C
A38: log10 Kpf | B38: =B2+B3*7.5+B4*35+B5*7.5*35+B6*(1/373.15-1/298.15)+INDEX(B10:B28,MATCH("Polypropylene (PP) homopolymer",A10:A28,0)) -> 3.2837043
A39: Old rule (v0.2) used log10 K = 3 for every lipophilic migrant in lean food.
A41: log10 Kpf = b0 + b_kow*logKow + b_etoh*EtOH + b_kow_etoh*logKow*EtOH + b_invt*(1/T - 1/298.15) + material offset
A42: Kpf = concentration in polymer / concentration in food (volume basis); EtOH in % v/v; T in K
A43: Residual SD 0.79 log10 units. RMSE of the refitted regression when each chemical is held out (GroupKFold by CAS); whole-study hold-out gives 1.11. Sources S76, S79.

Sheet ModelParams
A1: Key | B1: Value | C1: Unit | D1: Status | E1: Sources | F1: Note
A2: T0_frozen_C | B2: -18 | C2: C | D2: ASSUMPTION | F2: Home freezer temperature (0 F).
A3: T0_chilled_C | B3: 4 | C3: C | D3: ASSUMPTION | F3: Refrigerator temperature (40 F).
A4: T0_shelf_C | B4: 20 | C4: C | D4: ASSUMPTION | F4: Room temperature for shelf-stable cups, bowls and pouches.
A5: water_fraction | B5: 0.75 | C5: g/g | D5: UNVERIFIED | F5: Typical frozen meal water content 70-80 %; replace per product with USDA FoodData Central values.
A6: c_water | B6: 4.187 | C6: J/(g K) | D6: VERIFIED | E6: S27 | F6: Specific heat of liquid water.
A7: c_solids | B7: 1.8 | C7: J/(g K) | D7: UNVERIFIED | F7: Specific heat of food solids (protein, fat, carbohydrate are roughly 1.5-2.0).
A8: c_frozen | B8: 2.05 | C8: J/(g K) | D8: VERIFIED (illustrative) | E8: S27 | F8: Frozen food heat capacity used in the worked example of S27.
A9: latent_heat_water | B9: 333.57 | C9: J/g | D9: VERIFIED | E9: S27 | F9: Latent heat of fusion of water; multiplied by water_fraction.
A10: T_target_avg_C | B10: 85 | C10: C | D10: ASSUMPTION | E10: S22 | F10: Average food temperature reached when the label recipe ends. FSIS requires at least 165 F (74 C) at the coldest point, so the average is set above it.
A11: T_boil_C | B11: 100 | C11: C | D11: VERIFIED | E11: S31 | F11: Watery food cannot pass 100 C at 1 atm.
A12: edge_excess_C | B12: 15 | C12: C | D12: ASSUMPTION | E12: S28 | F12: Food next to the container wall is hotter than the average. Jung 2022 saw edges at 100 C while the rest stayed below 80 C.
A13: edge_excess_low_C | B13: 10 | C13: C | D13: ASSUMPTION | E13: S28 | F13: Monte Carlo lower bound.
A14: edge_excess_high_C | B14: 20 | C14: C | D14: ASSUMPTION | E14: S28 | F14: Monte Carlo upper bound.
A15: power_factor_low | B15: 0.85 | C15: - | D15: VERIFIED | E15: S26 | F15: Real output of a rated oven, lower bound (about -15 %).
A16: power_factor_high | B16: 1.15 | C16: - | D16: VERIFIED | E16: S26 | F16: Upper bound (+15 %).
A17: area_factor_low | B17: 0.8 | C17: - | D17: ASSUMPTION | F17: Contact area uncertainty.
A18: area_factor_high | B18: 1.2 | C18: - | D18: ASSUMPTION | F18: Contact area uncertainty.
A19: area_ref_mass_g | B19: 300 | C19: g | D19: ASSUMPTION | F19: Reference food mass for the container area values; area scales with (mass/300)^(2/3).
A20: food_density | B20: 1 | C20: g/cm3 | D20: ASSUMPTION | E20: S27 | F20: S27 uses 1.05 in its example.
A21: default_ref_watt | B21: 1100 | C21: W | D21: ASSUMPTION | E21: S25 | F21: Used when a label gives times without a wattage; 13 of 15 seed labels with a single reference use 1100 W.
A22: eat_minutes | B22: 10 | C22: min | D22: ASSUMPTION | F22: Time the food sits in the container while being eaten.
A23: eat_end_C | B23: 50 | C23: C | D23: ASSUMPTION | F23: Food temperature at the end of eating.
A24: dt_s | B24: 1 | C24: s | D24: ASSUMPTION | F24: Time step of the temperature-diffusion integration.
A25: short_time_Fo | B25: 0.05 | C25: - | D25: ASSUMPTION | E25: S01 | F25: Below this Fourier number the semi-infinite (short-time) Crank solution is used.
A26: mc_samples | B26: 300 | C26: - | D26: ASSUMPTION | F26: Monte Carlo samples per evaluation.
A27: mc_seed | B27: 20261026 | C27: - | D27: ASSUMPTION | F27: Fixed seed so results are reproducible.
A28: band_low_pct | B28: 2 | C28: % TDI | D28: DERIVED | E28: S08 | F28: Below this the meal uses under one tenth of the 20 % of the TDI that EU rules allocate to food contact materials.
A29: band_high_pct | B29: 10 | C29: % TDI | D29: DERIVED | E29: S08 | F29: At or above this one meal uses half of the 20 % allocation.
A30: daily_alert_pct | B30: 20 | C30: % TDI | D30: DERIVED | E30: S08 | F30: Daily packaging share equal to the EU allocation factor (20 % of the TDI).
A31: steam_onset_fraction | B31: 0.6 | C31: - | D31: ASSUMPTION | E31: S55 | F31: Steam bags: once this share of the label energy is delivered, the film sits in steam at 100 C. A patent steam bag reached 95-102 C after 4 min of a 5-6 min cook; the generic wall model gave only 46 C (validation V6).
A32: energy_short_ratio | B32: 0.95 | C32: - | D32: ASSUMPTION | E32: S22 | F32: Below 95 % of the label energy the app warns the food may not reach 165 F.
A33: R_gas | B33: 8.3144626 | C33: J/(mol K) | D33: VERIFIED | F33: Gas constant (CODATA).
A34: d_weight_central | B34: 0.5 | C34: - | D34: ASSUMPTION | E34: S78;S01 | F34: Position between the realistic diffusion coefficient (Huang 2017 QPPR, 0) and the regulatory upper bound (Piringer, 1) on a log scale. 0.5 is the log midpoint.
A35: d_weight_low | B35: 0 | C35: - | D35: ASSUMPTION | E35: S78 | F35: Monte Carlo lower end: Huang 2017 QPPR value.
A36: d_weight_high | B36: 1 | C36: - | D36: ASSUMPTION | E36: S01 | F36: Monte Carlo upper end: Piringer upper bound.
A37: kpf_resid_sd | B37: 0.79 | C37: log10 | D37: DERIVED | E37: S76 | F37: Prediction error of the partition regression when each chemical is held out (ml/train_kpf.py, GroupKFold by CAS). Monte Carlo adds a normal error with this SD.
A38: kpf_t_ref_K | B38: 298.15 | C38: K | D38: VERIFIED | E38: S76 | F38: Reference temperature of the partition regression.

Sheet BodyWeights
A1: Group | B1: Body weight (kg) | C1: Status | D1: Sources | E1: Note
A2: adult | B2: 70 | C2: VERIFIED | D2: S11 | E2: EFSA default adult body weight.
A3: adult_eu_fcm | B3: 60 | C3: VERIFIED | D3: S31 | E3: Convention behind EU specific migration limits (60 kg eating 1 kg food).
A4: teen | B4: 55 | C4: ASSUMPTION | E4: Placeholder for ages 13-17; the user should enter real weight.
A5: child | B5: 30 | C5: ASSUMPTION | E5: Placeholder for ages 8-12; the user should enter real weight.
A6: toddler | B6: 12 | C6: VERIFIED | D6: S11 | E6: EFSA default toddler body weight.

Sheet Products
A1: ID | B1: Brand | C1: Product | D1: UPC | E1: Category | F1: Net (oz) | G1: Net (g, label) | H1: Net (g) | I1: Servings | J1: Serving (g) | K1: Fat per serving (g) | L1: Added water (g) | M1: Food mass (g) | N1: Fat fraction | O1: Fat class | P1: Storage | Q1: Container key | R1: Container confidence | S1: Container note | T1: Reference watt | U1: Instructions | V1: Do not microwave | W1: Low-watt note | X1: Do-not statements | Y1: Oven directions | Z1: Container description | AA1: Data flags | AB1: Source URLs
A2: zw-001 | B2: Banquet | C2: Mega Bowls Mike's Hot Honey Chicken Mac 'N Cheese | D2: 031000008550 | E2: frozen_tray | F2: 13.8 | G2: 392 | H2: =IF(G2<>"",G2,IF(F2<>"",ROUND(F2*28.3495,0),"")) -> 392 | I2: 1 | J2: 392 | K2: 25 | L2: 0 | M2: =IF(H2="","",H2+L2) -> 392 | N2: =IF(OR(K2="",M2=""),"",IF(J2<>"",K2/J2*H2/M2,IF(I2<>"",K2*I2/M2,""))) -> 0.06377551 | O2: =IF(N2="","",IF(N2<FoodClasses!$C$2,"lean",IF(N2<FoodClasses!$C$3,"medium","fatty"))) -> medium | P2: frozen | Q2: cpet_tray | R2: inferred | S2: Same tray goes into a 375 F oven, which plastic other than CPET does not survive. | T2: 1100 | U2: complete | V2: no | W2: None given. Label says appliances vary and to adjust times. | X2: Do not prepare in toaster oven | Cook only one at a time | Keep frozen, do not thaw | Y2: 375°F, vent film, on baking sheet 45 min, stand 2 min, stir. | Z2: Film-covered bowl tray; same tray is used in the 375°F oven per the directions. Material not stated. | AB2: https://smartlabel.labelinsight.com/product/18609278/other/instructions https://smartlabel.labelinsight.com/product/18609278/nutrition
A3: zw-002 | B3: Healthy Choice | C3: Lemon Parmesan Chicken | D3: 072655003217 | E3: frozen_tray | F3: 11 | G3: 311 | H3: =IF(G3<>"",G3,IF(F3<>"",ROUND(F3*28.3495,0),"")) -> 311 | L3: 0 | M3: =IF(H3="","",H3+L3) -> 311 | N3: =IF(OR(K3="",M3=""),"",IF(J3<>"",K3/J3*H3/M3,IF(I3<>"",K3*I3/M3,""))) | O3: =IF(N3="","",IF(N3<FoodClasses!$C$2,"lean",IF(N3<FoodClasses!$C$3,"medium","fatty"))) | P3: frozen | Q3: pp_container | R3: unknown | S3: Material not stated; confirm by photo (black = CPET, clear or white = PP). | T3: 1100 | U3: complete | V3: no | W3: None given. Label says to adjust times for your appliance. | X3: Cook only one at a time | Keep frozen, do not thaw | Z3: Film-covered tray (film is lifted and replaced mid-cook). Material not stated. | AA3: nutrition page returned a server error on two attempts | AB3: https://smartlabel.labelinsight.com/product/18859044/other/instructions
A4: zw-003 | B4: Marie Callender's | C4: Cajun Style Chicken Alfredo Bowl | D4: 021131000226 | E4: frozen_tray | F4: 11 | G4: 312 | H4: =IF(G4<>"",G4,IF(F4<>"",ROUND(F4*28.3495,0),"")) -> 312 | I4: 1 | J4: 312 | K4: 16 | L4: 0 | M4: =IF(H4="","",H4+L4) -> 312 | N4: =IF(OR(K4="",M4=""),"",IF(J4<>"",K4/J4*H4/M4,IF(I4<>"",K4*I4/M4,""))) -> 0.051282051 | O4: =IF(N4="","",IF(N4<FoodClasses!$C$2,"lean",IF(N4<FoodClasses!$C$3,"medium","fatty"))) -> medium | P4: frozen | Q4: cpet_tray | R4: inferred | S4: Oven-safe at 375 F with film on. | T4: 1100 | U4: complete | V4: no | W4: None given. | X4: Do not prepare in toaster oven | Do not remove film before oven cooking | Cook only one at a time | Keep frozen, do not thaw | Y4: 375°F, leave film on, on baking sheet 50 min, stand 2 min, stir. | Z4: Film-covered bowl tray; oven-safe per directions (baked at 375°F with film on). Material not stated. | AA4: no microwave stand time listed on label | AB4: https://smartlabel.labelinsight.com/product/15972825/other/instructions https://smartlabel.labelinsight.com/product/15972825/nutrition
A5: zw-004 | B5: Marie Callender's | C5: Fettuccini With Chicken & Broccoli Dinner | D5: 021131504755 | E5: frozen_tray | F5: 13 | G5: 369 | H5: =IF(G5<>"",G5,IF(F5<>"",ROUND(F5*28.3495,0),"")) -> 369 | I5: 1 | J5: 369 | K5: 18 | L5: 0 | M5: =IF(H5="","",H5+L5) -> 369 | N5: =IF(OR(K5="",M5=""),"",IF(J5<>"",K5/J5*H5/M5,IF(I5<>"",K5*I5/M5,""))) -> 0.048780488 | O5: =IF(N5="","",IF(N5<FoodClasses!$C$2,"lean",IF(N5<FoodClasses!$C$3,"medium","fatty"))) -> medium | P5: frozen | Q5: cpet_tray | R5: inferred | S5: Oven directions use the same tray at 350 F. | T5: 1100 | U5: complete | V5: no | W5: None given. | X5: Do not prepare in toaster oven | Cook only one at a time | Keep frozen, do not thaw | Y5: 350°F, vent film corner, on baking sheet 45-48 min, stand 2 min, stir. | Z5: Film-sealed tray with vent corner marked 'Push here to open'. Material not stated. | AB5: https://smartlabel.labelinsight.com/product/6903342/other/instructions https://smartlabel.labelinsight.com/product/6903342/nutrition
A6: zw-005 | B6: Stouffer's | C6: Classic Meatloaf | E6: frozen_tray | F6: 16 | H6: =IF(G6<>"",G6,IF(F6<>"",ROUND(F6*28.3495,0),"")) -> 454 | I6: 2 | J6: 226 | K6: 9 | L6: 0 | M6: =IF(H6="","",H6+L6) -> 454 | N6: =IF(OR(K6="",M6=""),"",IF(J6<>"",K6/J6*H6/M6,IF(I6<>"",K6*I6/M6,""))) -> 0.039823009 | O6: =IF(N6="","",IF(N6<FoodClasses!$C$2,"lean",IF(N6<FoodClasses!$C$3,"medium","fatty"))) -> medium | P6: frozen | Q6: pp_container | R6: unknown | S6: Stouffer's uses both plastic trays (no black pigment) and pressed paper trays; microwave-only label; confirm by photo [S68]. | T6: 1100 | U6: complete | V6: no | W6: None given. | X6: Do not reheat tray | Do not prepare in toaster oven | Z6: Film-covered tray; label says not to reheat the tray. Material not stated. | AA6: retailer copy of label; directions may be abridged (no mid-cook stir step shown) | UPC not shown | AB6: https://www.safeway.com/shop/pd/stouffers-classic-meatloaf-frozen-meal-16-oz/960010754
A7: zw-006 | B7: Stouffer's | C7: Macaroni & Cheese (single serve) | D7: 00013800103406 | E7: frozen_tray | F7: 12 | G7: 340 | H7: =IF(G7<>"",G7,IF(F7<>"",ROUND(F7*28.3495,0),"")) -> 340 | I7: 1 | J7: 340 | K7: 21 | L7: 0 | M7: =IF(H7="","",H7+L7) -> 340 | N7: =IF(OR(K7="",M7=""),"",IF(J7<>"",K7/J7*H7/M7,IF(I7<>"",K7*I7/M7,""))) -> 0.061764706 | O7: =IF(N7="","",IF(N7<FoodClasses!$C$2,"lean",IF(N7<FoodClasses!$C$3,"medium","fatty"))) -> medium | P7: frozen | Q7: paperboard_tray | R7: inferred | S7: Stouffer's says single-serve trays changed from plastic to paper [S68]; coating not stated. | U7: partial | V7: no | X7: Do not prepare in toaster oven | Do not reheat tray | Z7: Carton opened by 'push in, pull out'; tray must not be reheated. Material not stated. | AA7: only total time (5.5 min) available; venting, stir and stand steps and wattage missing; stouffers.com page failed to load | AB7: https://www.heb.com/product-detail/stouffer-s-mac-cheese-frozen-meal/29054 https://www.shoprite.com/sm/delivery/rsid/256/product/stouffers-mac-&-cheese-12-oz-id-00013800103406
A8: zw-007 | B8: Lean Cuisine | C8: Protein Kick Spaghetti with Meat Sauce | E8: frozen_tray | F8: 11.5 | H8: =IF(G8<>"",G8,IF(F8<>"",ROUND(F8*28.3495,0),"")) -> 326 | I8: 1 | K8: 4 | L8: 0 | M8: =IF(H8="","",H8+L8) -> 326 | N8: =IF(OR(K8="",M8=""),"",IF(J8<>"",K8/J8*H8/M8,IF(I8<>"",K8*I8/M8,""))) -> 0.012269939 | O8: =IF(N8="","",IF(N8<FoodClasses!$C$2,"lean",IF(N8<FoodClasses!$C$3,"medium","fatty"))) -> lean | P8: frozen | Q8: pp_container | R8: inferred | S8: Lean Cuisine FAQ says plastic trays [S69]; microwave-only directions point to PP. | T8: 1100 | U8: complete | V8: no | W8: None given. Label says ovens vary. | X8: Do not prepare in toaster oven | Do not reheat tray | Z8: Uncolored plastic tray, recyclable in communities that accept them (per page). Resin code not stated. | AA8: UPC not shown | leancuisine.com product page failed to load | AB8: https://preview.hannaford.com/groceries/frozen/frozen-dinners-meals/pasta-frozen-meals/lean-cuisine-protein-kick-spaghetti-with-meat-sauce-frozen-meal-115-oz-box.html
A9: zw-008 | B9: Hungry-Man | C9: Selects Boneless Fried Chicken and Ham | D9: 658276202941 | E9: frozen_tray | F9: 16 | G9: 454 | H9: =IF(G9<>"",G9,IF(F9<>"",ROUND(F9*28.3495,0),"")) -> 454 | I9: 1 | J9: 454 | K9: 21 | L9: 0 | M9: =IF(H9="","",H9+L9) -> 454 | N9: =IF(OR(K9="",M9=""),"",IF(J9<>"",K9/J9*H9/M9,IF(I9<>"",K9*I9/M9,""))) -> 0.046255507 | O9: =IF(N9="","",IF(N9<FoodClasses!$C$2,"lean",IF(N9<FoodClasses!$C$3,"medium","fatty"))) -> medium | P9: frozen | Q9: cpet_tray | R9: inferred | S9: Oven directions at 350 F in the same tray. | T9: 1100 | U9: complete | V9: no | W9: None given. | X9: Do not prepare in toaster oven | Cook only one at a time | Keep frozen, do not thaw | Y9: 350°F, remove dessert film, slit entree film, on baking sheet 40-45 min, stand 2 min. | Z9: Multi-compartment tray with separate film areas over dessert and entree. Material not stated. | AB9: https://smartlabel.labelinsight.com/product/17238176/other/instructions https://smartlabel.labelinsight.com/product/17238176/nutrition
A10: zw-009 | B10: Healthy Choice | C10: Power Bowls Spicy Steak Burrito Bowl | D10: 072655006782 | E10: frozen_tray | F10: 9.25 | G10: 262 | H10: =IF(G10<>"",G10,IF(F10<>"",ROUND(F10*28.3495,0),"")) -> 262 | I10: 1 | J10: 262 | K10: 4.5 | L10: 0 | M10: =IF(H10="","",H10+L10) -> 262 | N10: =IF(OR(K10="",M10=""),"",IF(J10<>"",K10/J10*H10/M10,IF(I10<>"",K10*I10/M10,""))) -> 0.017175573 | O10: =IF(N10="","",IF(N10<FoodClasses!$C$2,"lean",IF(N10<FoodClasses!$C$3,"medium","fatty"))) -> lean | P10: frozen | Q10: pp_container | R10: inferred | S10: Microwave-only bowl; label forbids oven use. | T10: 1100 | U10: complete | V10: no | W10: None given. | X10: DO NOT cook in conventional or toaster ovens (microwave-only product) | Do not use if film seal is broken | Cook only one at a time | Z10: Film-sealed bowl; microwave only (label forbids conventional oven). Material not stated. | AA10: calorie value (180) looks low for a 262 g bowl; verify against package | AB10: https://smartlabel.labelinsight.com/product/14931912/other/instructions https://smartlabel.labelinsight.com/product/14931912/nutrition
A11: zw-010 | B11: Frontera | C11: Cheese Enchiladas with Red Enchilada Sauce | D11: 604183000194 | E11: frozen_tray | F11: 9 | G11: 255 | H11: =IF(G11<>"",G11,IF(F11<>"",ROUND(F11*28.3495,0),"")) -> 255 | I11: 1 | J11: 255 | K11: 15 | L11: 0 | M11: =IF(H11="","",H11+L11) -> 255 | N11: =IF(OR(K11="",M11=""),"",IF(J11<>"",K11/J11*H11/M11,IF(I11<>"",K11*I11/M11,""))) -> 0.058823529 | O11: =IF(N11="","",IF(N11<FoodClasses!$C$2,"lean",IF(N11<FoodClasses!$C$3,"medium","fatty"))) -> medium | P11: frozen | Q11: cpet_tray | R11: inferred | S11: Oven directions in the same tray at 350 F. | T11: 1100 | U11: complete | V11: no | W11: None given. | X11: Do not prepare in toaster oven | Cook only one at a time | Keep frozen, do not thaw | Y11: 350°F, remove film, cover with foil, on baking sheet 40 min, uncover 5 min, stand 1 min. | Z11: Tray in carton ('Push here to open'). Material not stated. | AB11: https://smartlabel.labelinsight.com/product/17883027/other/instructions https://smartlabel.labelinsight.com/product/17883027/nutrition
A12: zw-011 | B12: Healthy Choice | C12: Cafe Steamers BBQ-Seasoned Steak & Potatoes | E12: frozen_tray | F12: 9.5 | H12: =IF(G12<>"",G12,IF(F12<>"",ROUND(F12*28.3495,0),"")) -> 269 | I12: 1 | K12: 4 | L12: 0 | M12: =IF(H12="","",H12+L12) -> 269 | N12: =IF(OR(K12="",M12=""),"",IF(J12<>"",K12/J12*H12/M12,IF(I12<>"",K12*I12/M12,""))) -> 0.014869888 | O12: =IF(N12="","",IF(N12<FoodClasses!$C$2,"lean",IF(N12<FoodClasses!$C$3,"medium","fatty"))) -> lean | P12: frozen | Q12: pp_container | R12: unknown | S12: Two-part steamer bowl; material not stated. | U12: partial | V12: no | Z12: Two-compartment steamer bowl: steaming basket over a separate sauce bowl. Material not stated. | AA12: taken from retailer description; wattage, venting and stand time missing | UPC not shown | AB12: https://www.heb.com/product-detail/healthy-choice-caf-steamers-bbq-seasoned-steak-potatoes-frozen-meal/1042876
A13: zw-012 | B13: Amy's | C13: Amy's Bowls Mexican Casserole | E13: frozen_tray | F13: 9.5 | H13: =IF(G13<>"",G13,IF(F13<>"",ROUND(F13*28.3495,0),"")) -> 269 | I13: 1 | J13: 269 | K13: 16 | L13: 0 | M13: =IF(H13="","",H13+L13) -> 269 | N13: =IF(OR(K13="",M13=""),"",IF(J13<>"",K13/J13*H13/M13,IF(I13<>"",K13*I13/M13,""))) -> 0.059479554 | O13: =IF(N13="","",IF(N13<FoodClasses!$C$2,"lean",IF(N13<FoodClasses!$C$3,"medium","fatty"))) -> medium | P13: frozen | Q13: cpet_tray | R13: unknown | S13: Amy's bowls go into the conventional oven; material not stated. Confirm by photo. | U13: none | V13: no | AA13: amys.com product page failed to load; Wegmans and H-E-B pages show an empty Instructions section | photograph box for directions and tray info | AB13: https://www.wegmans.com/shop/product/261725-Mexican-Casserole
A14: zw-013 | B14: Marie Callender's | C14: Turkey Pot Pie | D14: 021131501143 | E14: frozen_tray | F14: 10 | G14: 283 | H14: =IF(G14<>"",G14,IF(F14<>"",ROUND(F14*28.3495,0),"")) -> 283 | I14: 1 | J14: 283 | K14: 31 | L14: 0 | M14: =IF(H14="","",H14+L14) -> 283 | N14: =IF(OR(K14="",M14=""),"",IF(J14<>"",K14/J14*H14/M14,IF(I14<>"",K14*I14/M14,""))) -> 0.10954064 | O14: =IF(N14="","",IF(N14<FoodClasses!$C$2,"lean",IF(N14<FoodClasses!$C$3,"medium","fatty"))) -> fatty | P14: frozen | Q14: pet_board_tray | R14: inferred | S14: Paperboard tray used in a 400 F oven; ovenable board carries a PET coating [S60]. | T14: 1100 | U14: complete | V14: no | W14: Microwaves below 1100 W are not recommended; the pie may not cook through. Use the conventional oven instead. | X14: Not recommended in microwaves under 1100 W | Do not prepare in toaster oven | Cook only one at a time | Y14: 400°F, remove from outer carton, keep in paper tray, foil strip around crust edge, on baking sheet 48-52 min, stand 5 min. | Z14: Outer carton plus paper (paperboard) tray; microwave in opened carton, oven in paper tray. | AB14: https://smartlabel.labelinsight.com/product/4662734/other/instructions https://smartlabel.labelinsight.com/product/4662734/nutrition
A15: zw-014 | B15: Marie Callender's | C15: Creamy Parmesan Chicken Pot Pie | D15: 021131506964 | E15: frozen_tray | F15: 15 | G15: 425 | H15: =IF(G15<>"",G15,IF(F15<>"",ROUND(F15*28.3495,0),"")) -> 425 | I15: 2 | J15: 200 | K15: 27 | L15: 0 | M15: =IF(H15="","",H15+L15) -> 425 | N15: =IF(OR(K15="",M15=""),"",IF(J15<>"",K15/J15*H15/M15,IF(I15<>"",K15*I15/M15,""))) -> 0.135 | O15: =IF(N15="","",IF(N15<FoodClasses!$C$2,"lean",IF(N15<FoodClasses!$C$3,"medium","fatty"))) -> fatty | P15: frozen | Q15: pet_board_tray | R15: inferred | S15: Paperboard tray used in a 400 F oven; ovenable board carries a PET coating [S60]. | T15: 1100 | U15: complete | V15: no | W15: Do not microwave in ovens below 1100 W; use the conventional oven instead. | X15: Do not microwave in ovens under 1100 W | Do not prepare in toaster oven | Cook only one at a time | Y15: 400°F, keep in paper tray, foil strip around crust edge, on baking sheet 60-63 min, stand 5 min. | Z15: Outer carton plus paper (paperboard) tray. | AA15: servings per container listed as 'about 2' | AB15: https://smartlabel.labelinsight.com/product/4662724/other/instructions https://smartlabel.labelinsight.com/product/4662724/nutrition
A16: zw-015 | B16: Kraft | C16: Easy Mac Original Flavor Mac & Cheese Cups | E16: cup_bowl | F16: 2.05 | H16: =IF(G16<>"",G16,IF(F16<>"",ROUND(F16*28.3495,0),"")) -> 58 | I16: 1 | K16: 3.5 | L16: 110 | M16: =IF(H16="","",H16+L16) -> 168 | N16: =IF(OR(K16="",M16=""),"",IF(J16<>"",K16/J16*H16/M16,IF(I16<>"",K16*I16/M16,""))) -> 0.020833333 | O16: =IF(N16="","",IF(N16<FoodClasses!$C$2,"lean",IF(N16<FoodClasses!$C$3,"medium","fatty"))) -> lean | P16: shelf | Q16: pp_container | R16: inferred | S16: Microwavable plastic cup; check the resin code under the cup. | U16: partial | V16: no | X16: Cup and contents get very hot; keep children from burns | Z16: Single-serve microwavable cup with fill line. Material not stated. | AA16: wattage, stand time and power level not shown | UPC not shown | Sold as a 4-cup pack; nutrition is per cup and the app treats one cup as the product. | AB16: https://www.heb.com/product-detail/kraft-easy-mac-original-flavor-mac-and-cheese-cups/1070769
A17: zw-016 | B17: Maruchan | C17: Instant Lunch Ramen Noodle Soup, Chicken Flavor | E17: cup_bowl | F17: 2.25 | H17: =IF(G17<>"",G17,IF(F17<>"",ROUND(F17*28.3495,0),"")) -> 64 | L17: 300 | M17: =IF(H17="","",H17+L17) -> 364 | N17: =IF(OR(K17="",M17=""),"",IF(J17<>"",K17/J17*H17/M17,IF(I17<>"",K17*I17/M17,""))) | O17: =IF(N17="","",IF(N17<FoodClasses!$C$2,"lean",IF(N17<FoodClasses!$C$3,"medium","fatty"))) | P17: shelf | Q17: eps_foam | R17: label | S17: Label says do not microwave; check whether the cup is foam or paper. | U17: not_applicable | V17: yes | X17: Do not microwave | Z17: Single-serve cup with peel lid and inside fill line. Material not stated on source pages. | AA17: nutrition not shown on readable pages | good negative example: cup-shaped but labeled do not microwave | AB17: https://www.ubereats.com/store/safeway-2980-e-capitol-expy/5-N2W3K9WEqK_hLD35hwVQ/c3297a1d-4fb9-53f4-a254-36d1fa306f6f/922e7cae-c81f-4bba-82fa-5e9f19cfaffd/eda8ec7f-dc34-5bd1-ab34-0b8aab8f923f https://www.heb.com/product-detail/maruchan-instant-lunch-ramen-noodle-soup-cups-chicken-flavor/133669
A18: zw-017 | B18: Nissin | C18: Cup Noodles Chicken Flavor | E18: cup_bowl | F18: 2.25 | H18: =IF(G18<>"",G18,IF(F18<>"",ROUND(F18*28.3495,0),"")) -> 64 | I18: 1 | K18: 11 | L18: 300 | M18: =IF(H18="","",H18+L18) -> 364 | N18: =IF(OR(K18="",M18=""),"",IF(J18<>"",K18/J18*H18/M18,IF(I18<>"",K18*I18/M18,""))) -> 0.03021978 | O18: =IF(N18="","",IF(N18<FoodClasses!$C$2,"lean",IF(N18<FoodClasses!$C$3,"medium","fatty"))) -> medium | P18: shelf | Q18: paper_cup | R18: label | S18: Paper cup since 2024. | U18: partial | V18: no | Z18: Paper cup that replaced the polystyrene cup in 2024 and made the product microwavable in the package. | AA18: 2:15 microwave time comes from retailer listing and news report; wattage, fill line and stir/stand steps are on the lid and were not readable online | older polystyrene cups may still be in some stores; check the cup | AB18: https://heb.com/product-detail/nissin-cup-noodles-chicken-flavor-noodle-soup/160083 https://www.orderroombox.com/product/nissin-cup-noodles-chicken-flavor-ramen-noodle-soup-2/ https://www.foxla.com/news/cup-noodles-unveils-game-changing-packaging-update-for-2024
A19: zw-018 | B19: Campbell's | C19: Chunky Beef with Country Vegetables Soup, Microwavable Bowl | D19: 51000148787 | E19: cup_bowl | F19: 15.25 | H19: =IF(G19<>"",G19,IF(F19<>"",ROUND(F19*28.3495,0),"")) -> 432 | I19: 1 | K19: 3 | L19: 0 | M19: =IF(H19="","",H19+L19) -> 432 | N19: =IF(OR(K19="",M19=""),"",IF(J19<>"",K19/J19*H19/M19,IF(I19<>"",K19*I19/M19,""))) -> 0.0069444444 | O19: =IF(N19="","",IF(N19<FoodClasses!$C$2,"lean",IF(N19<FoodClasses!$C$3,"medium","fatty"))) -> lean | P19: shelf | Q19: pp_container | R19: inferred | S19: Microwave-safe plastic bowl; remove the metal peel lid first. | U19: partial | V19: no | W19: Label notes microwave ovens vary and uneven heating may cause popping or splattering. | X19: Plastic cap may be hot | Z19: Microwave-safe bowl with peel-off cover and plastic cap; eat directly from bowl. | AA19: no reference wattage stated | AB19: https://www.campbellsfoodservice.com/product/beef-with-country-vegetables-soup/
A20: zw-019 | B20: Campbell's | C20: Chunky Classic Chicken Noodle Soup, Microwavable Bowl | E20: cup_bowl | F20: 15.25 | H20: =IF(G20<>"",G20,IF(F20<>"",ROUND(F20*28.3495,0),"")) -> 432 | I20: 1 | K20: 5 | L20: 0 | M20: =IF(H20="","",H20+L20) -> 432 | N20: =IF(OR(K20="",M20=""),"",IF(J20<>"",K20/J20*H20/M20,IF(I20<>"",K20*I20/M20,""))) -> 0.011574074 | O20: =IF(N20="","",IF(N20<FoodClasses!$C$2,"lean",IF(N20<FoodClasses!$C$3,"medium","fatty"))) -> lean | P20: shelf | Q20: pp_container | R20: inferred | S20: Microwavable bowl with metal peel lid; remove the lid first. | U20: none | V20: no | X20: Do not reuse or reheat bowl | Metal edges are sharp | Do not buy if open or punctured | Z20: Microwavable bowl; page warns of sharp metal edges (peel-off lid) and says not to reuse or reheat the bowl. | AA20: Instructions section empty on H-E-B page; photograph bowl label | AB20: https://www.heb.com/product-detail/campbell-s-chunky-classic-chicken-noodle-soup/569232
A21: zw-020 | B21: Hormel | C21: Compleats Meatloaf & Gravy with Mashed Potatoes | E21: cup_bowl | F21: 9 | G21: 255 | H21: =IF(G21<>"",G21,IF(F21<>"",ROUND(F21*28.3495,0),"")) -> 255 | I21: 1 | K21: 13 | L21: 0 | M21: =IF(H21="","",H21+L21) -> 255 | N21: =IF(OR(K21="",M21=""),"",IF(J21<>"",K21/J21*H21/M21,IF(I21<>"",K21*I21/M21,""))) -> 0.050980392 | O21: =IF(N21="","",IF(N21<FoodClasses!$C$2,"lean",IF(N21<FoodClasses!$C$3,"medium","fatty"))) -> medium | P21: shelf | Q21: pp_container | R21: inferred | S21: Shelf-stable film-sealed tray. | U21: partial | V21: no | W21: Times approximate because microwaves vary. | X21: Not for conventional ovens | Z21: Shelf-stable microwavable tray sealed with plastic film. Material not stated. | AA21: no reference wattage | UPC not shown | page header says '9 oz can' but description is a film-sealed tray | AB21: https://preview.hannaford.com/groceries/soups-canned-goods/canned-meat/hormel-compleats-meatloaf-gravy-with-mashed-potatoes-microwavable-9-oz-can.html
A22: zw-021 | B22: Hormel | C22: Compleats Beef Tips & Gravy with Mashed Potatoes | E22: cup_bowl | F22: 9 | H22: =IF(G22<>"",G22,IF(F22<>"",ROUND(F22*28.3495,0),"")) -> 255 | I22: 1 | K22: 8 | L22: 0 | M22: =IF(H22="","",H22+L22) -> 255 | N22: =IF(OR(K22="",M22=""),"",IF(J22<>"",K22/J22*H22/M22,IF(I22<>"",K22*I22/M22,""))) -> 0.031372549 | O22: =IF(N22="","",IF(N22<FoodClasses!$C$2,"lean",IF(N22<FoodClasses!$C$3,"medium","fatty"))) -> medium | P22: shelf | Q22: pp_container | R22: inferred | S22: Shelf-stable tray. | U22: none | V22: no | Z22: Single tray (serving size listed as 1 tray). Material not stated. | AA22: Instructions section empty; photograph tray label | AB22: https://www.heb.com/product-detail/hormel-compleats-beef-tips-gravy-with-mashed-potatoes/1058929
A23: zw-022 | B23: Chef Boyardee | C23: Beefaroni Microwavable Bowl | E23: cup_bowl | F23: 7.5 | H23: =IF(G23<>"",G23,IF(F23<>"",ROUND(F23*28.3495,0),"")) -> 213 | L23: 0 | M23: =IF(H23="","",H23+L23) -> 213 | N23: =IF(OR(K23="",M23=""),"",IF(J23<>"",K23/J23*H23/M23,IF(I23<>"",K23*I23/M23,""))) | O23: =IF(N23="","",IF(N23<FoodClasses!$C$2,"lean",IF(N23<FoodClasses!$C$3,"medium","fatty"))) | P23: shelf | Q23: pp_container | R23: inferred | S23: Microwavable bowl. | U23: none | V23: no | AA23: placeholder: net weight from retailer listing titles only; SmartLabel instructions page returned server errors twice; Ahold retailer sites were in maintenance | photograph bowl label | AB23: https://smartlabel.labelinsight.com/product/13051379/other/claims
A24: zw-023 | B24: Birds Eye | C24: Steamfresh Seasoned Asian Medley | D24: 014500021632 | E24: steam_bag | F24: 10.8 | G24: 306 | H24: =IF(G24<>"",G24,IF(F24<>"",ROUND(F24*28.3495,0),"")) -> 306 | L24: 0 | M24: =IF(H24="","",H24+L24) -> 306 | N24: =IF(OR(K24="",M24=""),"",IF(J24<>"",K24/J24*H24/M24,IF(I24<>"",K24*I24/M24,""))) | O24: =IF(N24="","",IF(N24<FoodClasses!$C$2,"lean",IF(N24<FoodClasses!$C$3,"medium","fatty"))) | P24: frozen | Q24: steam_bag | R24: label | S24: Steam bag. | U24: complete | V24: no | W24: Below 800 W, use stovetop directions instead. | X24: Do not puncture bag | Do not thaw | Cook only one at a time | Z24: Microwave-safe steam bag with built-in vent; bag inflates and may whistle; tear notch and corner tabs. | AA24: nutrition page returned a server error | AB24: https://smartlabel.labelinsight.com/product/6823283/other/instructions
A25: zw-024 | B25: Birds Eye | C25: Steamfresh Power Blend Hawaiian Style | D25: 014500016676 | E25: steam_bag | F25: 12.8 | G25: 363 | H25: =IF(G25<>"",G25,IF(F25<>"",ROUND(F25*28.3495,0),"")) -> 363 | I25: 1 | J25: 363 | K25: 5 | L25: 0 | M25: =IF(H25="","",H25+L25) -> 363 | N25: =IF(OR(K25="",M25=""),"",IF(J25<>"",K25/J25*H25/M25,IF(I25<>"",K25*I25/M25,""))) -> 0.013774105 | O25: =IF(N25="","",IF(N25<FoodClasses!$C$2,"lean",IF(N25<FoodClasses!$C$3,"medium","fatty"))) -> lean | P25: frozen | Q25: steam_bag | R25: label | S25: Steam bag. | U25: complete | V25: no | W25: Below 800 W, use stovetop directions instead. | X25: Do not pierce bag | Do not thaw | Cook only one at a time | Z25: Microwave-safe steam bag with vent; inflates while cooking, may whistle. | AB25: https://smartlabel.labelinsight.com/product/6100979/other/instructions https://smartlabel.labelinsight.com/product/6100979/nutrition
A26: zw-025 | B26: Birds Eye | C26: Steamfresh Power Blend Italian Style | D26: 014500015822 | E26: steam_bag | F26: 11.5 | G26: 326 | H26: =IF(G26<>"",G26,IF(F26<>"",ROUND(F26*28.3495,0),"")) -> 326 | I26: 1 | J26: 326 | K26: 6 | L26: 0 | M26: =IF(H26="","",H26+L26) -> 326 | N26: =IF(OR(K26="",M26=""),"",IF(J26<>"",K26/J26*H26/M26,IF(I26<>"",K26*I26/M26,""))) -> 0.018404908 | O26: =IF(N26="","",IF(N26<FoodClasses!$C$2,"lean",IF(N26<FoodClasses!$C$3,"medium","fatty"))) -> lean | P26: frozen | Q26: steam_bag | R26: label | S26: Steam bag. | T26: 1100 | U26: complete | V26: no | W26: None given; adjust for appliance. | X26: Do not pierce bag | Do not thaw | Cook only one bag at a time | Z26: Sealed microwave steam bag with vent; printed 'THIS SIDE UP', 'TEAR HERE', 'PICK UP HERE'. | AA26: same product line as zw-023/024 but uses a single 1100 W reference instead of a wattage table | AB26: https://smartlabel.labelinsight.com/product/13770749/other/instructions https://smartlabel.labelinsight.com/product/13770749/nutrition
A27: zw-026 | B27: Green Giant | C27: Riced Veggies Cauliflower & Broccoli | D27: 190569123118 | E27: steam_bag | F27: 10 | G27: 283 | H27: =IF(G27<>"",G27,IF(F27<>"",ROUND(F27*28.3495,0),"")) -> 283 | I27: 3 | K27: 0 | L27: 0 | M27: =IF(H27="","",H27+L27) -> 283 | N27: =IF(OR(K27="",M27=""),"",IF(J27<>"",K27/J27*H27/M27,IF(I27<>"",K27*I27/M27,""))) -> 0 | O27: =IF(N27="","",IF(N27<FoodClasses!$C$2,"lean",IF(N27<FoodClasses!$C$3,"medium","fatty"))) -> lean | P27: frozen | Q27: steam_bag | R27: label | S27: Steam bag. | T27: 1000 | U27: complete | V27: no | W27: 700 W: 7 min on HIGH. | X27: Do not thaw | Z27: Microwave-in bag cooked standing upright; vent not mentioned. | AA27: servings per container listed as 'about 3' | AB27: https://smartlabel.labelinsight.com/product/6822702/other/instructions https://smartlabel.labelinsight.com/product/6822702/nutrition
A28: zw-027 | B28: Green Giant | C28: Riced Veggies Cauliflower Risotto Medley | D28: 190569123286 | E28: steam_bag | F28: 10 | G28: 283 | H28: =IF(G28<>"",G28,IF(F28<>"",ROUND(F28*28.3495,0),"")) -> 283 | L28: 0 | M28: =IF(H28="","",H28+L28) -> 283 | N28: =IF(OR(K28="",M28=""),"",IF(J28<>"",K28/J28*H28/M28,IF(I28<>"",K28*I28/M28,""))) | O28: =IF(N28="","",IF(N28<FoodClasses!$C$2,"lean",IF(N28<FoodClasses!$C$3,"medium","fatty"))) | P28: frozen | Q28: steam_bag | R28: label | S28: Steam bag. | T28: 1000 | U28: complete | V28: no | W28: 700 W: 7 min on HIGH. | X28: Do not thaw | Z28: Microwave-in bag cooked standing upright; vent not mentioned. | AA28: nutrition page not fetched (call budget) | AB28: https://smartlabel.labelinsight.com/product/6822696/other/instructions
A29: zw-028 | B29: Green Giant | C29: Lightly Sauced Broccoli, Carrots, Cauliflower & Cheese Sauce | D29: 020000199641 | E29: steam_bag | F29: 10 | G29: 283 | H29: =IF(G29<>"",G29,IF(F29<>"",ROUND(F29*28.3495,0),"")) -> 283 | I29: 2.5 | J29: 109 | K29: 1 | L29: 0 | M29: =IF(H29="","",H29+L29) -> 283 | N29: =IF(OR(K29="",M29=""),"",IF(J29<>"",K29/J29*H29/M29,IF(I29<>"",K29*I29/M29,""))) -> 0.0091743119 | O29: =IF(N29="","",IF(N29<FoodClasses!$C$2,"lean",IF(N29<FoodClasses!$C$3,"medium","fatty"))) -> lean | P29: frozen | Q29: steam_bag | R29: label | S29: Steam bag. | U29: complete | V29: no | W29: Table covers 700 W. | X29: Do not leave microwave unattended | Z29: Microwave-in bag cooked standing on a plate; tear notch. Vent not mentioned. | AA29: servings per container listed as 'about 2.5' | best example of a 3-level wattage table | AB29: https://smartlabel.labelinsight.com/product/6822674/other/instructions https://smartlabel.labelinsight.com/product/6822674/nutrition
A30: zw-029 | B30: Ben's Original | C30: Ready Rice Jasmine | E30: pouch | F30: 8.5 | H30: =IF(G30<>"",G30,IF(F30<>"",ROUND(F30*28.3495,0),"")) -> 241 | K30: 3 | L30: 0 | M30: =IF(H30="","",H30+L30) -> 241 | N30: =IF(OR(K30="",M30=""),"",IF(J30<>"",K30/J30*H30/M30,IF(I30<>"",K30*I30/M30,""))) | O30: =IF(N30="","",IF(N30<FoodClasses!$C$2,"lean",IF(N30<FoodClasses!$C$3,"medium","fatty"))) | P30: shelf | Q30: pouch | R30: label | S30: BPA-free pouch. | U30: partial | V30: no | Z30: BPA-free microwaveable rice pouch. | AA30: squeeze/tear-vent steps and wattage not shown on US retailer page | UPC not shown | AB30: https://heb.com/product-detail/ben-s-original-ready-rice-jasmine/1250123
A31: zw-030 | B31: Ben's Original | C31: Ready Rice Spanish Style | E31: pouch | F31: 8.8 | H31: =IF(G31<>"",G31,IF(F31<>"",ROUND(F31*28.3495,0),"")) -> 249 | J31: 144 | K31: 3 | L31: 0 | M31: =IF(H31="","",H31+L31) -> 249 | N31: =IF(OR(K31="",M31=""),"",IF(J31<>"",K31/J31*H31/M31,IF(I31<>"",K31*I31/M31,""))) -> 0.020833333 | O31: =IF(N31="","",IF(N31<FoodClasses!$C$2,"lean",IF(N31<FoodClasses!$C$3,"medium","fatty"))) -> lean | P31: shelf | Q31: pouch | R31: label | S31: BPA-free pouch. | U31: partial | V31: no | Z31: BPA-free microwaveable pouch. | AA31: squeeze/tear-vent steps and wattage not shown | UPC not shown | AB31: https://heb.com/product-detail/ben-s-original-ready-rice-spanish-style/592802
A32: zw-031 | B32: Tyson | C32: Breaded & Stuffed Chicken Breasts Cordon Bleu, 2 Count (raw) | E32: oven_only | F32: 10 | H32: =IF(G32<>"",G32,IF(F32<>"",ROUND(F32*28.3495,0),"")) -> 283 | I32: 2 | J32: 140 | K32: 14 | L32: 0 | M32: =IF(H32="","",H32+L32) -> 283 | N32: =IF(OR(K32="",M32=""),"",IF(J32<>"",K32/J32*H32/M32,IF(I32<>"",K32*I32/M32,""))) -> 0.1 | O32: =IF(N32="","",IF(N32<FoodClasses!$C$2,"lean",IF(N32<FoodClasses!$C$3,"medium","fatty"))) -> fatty | P32: frozen | Q32: paperboard_tray | R32: label | S32: Oven only, raw chicken. | U32: not_applicable | V32: yes | X32: DO NOT MICROWAVE OR AIR FRY | Oven bake only, raw chicken | Y32: 375°F, frozen raw breasts on flat metal baking sheet 2 in apart; 31-33 min for 1-2 pieces, 36-39 min for 3-6 pieces; 165°F internal; cool about 3 min. | Z32: Individually wrapped raw breaded pieces in a carton. | AA32: the 14-digit code appears only in a Tyson URL and is not labeled as a UPC; confirm from package | AB32: https://www.tyson.com/products/stuffed-chicken-breasts-cordon-bleu-2-count https://www.tyson.com/products/stuffed-entrees/00023700060273
A33: zw-032 | B33: DiGiorno | C33: Original Rising Crust Pepperoni Pizza | E33: oven_only | F33: 24.7 | G33: 702 | H33: =IF(G33<>"",G33,IF(F33<>"",ROUND(F33*28.3495,0),"")) -> 702 | I33: 5 | J33: 140 | K33: 13 | L33: 0 | M33: =IF(H33="","",H33+L33) -> 702 | N33: =IF(OR(K33="",M33=""),"",IF(J33<>"",K33/J33*H33/M33,IF(I33<>"",K33*I33/M33,""))) -> 0.092857143 | O33: =IF(N33="","",IF(N33<FoodClasses!$C$2,"lean",IF(N33<FoodClasses!$C$3,"medium","fatty"))) -> medium | P33: frozen | Q33: paperboard_tray | R33: label | S33: Oven only (pizza). | U33: not_applicable | V33: unknown | Y33: 400°F, keep frozen while preheating, remove freshness wrap, place directly on center rack, 19 min, stand 5 min. | Z33: Pizza in freshness wrap inside carton. No other packaging detail given. | AA33: page gives oven directions only; no explicit 'do not microwave' wording found online, so do_not_microwave is null (check box) | page body calls it 'Ultimate Pepperoni'; title says 'Original Rising Crust Pepperoni Pizza 24.7oz' | servings listed as 'about 5' | AB33: https://www.goodnes.com/digiorno/products/rising-crust-pepperoni-pizza-24-oz/
A34: zw-033 | B34: Marie Callender's | C34: Family Size Chicken Parmesan | D34: 021131034344 | E34: oven_only | F34: 38 | G34: 1070 | H34: =IF(G34<>"",G34,IF(F34<>"",ROUND(F34*28.3495,0),"")) -> 1070 | I34: 4 | J34: 269 | K34: 20 | L34: 0 | M34: =IF(H34="","",H34+L34) -> 1070 | N34: =IF(OR(K34="",M34=""),"",IF(J34<>"",K34/J34*H34/M34,IF(I34<>"",K34*I34/M34,""))) -> 0.074349442 | O34: =IF(N34="","",IF(N34<FoodClasses!$C$2,"lean",IF(N34<FoodClasses!$C$3,"medium","fatty"))) -> medium | P34: frozen | Q34: cpet_tray | R34: inferred | S34: Oven-safe tray, oven step required. | T34: 1100 | U34: partial | V34: no | W34: None given. | X34: No microwave-only method; oven finish required | Do not prepare in toaster oven | Cook only one at a time | Y34: 375°F, vent film corner, on baking sheet 60-70 min, stand 5 min. | Z34: Family-size film-covered tray; oven-safe per directions. Material not stated. | AA34: oven required: microwave is only the first stage of a microwave-plus-oven method | net weight 38 oz = 2 lb 6 oz (1.07 kg) per label | AB34: https://smartlabel.labelinsight.com/product/18719462/other/instructions https://smartlabel.labelinsight.com/product/18719462/nutrition
A35: zw-101 | B35: Banquet | C35: Mega Bowls Chicken Fried Beef Steak | D35: 031000126117 | E35: frozen_tray | F35: 14 | G35: 396 | H35: =IF(G35<>"",G35,IF(F35<>"",ROUND(F35*28.3495,0),"")) -> 396 | I35: 1 | J35: 396 | K35: 30 | L35: 0 | M35: =IF(H35="","",H35+L35) -> 396 | N35: =IF(OR(K35="",M35=""),"",IF(J35<>"",K35/J35*H35/M35,IF(I35<>"",K35*I35/M35,""))) -> 0.075757576 | O35: =IF(N35="","",IF(N35<FoodClasses!$C$2,"lean",IF(N35<FoodClasses!$C$3,"medium","fatty"))) -> medium | P35: frozen | Q35: cpet_tray | R35: inferred | S35: The same tray goes into a 350-375 F oven, which plastic other than CPET does not survive. | T35: 1100 | U35: complete | V35: no | W35: None given. Label says appliances vary and to adjust times. | X35: Do not prepare in toaster oven | Keep frozen. Do not thaw. | Cook only one at a time | Y35: 375°F, do not remove film, on baking sheet 50-55 min, stand 2 min. | Z35: Film-covered bowl; same bowl goes in the 375°F oven with film left on. Material not stated on label. Brand-level only: Conagra said c. 2009 that nearly all frozen meal trays for Healthy Choice, Banquet, Kid Cuisine and Marie Callender's used 30 to 40 percent post-consumer recycled plastic (https://progressivegrocer.com/conagra-unveils-new-eco-friendly-frozen-tray-design), described as a dual-ovenable monolayer rPET tray (https://www.foodingredientsfirst.com/news/a-first-in-monolayer-rpet-trays-used-by-conagra-foods-for-its-frozen-entrees-and-meals.html). Not confirmed for this current SKU. | AA35: inferred CPET (oven-safe tray) | AB35: https://smartlabel.labelinsight.com/product/10998562/other/instructions https://smartlabel.labelinsight.com/product/10998562/nutrition
A36: zw-102 | B36: Banquet | C36: Mega Bowls Chicken Fajita Bowl | D36: 031000126131 | E36: frozen_tray | F36: 14 | G36: 396 | H36: =IF(G36<>"",G36,IF(F36<>"",ROUND(F36*28.3495,0),"")) -> 396 | I36: 1 | J36: 396 | K36: 10 | L36: 0 | M36: =IF(H36="","",H36+L36) -> 396 | N36: =IF(OR(K36="",M36=""),"",IF(J36<>"",K36/J36*H36/M36,IF(I36<>"",K36*I36/M36,""))) -> 0.025252525 | O36: =IF(N36="","",IF(N36<FoodClasses!$C$2,"lean",IF(N36<FoodClasses!$C$3,"medium","fatty"))) -> lean | P36: frozen | Q36: cpet_tray | R36: inferred | S36: The same tray goes into a 350-375 F oven, which plastic other than CPET does not survive. | T36: 1100 | U36: complete | V36: no | W36: None given. Label says appliances vary and to adjust times. | X36: Do not prepare in toaster oven | Keep frozen. Do not thaw. | Cook only one at a time | Y36: 375°F, do not remove film, on baking sheet 52-55 min, stand 2 min, stir. | Z36: Film-covered bowl; same bowl goes in the 375°F oven with film left on. Material not stated on label. Brand-level only: Conagra said c. 2009 that nearly all frozen meal trays for Healthy Choice, Banquet, Kid Cuisine and Marie Callender's used 30 to 40 percent post-consumer recycled plastic (https://progressivegrocer.com/conagra-unveils-new-eco-friendly-frozen-tray-design), described as a dual-ovenable monolayer rPET tray (https://www.foodingredientsfirst.com/news/a-first-in-monolayer-rpet-trays-used-by-conagra-foods-for-its-frozen-entrees-and-meals.html). Not confirmed for this current SKU. | AA36: inferred CPET (oven-safe tray) | no microwave stand time listed (oven directions give 2 min) | AB36: https://smartlabel.labelinsight.com/product/9615098/other/instructions https://smartlabel.labelinsight.com/product/9615098/nutrition
A37: zw-103 | B37: Banquet | C37: Mega Bowls Chicken Bacon Alfredo | D37: 031000009236 | E37: frozen_tray | F37: 13 | G37: 368 | H37: =IF(G37<>"",G37,IF(F37<>"",ROUND(F37*28.3495,0),"")) -> 368 | I37: 1 | J37: 368 | K37: 18 | L37: 0 | M37: =IF(H37="","",H37+L37) -> 368 | N37: =IF(OR(K37="",M37=""),"",IF(J37<>"",K37/J37*H37/M37,IF(I37<>"",K37*I37/M37,""))) -> 0.048913043 | O37: =IF(N37="","",IF(N37<FoodClasses!$C$2,"lean",IF(N37<FoodClasses!$C$3,"medium","fatty"))) -> medium | P37: frozen | Q37: cpet_tray | R37: inferred | S37: The same tray goes into a 350-375 F oven, which plastic other than CPET does not survive. | T37: 1100 | U37: complete | V37: no | W37: None given. Label says appliances vary and to adjust times. | X37: Do not prepare in toaster oven | Keep frozen. Do not thaw. | Cook only one at a time | Y37: 375°F, do not remove film, on baking sheet 40-45 min, stand 2 min, stir. | Z37: Film-covered bowl; same bowl goes in the 375°F oven with film left on. Material not stated on label. Brand-level only: Conagra said c. 2009 that nearly all frozen meal trays for Healthy Choice, Banquet, Kid Cuisine and Marie Callender's used 30 to 40 percent post-consumer recycled plastic (https://progressivegrocer.com/conagra-unveils-new-eco-friendly-frozen-tray-design), described as a dual-ovenable monolayer rPET tray (https://www.foodingredientsfirst.com/news/a-first-in-monolayer-rpet-trays-used-by-conagra-foods-for-its-frozen-entrees-and-meals.html). Not confirmed for this current SKU. | AA37: inferred CPET (oven-safe tray) | AB37: https://smartlabel.labelinsight.com/product/15120999/other/instructions https://smartlabel.labelinsight.com/product/15120999/nutrition
A38: zw-104 | B38: Banquet | C38: Classic Dinner Salisbury Steak Meal | D38: 031000007300 | E38: frozen_tray | F38: 11.88 | G38: 337 | H38: =IF(G38<>"",G38,IF(F38<>"",ROUND(F38*28.3495,0),"")) -> 337 | I38: 1 | J38: 337 | K38: 16 | L38: 0 | M38: =IF(H38="","",H38+L38) -> 337 | N38: =IF(OR(K38="",M38=""),"",IF(J38<>"",K38/J38*H38/M38,IF(I38<>"",K38*I38/M38,""))) -> 0.047477745 | O38: =IF(N38="","",IF(N38<FoodClasses!$C$2,"lean",IF(N38<FoodClasses!$C$3,"medium","fatty"))) -> medium | P38: frozen | Q38: cpet_tray | R38: inferred | S38: The same tray goes into a 350-375 F oven, which plastic other than CPET does not survive. | T38: 1100 | U38: complete | V38: no | W38: None given. Label says appliances vary and to adjust times. | X38: Do not prepare in toaster oven | Keep frozen. Do not thaw. | Cook only one at a time | Y38: 350°F, cut and remove film from dessert, on baking sheet 33-35 min, stand 2 min, stir potatoes. | Z38: Multi-compartment film-covered tray with a dessert compartment; same tray goes in the 350°F oven. Material not stated on label. Brand-level only: Conagra said c. 2009 that nearly all frozen meal trays for Healthy Choice, Banquet, Kid Cuisine and Marie Callender's used 30 to 40 percent post-consumer recycled plastic (https://progressivegrocer.com/conagra-unveils-new-eco-friendly-frozen-tray-design), described as a dual-ovenable monolayer rPET tray (https://www.foodingredientsfirst.com/news/a-first-in-monolayer-rpet-trays-used-by-conagra-foods-for-its-frozen-entrees-and-meals.html). Not confirmed for this current SKU. | AA38: inferred CPET (oven-safe tray) | single cook period with no mid-cook stir; label does not mention venting the entree film | AB38: https://smartlabel.labelinsight.com/product/6361412/other/instructions https://smartlabel.labelinsight.com/product/6361412/nutrition
A39: zw-105 | B39: Banquet | C39: Salisbury Steak Meal (8 oz) | D39: 031000007454 | E39: frozen_tray | F39: 8 | G39: 227 | H39: =IF(G39<>"",G39,IF(F39<>"",ROUND(F39*28.3495,0),"")) -> 227 | I39: 1 | J39: 227 | K39: 17 | L39: 0 | M39: =IF(H39="","",H39+L39) -> 227 | N39: =IF(OR(K39="",M39=""),"",IF(J39<>"",K39/J39*H39/M39,IF(I39<>"",K39*I39/M39,""))) -> 0.074889868 | O39: =IF(N39="","",IF(N39<FoodClasses!$C$2,"lean",IF(N39<FoodClasses!$C$3,"medium","fatty"))) -> medium | P39: frozen | Q39: cpet_tray | R39: inferred | S39: The same tray goes into a 350-375 F oven, which plastic other than CPET does not survive. | T39: 1100 | U39: complete | V39: no | W39: None given. Label says appliances vary and to adjust times. | X39: Do not prepare in toaster oven | Keep frozen. Do not thaw. | Cook only one at a time | Y39: 350°F, slit film, on baking sheet 26-28 min, stand 2 min. | Z39: Film-covered compartment tray; same tray goes in the 350°F oven. Material not stated on label. Brand-level only: Conagra said c. 2009 that nearly all frozen meal trays for Healthy Choice, Banquet, Kid Cuisine and Marie Callender's used 30 to 40 percent post-consumer recycled plastic (https://progressivegrocer.com/conagra-unveils-new-eco-friendly-frozen-tray-design), described as a dual-ovenable monolayer rPET tray (https://www.foodingredientsfirst.com/news/a-first-in-monolayer-rpet-trays-used-by-conagra-foods-for-its-frozen-entrees-and-meals.html). Not confirmed for this current SKU. | AA39: inferred CPET (oven-safe tray) | fetch tool returned this page paraphrased, not verbatim; re-check step wording | side dish appears to be macaroni and cheese (from the stir step); full product name not confirmed | AB39: https://smartlabel.labelinsight.com/product/13969372/other/instructions https://smartlabel.labelinsight.com/product/13969372/nutrition
A40: zw-106 | B40: Healthy Choice | C40: Power Bowls Buddha Bowl | D40: 072655011120 | E40: frozen_tray | F40: 9.65 | G40: 273 | H40: =IF(G40<>"",G40,IF(F40<>"",ROUND(F40*28.3495,0),"")) -> 273 | I40: 1 | J40: 273 | K40: 11 | L40: 0 | M40: =IF(H40="","",H40+L40) -> 273 | N40: =IF(OR(K40="",M40=""),"",IF(J40<>"",K40/J40*H40/M40,IF(I40<>"",K40*I40/M40,""))) -> 0.04029304 | O40: =IF(N40="","",IF(N40<FoodClasses!$C$2,"lean",IF(N40<FoodClasses!$C$3,"medium","fatty"))) -> medium | P40: frozen | Q40: pp_container | R40: inferred | S40: Microwave-only tray or bowl; label forbids the conventional oven or gives no oven method. | T40: 1100 | U40: complete | V40: no | W40: None given. Label says appliances vary and to adjust times. | X40: Do not cook in conventional or toaster ovens | Do not use if film seal is broken | Keep frozen. Do not thaw. | Cook only one at a time | Z40: Film-sealed bowl. Label says do not cook in conventional or toaster ovens, so this container is microwave-only. Material not stated. Brand-level 2009 statement on Healthy Choice trays (30 to 40 percent PCR plastic): https://progressivegrocer.com/conagra-unveils-new-eco-friendly-frozen-tray-design (older tray formats; not confirmed for this SKU). | AB40: https://smartlabel.labelinsight.com/product/11502888/other/instructions https://smartlabel.labelinsight.com/product/11502888/nutrition
A41: zw-107 | B41: Healthy Choice | C41: Simply Steamers Grilled Chicken Pesto & Vegetables | D41: 072655001275 | E41: frozen_tray | F41: 9.15 | G41: 259 | H41: =IF(G41<>"",G41,IF(F41<>"",ROUND(F41*28.3495,0),"")) -> 259 | I41: 1 | J41: 259 | K41: 5 | L41: 0 | M41: =IF(H41="","",H41+L41) -> 259 | N41: =IF(OR(K41="",M41=""),"",IF(J41<>"",K41/J41*H41/M41,IF(I41<>"",K41*I41/M41,""))) -> 0.019305019 | O41: =IF(N41="","",IF(N41<FoodClasses!$C$2,"lean",IF(N41<FoodClasses!$C$3,"medium","fatty"))) -> lean | P41: frozen | Q41: pp_container | R41: inferred | S41: Microwave-only tray or bowl; label forbids the conventional oven or gives no oven method. | T41: 1100 | U41: complete | V41: no | W41: None given. Label says appliances vary and to adjust times. | X41: Do not cook in conventional or toaster ovens | Do not use if film seal is broken | Keep frozen. Do not thaw. | Cook only one at a time | Z41: Two-part steamer: steamed food sits above a separate sauce bowl and is stirred into it after cooking. Label says do not cook in conventional or toaster ovens, so this container is microwave-only. Material not stated. Brand-level 2009 statement on Healthy Choice trays (30 to 40 percent PCR plastic): https://progressivegrocer.com/conagra-unveils-new-eco-friendly-frozen-tray-design (older tray formats; not confirmed for this SKU). | AA41: no stand time listed | AB41: https://smartlabel.labelinsight.com/product/6453644/other/instructions https://smartlabel.labelinsight.com/product/6453644/nutrition
A42: zw-108 | B42: Healthy Choice | C42: Simply Steamers Chicken & Vegetable Stir Fry, 3 Pack | D42: 072655000780 | E42: frozen_tray | F42: 9.2 | H42: =IF(G42<>"",G42,IF(F42<>"",ROUND(F42*28.3495,0),"")) -> 261 | I42: 1 | J42: 262 | K42: 4 | L42: 0 | M42: =IF(H42="","",H42+L42) -> 261 | N42: =IF(OR(K42="",M42=""),"",IF(J42<>"",K42/J42*H42/M42,IF(I42<>"",K42*I42/M42,""))) -> 0.015267176 | O42: =IF(N42="","",IF(N42<FoodClasses!$C$2,"lean",IF(N42<FoodClasses!$C$3,"medium","fatty"))) -> lean | P42: frozen | Q42: pp_container | R42: inferred | S42: Microwave-only tray or bowl; label forbids the conventional oven or gives no oven method. | T42: 1100 | U42: complete | V42: no | W42: None given. Label says appliances vary and to adjust times. | X42: Do not cook in conventional or toaster ovens | Do not use if film seal is broken | Keep frozen. Do not thaw. | Cook only one at a time | Z42: Two-part steamer (steamed food over a sauce bowl), 3 per carton. Label says do not cook in conventional or toaster ovens, so this container is microwave-only. Material not stated. Brand-level 2009 statement on Healthy Choice trays (30 to 40 percent PCR plastic): https://progressivegrocer.com/conagra-unveils-new-eco-friendly-frozen-tray-design (older tray formats; not confirmed for this SKU). | AA42: multipack: net weight is for 3 meals of 9.25 oz each; directions are per meal | no stand time listed | UPC is for the 3-pack; single-meal UPC not collected | 3-pack; the label time is for one meal (262 g). | AB42: https://smartlabel.labelinsight.com/product/4580876/other/instructions https://smartlabel.labelinsight.com/product/4580876/nutrition
A43: zw-109 | B43: Healthy Choice | C43: Cafe Steamers General Tso's Spicy Chicken, 3 Pack | D43: 072655001909 | E43: frozen_tray | F43: 10.3 | H43: =IF(G43<>"",G43,IF(F43<>"",ROUND(F43*28.3495,0),"")) -> 292 | I43: 1 | J43: 292 | K43: 3.5 | L43: 0 | M43: =IF(H43="","",H43+L43) -> 292 | N43: =IF(OR(K43="",M43=""),"",IF(J43<>"",K43/J43*H43/M43,IF(I43<>"",K43*I43/M43,""))) -> 0.011986301 | O43: =IF(N43="","",IF(N43<FoodClasses!$C$2,"lean",IF(N43<FoodClasses!$C$3,"medium","fatty"))) -> lean | P43: frozen | Q43: pp_container | R43: inferred | S43: Microwave-only tray or bowl; label forbids the conventional oven or gives no oven method. | T43: 1100 | U43: complete | V43: no | W43: None given. Label says appliances vary and to adjust times. | X43: Do not cook in conventional or toaster ovens | Do not use if film seal is broken | Keep frozen. Do not thaw. | Cook only one at a time | Z43: Two-part steamer (steamed food over a sauce bowl), 3 per carton. Label says do not cook in conventional or toaster ovens, so this container is microwave-only. Material not stated. Brand-level 2009 statement on Healthy Choice trays (30 to 40 percent PCR plastic): https://progressivegrocer.com/conagra-unveils-new-eco-friendly-frozen-tray-design (older tray formats; not confirmed for this SKU). | AA43: multipack: net weight is for 3 meals; per-meal weight not printed in fetched text (serving 292 g) | no stand time listed | UPC is for the 3-pack; single-meal UPC not collected | 3-pack; the label time is for one meal (292 g). | AB43: https://smartlabel.labelinsight.com/product/6497763/other/instructions https://smartlabel.labelinsight.com/product/6497763/nutrition
A44: zw-110 | B44: Marie Callender's | C44: Cheesy Bacon Chicken Dinner | D44: 021131009991 | E44: frozen_tray | F44: 12 | G44: 340 | H44: =IF(G44<>"",G44,IF(F44<>"",ROUND(F44*28.3495,0),"")) -> 340 | L44: 0 | M44: =IF(H44="","",H44+L44) -> 340 | N44: =IF(OR(K44="",M44=""),"",IF(J44<>"",K44/J44*H44/M44,IF(I44<>"",K44*I44/M44,""))) | O44: =IF(N44="","",IF(N44<FoodClasses!$C$2,"lean",IF(N44<FoodClasses!$C$3,"medium","fatty"))) | P44: frozen | Q44: cpet_tray | R44: inferred | S44: The same tray goes into a 350-375 F oven, which plastic other than CPET does not survive. | T44: 1100 | U44: complete | V44: no | W44: None given. Label says appliances vary and to adjust times. | X44: Do not prepare in toaster oven | Keep frozen. Do not thaw. | Cook only one at a time | Y44: 350°F, slit film, on baking sheet 40-45 min, stand 2 min. | Z44: Film-covered dinner tray; same tray goes in the 350°F oven. Material not stated on label. Brand-level only: Conagra said c. 2009 that nearly all frozen meal trays for Healthy Choice, Banquet, Kid Cuisine and Marie Callender's used 30 to 40 percent post-consumer recycled plastic (https://progressivegrocer.com/conagra-unveils-new-eco-friendly-frozen-tray-design), described as a dual-ovenable monolayer rPET tray (https://www.foodingredientsfirst.com/news/a-first-in-monolayer-rpet-trays-used-by-conagra-foods-for-its-frozen-entrees-and-meals.html). Not confirmed for this current SKU. | AA44: inferred CPET (oven-safe tray) | nutrition page returned a server error on two attempts | unusual step: rotate the chicken (not the tray) half a turn | AB44: https://smartlabel.labelinsight.com/product/12573547/other/instructions https://smartlabel.labelinsight.com/product/12573547/nutrition
A45: zw-111 | B45: Marie Callender's | C45: Country Fried Chicken & Gravy Dinner | D45: 021131905330 | E45: frozen_tray | F45: 13.1 | G45: 371 | H45: =IF(G45<>"",G45,IF(F45<>"",ROUND(F45*28.3495,0),"")) -> 371 | L45: 0 | M45: =IF(H45="","",H45+L45) -> 371 | N45: =IF(OR(K45="",M45=""),"",IF(J45<>"",K45/J45*H45/M45,IF(I45<>"",K45*I45/M45,""))) | O45: =IF(N45="","",IF(N45<FoodClasses!$C$2,"lean",IF(N45<FoodClasses!$C$3,"medium","fatty"))) | P45: frozen | Q45: cpet_tray | R45: inferred | S45: The same tray goes into a 350-375 F oven, which plastic other than CPET does not survive. | T45: 1100 | U45: complete | V45: no | W45: None given. Label says appliances vary and to adjust times. | X45: Do not prepare in toaster oven | Keep frozen. Do not thaw. | Cook only one at a time | Y45: 350°F, cut film to vent, on baking sheet 40-45 min, stand 2 min, stir potatoes and corn. | Z45: Film-covered compartment tray; same tray goes in the 350°F oven. Material not stated on label. Brand-level only: Conagra said c. 2009 that nearly all frozen meal trays for Healthy Choice, Banquet, Kid Cuisine and Marie Callender's used 30 to 40 percent post-consumer recycled plastic (https://progressivegrocer.com/conagra-unveils-new-eco-friendly-frozen-tray-design), described as a dual-ovenable monolayer rPET tray (https://www.foodingredientsfirst.com/news/a-first-in-monolayer-rpet-trays-used-by-conagra-foods-for-its-frozen-entrees-and-meals.html). Not confirmed for this current SKU. | AA45: inferred CPET (oven-safe tray) | nutrition page returned a server error on two attempts | AB45: https://smartlabel.labelinsight.com/product/12155417/other/instructions https://smartlabel.labelinsight.com/product/12155417/nutrition
A46: zw-112 | B46: Marie Callender's | C46: Kansas City Style Pulled Pork Mac & Cheese Bowl | D46: 021131000219 | E46: frozen_tray | F46: 11 | G46: 312 | H46: =IF(G46<>"",G46,IF(F46<>"",ROUND(F46*28.3495,0),"")) -> 312 | I46: 1 | J46: 312 | K46: 14 | L46: 0 | M46: =IF(H46="","",H46+L46) -> 312 | N46: =IF(OR(K46="",M46=""),"",IF(J46<>"",K46/J46*H46/M46,IF(I46<>"",K46*I46/M46,""))) -> 0.044871795 | O46: =IF(N46="","",IF(N46<FoodClasses!$C$2,"lean",IF(N46<FoodClasses!$C$3,"medium","fatty"))) -> medium | P46: frozen | Q46: cpet_tray | R46: inferred | S46: The same tray goes into a 350-375 F oven, which plastic other than CPET does not survive. | T46: 1100 | U46: complete | V46: no | W46: None given. Label says appliances vary and to adjust times. | X46: Do not prepare in toaster oven | Keep frozen. Do not thaw. | Cook only one at a time | Y46: 375°F, do not remove film, on baking sheet 45-50 min, stand 2 min. | Z46: Film-covered bowl; same bowl goes in the 375°F oven with film left on. Material not stated on label. Brand-level only: Conagra said c. 2009 that nearly all frozen meal trays for Healthy Choice, Banquet, Kid Cuisine and Marie Callender's used 30 to 40 percent post-consumer recycled plastic (https://progressivegrocer.com/conagra-unveils-new-eco-friendly-frozen-tray-design), described as a dual-ovenable monolayer rPET tray (https://www.foodingredientsfirst.com/news/a-first-in-monolayer-rpet-trays-used-by-conagra-foods-for-its-frozen-entrees-and-meals.html). Not confirmed for this current SKU. | AA46: inferred CPET (oven-safe tray) | AB46: https://smartlabel.labelinsight.com/product/18110872/other/instructions https://smartlabel.labelinsight.com/product/18110872/nutrition
A47: zw-113 | B47: Marie Callender's | C47: Creamy Chicken & Dumplings Bowl | D47: 021131500856 | E47: frozen_tray | F47: 12 | G47: 340 | H47: =IF(G47<>"",G47,IF(F47<>"",ROUND(F47*28.3495,0),"")) -> 340 | I47: 1 | J47: 340 | K47: 14 | L47: 0 | M47: =IF(H47="","",H47+L47) -> 340 | N47: =IF(OR(K47="",M47=""),"",IF(J47<>"",K47/J47*H47/M47,IF(I47<>"",K47*I47/M47,""))) -> 0.041176471 | O47: =IF(N47="","",IF(N47<FoodClasses!$C$2,"lean",IF(N47<FoodClasses!$C$3,"medium","fatty"))) -> medium | P47: frozen | Q47: cpet_tray | R47: inferred | S47: The same tray goes into a 350-375 F oven, which plastic other than CPET does not survive. | T47: 1100 | U47: complete | V47: no | W47: None given. Label says appliances vary and to adjust times. | X47: Do not prepare in toaster oven | Keep frozen. Do not thaw. | Cook only one at a time | Y47: 375°F, do not remove film, on baking sheet 50-55 min, stand 2 min, stir. | Z47: Film-covered bowl; same bowl goes in the 375°F oven with film left on. Material not stated on label. Brand-level only: Conagra said c. 2009 that nearly all frozen meal trays for Healthy Choice, Banquet, Kid Cuisine and Marie Callender's used 30 to 40 percent post-consumer recycled plastic (https://progressivegrocer.com/conagra-unveils-new-eco-friendly-frozen-tray-design), described as a dual-ovenable monolayer rPET tray (https://www.foodingredientsfirst.com/news/a-first-in-monolayer-rpet-trays-used-by-conagra-foods-for-its-frozen-entrees-and-meals.html). Not confirmed for this current SKU. | AA47: inferred CPET (oven-safe tray) | no microwave stand time listed (oven directions give 2 min) | AB47: https://smartlabel.labelinsight.com/product/17457319/other/instructions https://smartlabel.labelinsight.com/product/17457319/nutrition
A48: zw-114 | B48: Hungry-Man | C48: Country Fried Chicken Dinner | D48: 051000118608 | E48: frozen_tray | F48: 16 | G48: 454 | H48: =IF(G48<>"",G48,IF(F48<>"",ROUND(F48*28.3495,0),"")) -> 454 | I48: 1 | J48: 454 | K48: 27 | L48: 0 | M48: =IF(H48="","",H48+L48) -> 454 | N48: =IF(OR(K48="",M48=""),"",IF(J48<>"",K48/J48*H48/M48,IF(I48<>"",K48*I48/M48,""))) -> 0.059471366 | O48: =IF(N48="","",IF(N48<FoodClasses!$C$2,"lean",IF(N48<FoodClasses!$C$3,"medium","fatty"))) -> medium | P48: frozen | Q48: cpet_tray | R48: inferred | S48: The same tray goes into a 350-375 F oven, which plastic other than CPET does not survive. | T48: 1100 | U48: complete | V48: no | W48: None given. Label says appliances vary and to adjust times. | X48: Do not prepare in toaster oven | Keep frozen. Do not thaw. | Cook only one at a time | Y48: 350°F, remove dessert film, slit film over chicken, on baking sheet 40-45 min, stand 2 min, stir potatoes. | Z48: Film-covered compartment tray with a dessert compartment; same tray goes in the 350°F oven. Material not stated on label. Hungry-Man came to Conagra with Pinnacle Foods (2018), so the 2009 Conagra tray statements do not cover it. | AA48: inferred CPET (oven-safe tray) | fetch tool returned the steps paraphrased, not verbatim; re-check wording | UPC prefix 051000 differs from the other Hungry-Man item (658276); recorded as shown | AB48: https://smartlabel.labelinsight.com/product/6319477/other/instructions https://smartlabel.labelinsight.com/product/6319477/nutrition
A49: zw-115 | B49: Hungry-Man | C49: Combos Meatloaf & BBQ Sauced Chicken | D49: 658276202484 | E49: frozen_tray | F49: 15 | G49: 425 | H49: =IF(G49<>"",G49,IF(F49<>"",ROUND(F49*28.3495,0),"")) -> 425 | I49: 1 | J49: 425 | K49: 26 | L49: 0 | M49: =IF(H49="","",H49+L49) -> 425 | N49: =IF(OR(K49="",M49=""),"",IF(J49<>"",K49/J49*H49/M49,IF(I49<>"",K49*I49/M49,""))) -> 0.061176471 | O49: =IF(N49="","",IF(N49<FoodClasses!$C$2,"lean",IF(N49<FoodClasses!$C$3,"medium","fatty"))) -> medium | P49: frozen | Q49: cpet_tray | R49: inferred | S49: The same tray goes into a 350-375 F oven, which plastic other than CPET does not survive. | T49: 1100 | U49: complete | V49: no | W49: None given. Label says appliances vary and to adjust times. | X49: Do not prepare in toaster oven | Keep frozen. Do not thaw. | Cook only one at a time | Y49: 350°F, slit film, on baking sheet 43-46 min, stand 2 min. | Z49: Film-covered compartment tray; same tray goes in the 350°F oven. Material not stated on label. Hungry-Man came to Conagra with Pinnacle Foods (2018), so the 2009 Conagra tray statements do not cover it. | AA49: inferred CPET (oven-safe tray) | AB49: https://smartlabel.labelinsight.com/product/17450027/other/instructions https://smartlabel.labelinsight.com/product/17450027/nutrition
A50: zw-116 | B50: P.F. Chang's | C50: Whole Grain Brown Rice (frozen microwave pouches) | D50: 031000700065 | E50: pouch | F50: 8 | H50: =IF(G50<>"",G50,IF(F50<>"",ROUND(F50*28.3495,0),"")) -> 227 | I50: 1 | J50: 227 | K50: 2.5 | L50: 0 | M50: =IF(H50="","",H50+L50) -> 227 | N50: =IF(OR(K50="",M50=""),"",IF(J50<>"",K50/J50*H50/M50,IF(I50<>"",K50*I50/M50,""))) -> 0.011013216 | O50: =IF(N50="","",IF(N50<FoodClasses!$C$2,"lean",IF(N50<FoodClasses!$C$3,"medium","fatty"))) -> lean | P50: frozen | Q50: steam_bag | R50: inferred | S50: Self-venting frozen microwave rice bag. | T50: 1100 | U50: complete | V50: no | W50: None given. Label says appliances vary and to adjust times. | X50: Do not puncture (bag self-vents) | Keep frozen. Do not thaw. | Cook only one at a time | Z50: Self-venting microwave pouch; carton appears to hold 2 pouches. Material not stated. | AA50: carton likely holds 2 pouches (serving = 1 microwaveable bag, 227 g, 2 servings); check package | 'Home Menu' line name not shown on the SmartLabel page | stovetop directions on label: 2 tbsp water in saucepan, covered on medium 6-7 min, stand 1 min. | 2 pouches; the label time is for one pouch (227 g). | AB50: https://smartlabel.labelinsight.com/product/5005127/other/instructions https://smartlabel.labelinsight.com/product/5005127/nutrition
A51: zw-117 | B51: P.F. Chang's | C51: Signature Fried Rice (frozen steam bag) | D51: 031000198763 | E51: steam_bag | F51: 16 | G51: 454 | H51: =IF(G51<>"",G51,IF(F51<>"",ROUND(F51*28.3495,0),"")) -> 454 | I51: 2.5 | J51: 196 | K51: 3 | L51: 0 | M51: =IF(H51="","",H51+L51) -> 454 | N51: =IF(OR(K51="",M51=""),"",IF(J51<>"",K51/J51*H51/M51,IF(I51<>"",K51*I51/M51,""))) -> 0.015306122 | O51: =IF(N51="","",IF(N51<FoodClasses!$C$2,"lean",IF(N51<FoodClasses!$C$3,"medium","fatty"))) -> lean | P51: frozen | Q51: steam_bag | R51: label | S51: Microwave steam bag or pouch. | T51: 1100 | U51: complete | V51: no | W51: None given. Label says appliances vary and to adjust times. | X51: Do not puncture (bag self-vents) | Cook only one bag at a time | Keep frozen. Do not thaw. | Z51: Self-venting microwave bag printed 'This Side Up, Lay Flat When Microwaving', 'Tear Here', 'Pick Up Here'. Material not stated. | AA51: servings per container listed as 'about 2.5' | stovetop directions on label: nonstick skillet, 2 tsp oil, 5-8 min stirring. | AB51: https://smartlabel.labelinsight.com/product/18164632/other/instructions https://smartlabel.labelinsight.com/product/18164632/nutrition
A52: zw-118 | B52: P.F. Chang's | C52: Chicken Fried Rice skillet meal (22 oz) | D52: 031000700003 | E52: oven_only | F52: 22 | G52: 624 | H52: =IF(G52<>"",G52,IF(F52<>"",ROUND(F52*28.3495,0),"")) -> 624 | I52: 3 | J52: 211 | K52: 6 | L52: 0 | M52: =IF(H52="","",H52+L52) -> 624 | N52: =IF(OR(K52="",M52=""),"",IF(J52<>"",K52/J52*H52/M52,IF(I52<>"",K52*I52/M52,""))) -> 0.028436019 | O52: =IF(N52="","",IF(N52<FoodClasses!$C$2,"lean",IF(N52<FoodClasses!$C$3,"medium","fatty"))) -> lean | P52: frozen | Q52: stove_pot | R52: label | S52: Skillet meal: contents go into a pan. | U52: not_applicable | V52: unknown | X52: Cook only one bag at a time | Keep frozen. Do not thaw. | Z52: Skillet-meal bag (contents are emptied into a pan). Material not stated. | AA52: stovetop-only product: label gives no microwave directions but also no explicit 'do not microwave', so do_not_microwave is null | category oven_only used for 'no microwave method'; schema has no stovetop category | servings per container listed as 'about 3' | 'Home Menu' line name not shown on the SmartLabel page | stovetop directions on label: hot nonstick skillet, 1 tbsp oil, covered 4 min, then uncovered 4-6 min stirring, to 165°F. | AB52: https://smartlabel.labelinsight.com/product/18466359/other/instructions https://smartlabel.labelinsight.com/product/18466359/nutrition
A53: zw-119 | B53: Birds Eye | C53: Steamfresh Power Blend California Style | D53: 014500015792 | E53: steam_bag | F53: 10.8 | G53: 306 | H53: =IF(G53<>"",G53,IF(F53<>"",ROUND(F53*28.3495,0),"")) -> 306 | I53: 1 | J53: 306 | K53: 6 | L53: 0 | M53: =IF(H53="","",H53+L53) -> 306 | N53: =IF(OR(K53="",M53=""),"",IF(J53<>"",K53/J53*H53/M53,IF(I53<>"",K53*I53/M53,""))) -> 0.019607843 | O53: =IF(N53="","",IF(N53<FoodClasses!$C$2,"lean",IF(N53<FoodClasses!$C$3,"medium","fatty"))) -> lean | P53: frozen | Q53: steam_bag | R53: label | S53: Microwave steam bag or pouch. | T53: 1100 | U53: complete | V53: no | W53: None given. Label says appliances vary and to adjust times. | X53: Do not pierce bag | Cook only one bag at a time | Keep frozen. Do not thaw. | Z53: Steam bag cooked flat 'this side up'; inflates and vents steam (may whistle); lift by marked corners, tear at notch. Material not stated. | AA53: fetch tool returned the steps paraphrased, not verbatim; re-check wording | stovetop directions on label: 2-qt nonstick saucepan, 1/4 cup water, covered on medium 8-12 min, stand 1-2 min. | AB53: https://smartlabel.labelinsight.com/product/10671730/other/instructions https://smartlabel.labelinsight.com/product/10671730/nutrition
A54: zw-120 | B54: Birds Eye | C54: Steamfresh Power Blend Southwest Style, 4 Pack | D54: 014500016898 | E54: steam_bag | F54: 12.7 | H54: =IF(G54<>"",G54,IF(F54<>"",ROUND(F54*28.3495,0),"")) -> 360 | I54: 1 | J54: 360 | K54: 2.5 | L54: 0 | M54: =IF(H54="","",H54+L54) -> 360 | N54: =IF(OR(K54="",M54=""),"",IF(J54<>"",K54/J54*H54/M54,IF(I54<>"",K54*I54/M54,""))) -> 0.0069444444 | O54: =IF(N54="","",IF(N54<FoodClasses!$C$2,"lean",IF(N54<FoodClasses!$C$3,"medium","fatty"))) -> lean | P54: frozen | Q54: steam_bag | R54: label | S54: Microwave steam bag or pouch. | T54: 1100 | U54: complete | V54: no | W54: None given. Label says appliances vary and to adjust times. | X54: Do not pierce bag | Cook only one bag at a time | Keep frozen. Do not thaw. | Z54: Steam bag cooked flat 'this side up'; inflates and vents steam (may whistle); lift by marked corners, tear at notch. Material not stated. 4 bags per carton. | AA54: multipack: 4 bags of 12.7 oz (360 g); directions are per bag | label gives 1.44 kg; stored as 1440 g | stovetop directions on label: 2-qt nonstick saucepan, 2 tbsp water, covered on medium 9-14 min, stand 1-2 min. | 4-pack; the label time is for one bag (360 g, one serving). | AB54: https://smartlabel.labelinsight.com/product/6362189/other/instructions https://smartlabel.labelinsight.com/product/6362189/nutrition
A55: zw-121 | B55: Birds Eye | C55: Steamfresh Broccoli, Cauliflower & Carrots, 4 Pack | D55: 014500015662 | E55: steam_bag | F55: 12 | H55: =IF(G55<>"",G55,IF(F55<>"",ROUND(F55*28.3495,0),"")) -> 340 | I55: 4 | J55: 84 | K55: 0 | L55: 0 | M55: =IF(H55="","",H55+L55) -> 340 | N55: =IF(OR(K55="",M55=""),"",IF(J55<>"",K55/J55*H55/M55,IF(I55<>"",K55*I55/M55,""))) -> 0 | O55: =IF(N55="","",IF(N55<FoodClasses!$C$2,"lean",IF(N55<FoodClasses!$C$3,"medium","fatty"))) -> lean | P55: frozen | Q55: steam_bag | R55: label | S55: Microwave steam bag or pouch. | U55: complete | V55: no | W55: Below 800 W the label says to use stovetop directions. | X55: Do not pierce bag | Microwave only one bag at a time | Keep frozen. Do not thaw. | Z55: Steam bag cooked flat 'this side up'; inflates and vents steam (may whistle); lift by marked corners, tear at notch. Material not stated. 4 bags per carton. | AA55: multipack: 4 bags of 12 oz (340 g); directions are per bag | label gives 1.36 kg; stored as 1360 g | servings per container listed as 'about 16' | stovetop stand time text is garbled on SmartLabel | fetch tool returned the steps paraphrased, not verbatim; re-check wording | same product line as zw-119/120 but uses a wattage table instead of a single 1100 W reference | stovetop directions on label: 2-qt nonstick saucepan, 1/2 cup water, covered on medium 7-8 min, drain. | 4-pack (48 oz, 16 servings); the label time is for one bag, taken as 12 oz and 4 servings. | AB55: https://smartlabel.labelinsight.com/product/6190170/other/instructions https://smartlabel.labelinsight.com/product/6190170/nutrition
A56: zw-122 | B56: Orville Redenbacher's | C56: Microwave Popcorn Sea Salt Made With 100% Avocado Oil, 12 Mini Bags | D56: 027000072875 | E56: popcorn_bag | F56: 14.39 | G56: 408 | H56: =IF(G56<>"",G56,IF(F56<>"",ROUND(F56*28.3495,0),"")) -> 408 | I56: 12 | J56: 34 | K56: 5 | L56: 0 | M56: =IF(H56="","",H56+L56) -> 408 | N56: =IF(OR(K56="",M56=""),"",IF(J56<>"",K56/J56*H56/M56,IF(I56<>"",K56*I56/M56,""))) -> 0.14705882 | O56: =IF(N56="","",IF(N56<FoodClasses!$C$2,"lean",IF(N56<FoodClasses!$C$3,"medium","fatty"))) -> fatty | P56: shelf | Q56: popcorn_bag | R56: label | S56: Microwave popcorn bag. | U56: partial | V56: no | W56: No wattage stated. Label gives a time range on HIGH and says to stop when popping slows. | X56: Do not use popcorn button | Children should not prepare without adult supervision | Z56: Microwave popcorn bag. Bag paper and grease-resistant coating are not stated on the label, and no Orville Redenbacher's packaging or PFAS statement was found. 12 bags of 1.2 oz (34 g). | AA56: label states no wattage; popcorn directions rely on listening for popping to slow, so 'partial' follows the schema rule rather than missing data | fetch tool returned the steps paraphrased, not verbatim; re-check wording | AB56: https://smartlabel.labelinsight.com/product/11000646/other/instructions https://smartlabel.labelinsight.com/product/11000646/nutrition
A57: zw-123 | B57: Orville Redenbacher's | C57: Microwave Popcorn Pour Over Movie Theater Butter, 2 Bags & Pouches | D57: 027000485392 | E57: popcorn_bag | F57: 9.9 | G57: 280.8 | H57: =IF(G57<>"",G57,IF(F57<>"",ROUND(F57*28.3495,0),"")) -> 280.8 | I57: 8 | J57: 33 | K57: 14 | L57: 0 | M57: =IF(H57="","",H57+L57) -> 280.8 | N57: =IF(OR(K57="",M57=""),"",IF(J57<>"",K57/J57*H57/M57,IF(I57<>"",K57*I57/M57,""))) -> 0.42424242 | O57: =IF(N57="","",IF(N57<FoodClasses!$C$2,"lean",IF(N57<FoodClasses!$C$3,"medium","fatty"))) -> fatty | P57: shelf | Q57: popcorn_bag | R57: label | S57: Microwave popcorn bag. | U57: partial | V57: no | W57: No wattage stated. Label gives a time range on HIGH and says to stop when popping slows. | X57: Do not use popcorn button | Children should not prepare without adult supervision | Z57: Microwave popcorn bag. Bag paper and grease-resistant coating are not stated on the label, and no Orville Redenbacher's packaging or PFAS statement was found. 2 bags of 107.3 g plus 2 separate topping pouches of 33.1 g (topping is not in the bag). | AA57: label states no wattage; popcorn directions rely on listening for popping to slow, so 'partial' follows the schema rule rather than missing data | servings listed as 'about 8' (about 4 per bag) | 14 g fat per 33 g serving recorded as found; check whether the figure includes the topping | AB57: https://smartlabel.labelinsight.com/product/10779734/other/instructions https://smartlabel.labelinsight.com/product/10779734/nutrition
A58: zw-124 | B58: Orville Redenbacher's | C58: Microwave Popcorn Butter & Sea Salt, 10 Mini Bags | D58: 027000623244 | E58: popcorn_bag | F58: 15 | G58: 425 | H58: =IF(G58<>"",G58,IF(F58<>"",ROUND(F58*28.3495,0),"")) -> 425 | I58: 10 | J58: 42.5 | K58: 6 | L58: 0 | M58: =IF(H58="","",H58+L58) -> 425 | N58: =IF(OR(K58="",M58=""),"",IF(J58<>"",K58/J58*H58/M58,IF(I58<>"",K58*I58/M58,""))) -> 0.14117647 | O58: =IF(N58="","",IF(N58<FoodClasses!$C$2,"lean",IF(N58<FoodClasses!$C$3,"medium","fatty"))) -> fatty | P58: shelf | Q58: popcorn_bag | R58: label | S58: Microwave popcorn bag. | U58: partial | V58: no | W58: No wattage stated. Label gives a time range on HIGH and says to stop when popping slows. | X58: Do not use popcorn button | Children should not prepare without adult supervision | Z58: Microwave popcorn bag. Bag paper and grease-resistant coating are not stated on the label, and no Orville Redenbacher's packaging or PFAS statement was found. 10 bags of 1.5 oz (42.5 g). | AA58: label states no wattage; popcorn directions rely on listening for popping to slow, so 'partial' follows the schema rule rather than missing data | AB58: https://smartlabel.labelinsight.com/product/10901633/other/instructions https://smartlabel.labelinsight.com/product/10901633/nutrition
A59: zw-125 | B59: Act II | C59: Light Butter Microwave Popcorn (foodservice case, 4 boxes x 18 packs) | E59: popcorn_bag | F59: 2.75 | H59: =IF(G59<>"",G59,IF(F59<>"",ROUND(F59*28.3495,0),"")) -> 78 | K59: 3 | L59: 0 | M59: =IF(H59="","",H59+L59) -> 78 | N59: =IF(OR(K59="",M59=""),"",IF(J59<>"",K59/J59*H59/M59,IF(I59<>"",K59*I59/M59,""))) | O59: =IF(N59="","",IF(N59<FoodClasses!$C$2,"lean",IF(N59<FoodClasses!$C$3,"medium","fatty"))) | P59: shelf | Q59: popcorn_bag | R59: label | S59: Microwave popcorn bag. | U59: partial | V59: no | W59: No wattage stated. Label gives a time range on HIGH and says to stop when popping slows. | X59: Do not use popcorn button | Children should not prepare without adult supervision | Z59: Microwave popcorn bag. Conagra wrote in a 10 Feb 2023 email quoted by IPEN that it removed PFAS in 2022 from the packaging used for Act II microwave popcorn in the U.S. (https://ipen.org/wp-content/uploads/2023/03/2023_03_r_en_pfas_popcorn_web.pdf). The replacement grease barrier is not described. | AA59: label states no wattage; popcorn directions rely on listening for popping to slow, so 'partial' follows the schema rule rather than missing data | source is a Conagra Foodservice listing, not a retail label transcription; Act II was not found on SmartLabel | UPC not shown; page gives foodservice SKU 7615023244, which is not a UPC | per-bag size read as '2.75 OZ' from a garbled field ('Net Weight 12.38' with no unit also shown); grams not given | servings per bag not listed | AB59: https://www.conagrafoodservice.com/products/act-ii-light-butter-popcorn-4-boxes-18-packs https://ipen.org/wp-content/uploads/2023/03/2023_03_r_en_pfas_popcorn_web.pdf
A60: zw-126 | B60: Green Giant | C60: Seasoned Backyard Grilled Potatoes (roasted potatoes, peppers and onions) | D60: 020000449975 | E60: steam_bag | F60: 9 | G60: 255 | H60: =IF(G60<>"",G60,IF(F60<>"",ROUND(F60*28.3495,0),"")) -> 255 | I60: 2.5 | J60: 110 | K60: 3 | L60: 0 | M60: =IF(H60="","",H60+L60) -> 255 | N60: =IF(OR(K60="",M60=""),"",IF(J60<>"",K60/J60*H60/M60,IF(I60<>"",K60*I60/M60,""))) -> 0.027272727 | O60: =IF(N60="","",IF(N60<FoodClasses!$C$2,"lean",IF(N60<FoodClasses!$C$3,"medium","fatty"))) -> lean | P60: frozen | Q60: steam_bag | R60: label | S60: Microwave steam bag or pouch. | U60: complete | V60: no | W60: Table covers 700 W. | X60: Do not leave microwave unattended | Z60: Microwave-in bag cooked standing on a plate; tear notch. Vent not mentioned. Material not stated. | AA60: servings per container listed as 'about 2.5' (second column is 1/2 cup prepared) | AB60: https://smartlabel.labelinsight.com/product/6822662/other/instructions https://smartlabel.labelinsight.com/product/6822662/nutrition
A61: zw-127 | B61: Green Giant | C61: Garlic Parmesan Crispy Smashed Potatoes | D61: 190569679790 | E61: oven_only | F61: 12 | G61: 340 | H61: =IF(G61<>"",G61,IF(F61<>"",ROUND(F61*28.3495,0),"")) -> 340 | I61: 4 | J61: 79 | K61: 2 | L61: 0 | M61: =IF(H61="","",H61+L61) -> 340 | N61: =IF(OR(K61="",M61=""),"",IF(J61<>"",K61/J61*H61/M61,IF(I61<>"",K61*I61/M61,""))) -> 0.025316456 | O61: =IF(N61="","",IF(N61<FoodClasses!$C$2,"lean",IF(N61<FoodClasses!$C$3,"medium","fatty"))) -> lean | P61: frozen | Q61: paperboard_tray | R61: label | S61: Oven only, baked on the user's own sheet. | U61: not_applicable | V61: yes | X61: Microwave oven not recommended | Y61: 425°F, oiled baking sheet, single layer, bottom rack 18-20 min. | Z61: Box; potatoes are baked on the consumer's own baking sheet. Material not stated. | AA61: label wording is 'Microwave oven not recommended' rather than 'do not microwave' | oven directions sit under a SmartLabel heading named 'Microwave Manual Claim' | servings per container listed as 'about 4' | AB61: https://smartlabel.labelinsight.com/product/19949172/other/instructions https://smartlabel.labelinsight.com/product/19949172/nutrition
A62: zw-201 | B62: Hot Pockets | C62: Pepperoni Pizza Sandwiches, 2 count (sleeve-era package) | E62: sleeve | F62: 4.5 | H62: =IF(G62<>"",G62,IF(F62<>"",ROUND(F62*28.3495,0),"")) -> 128 | I62: 1 | K62: 15 | L62: 0 | M62: =IF(H62="","",H62+L62) -> 128 | N62: =IF(OR(K62="",M62=""),"",IF(J62<>"",K62/J62*H62/M62,IF(I62<>"",K62*I62/M62,""))) -> 0.1171875 | O62: =IF(N62="","",IF(N62<FoodClasses!$C$2,"lean",IF(N62<FoodClasses!$C$3,"medium","fatty"))) -> fatty | P62: frozen | Q62: susceptor_sleeve | R62: label | S62: Older pack with crisping sleeve (sleeves removed in 2024). | T62: 1100 | U62: complete | V62: no | W62: Lower wattage/compact microwave: 2 min 50 s for 1 sandwich; cook 2 sandwiches one at a time. | X62: Do not use crisping sleeve in air fryer | Oven: place on baking sheet without the crisping sleeve | Cook to internal temperature of 165°F | Keep frozen | Y62: Oven 350°F, unwrapped on baking sheet without sleeve, 26 min. Air fryer 360°F, 15 min in directions (16 min in description). | Z62: Individually wrapped sandwiches in a carton with a microwave crisping sleeve. Packaging Dive describes the Hot Pockets sleeves as microwave susceptor crisping sleeves. Brand FAQ says the sleeve is single use. Sleeve material not stated on the label text found. | AA62: Legacy package: Nestlé removed the crisping sleeve from Hot Pockets packaging (announced Sept 30, 2024) and replaced 2-packs with 4-packs during 2025, so this label likely matches only old stock. See zw-203 for the current sleeveless pepperoni box. | Source is a third-party delivery listing (Uber Eats, Safeway Flash) that says its information may not be current | Calories and serving size not shown on the listing; goodnes.com lists 330 kcal per 127 g sandwich for the current pepperoni product, not merged here | Air fryer time inconsistent on listing (15 vs 16 min) | UPC not shown | 2-pack (9 oz); the label time is for one sandwich. | AB62: https://www.ubereats.com/store/safeway-flash-225-brierhill-dr/u7Xdbrc1WzWBNHf2mgyltg/8bb157fb-7d37-5119-991d-88aa698ea51d/30db39c9-9a04-5985-b67a-179a84674fb8/f84bae16-f08d-5214-bee1-91be23d83aa9 https://www.goodnes.com/hot-pockets/faq https://www.packagingdive.com/news/packaging-innovations-hot-pockets-overtone-henkel/728876/
A63: zw-202 | B63: Hot Pockets | C63: Hickory Ham & Cheddar Crispy Buttery Crust Sandwiches, 2 count (sleeve-era package) | E63: sleeve | F63: 9 | H63: =IF(G63<>"",G63,IF(F63<>"",ROUND(F63*28.3495,0),"")) -> 255 | I63: 2 | K63: 10 | L63: 0 | M63: =IF(H63="","",H63+L63) -> 255 | N63: =IF(OR(K63="",M63=""),"",IF(J63<>"",K63/J63*H63/M63,IF(I63<>"",K63*I63/M63,""))) -> 0.078431373 | O63: =IF(N63="","",IF(N63<FoodClasses!$C$2,"lean",IF(N63<FoodClasses!$C$3,"medium","fatty"))) -> medium | P63: frozen | Q63: susceptor_sleeve | R63: label | S63: Older pack with crisping sleeve (sleeves removed in 2024). | U63: partial | V63: no | W63: Lower wattage/compact microwave: 2 min 50 s for 1 sandwich. For best results cook one at a time. | X63: Do not use crisping sleeve in oven | Cook to internal temperature of 165°F | Keep frozen | Y63: Oven 350°F, unwrapped on baking sheet without sleeve, 26 min. Air fryer 360°F, 16 min. | Z63: Individually wrapped sandwiches in a carton with a microwave crisping sleeve (susceptor sleeve per Packaging Dive). Sleeve is single use per brand FAQ. Material not stated. | AA63: Legacy package: sleeve removed from Hot Pockets packaging in the 2024 redesign; 2-packs replaced by 4-packs in 2025. Current Hannaford listing for the 4-ct croissant-crust ham & cheddar uses a microwave-safe plate with no sleeve. | Reference wattage not printed on the two listings (CVS listing says 'full-wattage ovens'; the current Hot Pockets range uses 1100 W) | Calories and serving size not shown; total fat 10 g from CVS listing | Third-party delivery listings (Uber Eats Walgreens/CVS) may not be current | UPC not shown | AB63: https://www.ubereats.com/store/walgreens-12407-grant-rd/c9_So-KORGOLsyZb6DFGKA/7f00a5db-35cb-5775-986f-cfd4d85a6310/7d7bff25-1880-4ae9-a9c1-83e7bfefca55/c4a39b83-b805-5ae9-9b39-d2361c6caa1a https://www.ubereats.com/store/cvs/rn4GRmLHWvCLWi_7CDHUYg/3d9e84e1-e36e-5c90-a0b7-71703dac0e0c/7d7bff25-1880-4ae9-a9c1-83e7bfefca55/61b1219f-c230-5c60-8f88-0978bc3bb467 https://www.goodnes.com/hot-pockets/faq https://www.packagingdive.com/news/packaging-innovations-hot-pockets-overtone-henkel/728876/
A64: zw-203 | B64: Hot Pockets | C64: Pepperoni Pizza Sandwiches (Italian Style Seasoned Crust), 4 Pack, current sleeveless package | D64: 00043695206203 | E64: plate | F64: 4.5 | H64: =IF(G64<>"",G64,IF(F64<>"",ROUND(F64*28.3495,0),"")) -> 128 | I64: 1 | J64: 127 | K64: 15 | L64: 0 | M64: =IF(H64="","",H64+L64) -> 128 | N64: =IF(OR(K64="",M64=""),"",IF(J64<>"",K64/J64*H64/M64,IF(I64<>"",K64*I64/M64,""))) -> 0.11811024 | O64: =IF(N64="","",IF(N64<FoodClasses!$C$2,"lean",IF(N64<FoodClasses!$C$3,"medium","fatty"))) -> fatty | P64: frozen | Q64: ceramic | R64: label | S64: Label says to heat on a microwave-safe plate. | T64: 1100 | U64: complete | V64: no | W64: Lower wattage/compact microwave: 2 min 50 s for 1 sandwich; cook 2 one at a time. | X64: Cook to internal temperature of 165°F | Product will be hot; let cool | Keep frozen | Y64: Air fryer 360°F, 14 min (1 sandwich, or 2 placed separately). No conventional oven directions on the goodnes.com page. | Z64: Carton of individually wrapped sandwiches, no crisping sleeve. Material not stated. | AA64: Category 'plate' is a proposed new value (see notes); listed under Hot Pockets for contrast with sleeve-era zw-201 | goodnes.com 8-pack and 1-pack pages give the same times | 4-pack; the label time is for one sandwich (127 g). | AB64: https://www.goodnes.com/hot-pockets/products/frozen-sandwich-pepperoni-pizza/ https://www.goodnes.com/hot-pockets/products/pepperoni-pizza-italian-seasoned-crust https://www.acmestores.com/product/00043695071115/hot-pockets-sandwiches-premium-garlic-buttery https://www.packagingdive.com/news/packaging-innovations-hot-pockets-overtone-henkel/728876/
A65: zw-204 | B65: Lean Cuisine | C65: Chicken Fettuccini | E65: frozen_tray | F65: 9.25 | G65: 262 | H65: =IF(G65<>"",G65,IF(F65<>"",ROUND(F65*28.3495,0),"")) -> 262 | I65: 1 | J65: 262 | K65: 5 | L65: 0 | M65: =IF(H65="","",H65+L65) -> 262 | N65: =IF(OR(K65="",M65=""),"",IF(J65<>"",K65/J65*H65/M65,IF(I65<>"",K65*I65/M65,""))) -> 0.019083969 | O65: =IF(N65="","",IF(N65<FoodClasses!$C$2,"lean",IF(N65<FoodClasses!$C$3,"medium","fatty"))) -> lean | P65: frozen | Q65: pp_container | R65: inferred | S65: Lean Cuisine FAQ says plastic trays [S69]; microwave-only directions point to PP. | T65: 1100 | U65: complete | V65: no | W65: Not on product page. Lean Cuisine FAQ: times are based on 1100 W; lower-wattage ovens may need more time, watch for bubbling over and check 165°F. | X65: Do not prepare in conventional or toaster ovens | Do not reheat tray | Z65: Film-covered plastic tray in paperboard carton. Lean Cuisine FAQ: plastic trays recyclable only where local programs accept them, paperboard carton recyclable, trays not designed for reuse. | AA65: Reference wattage taken from the Lean Cuisine FAQ ('All of our entrees ... based on ... an 1100-watt microwave oven'); the product page shows no wattage | Page says both 'Do not reheat tray' and 'Do not reheat bowl' | UPC not shown | AB65: https://www.goodnes.com/lean-cuisine/products/chicken-fettuccine https://www.goodnes.com/lean-cuisine/faq
A66: zw-205 | B66: Lean Cuisine | C66: Sesame Chicken (listed as Signature; Hannaford URL says Protein Kick) | E66: frozen_tray | F66: 9 | H66: =IF(G66<>"",G66,IF(F66<>"",ROUND(F66*28.3495,0),"")) -> 255 | I66: 1 | K66: 10 | L66: 0 | M66: =IF(H66="","",H66+L66) -> 255 | N66: =IF(OR(K66="",M66=""),"",IF(J66<>"",K66/J66*H66/M66,IF(I66<>"",K66*I66/M66,""))) -> 0.039215686 | O66: =IF(N66="","",IF(N66<FoodClasses!$C$2,"lean",IF(N66<FoodClasses!$C$3,"medium","fatty"))) -> medium | P66: frozen | Q66: pp_container | R66: inferred | S66: Lean Cuisine FAQ says plastic trays [S69]; microwave-only directions point to PP. | T66: 1100 | U66: complete | V66: no | W66: None on page. Lean Cuisine FAQ: lower-wattage ovens may need more time. | X66: Microwave oven only | Do not prepare in conventional or toaster ovens | Do not reheat tray | Keep frozen | Z66: Film-covered tray; film is removed for the second heating step. Material not stated on page. | AA66: Page prints 'Microwave Oven Only: 110 watts', read as a typo for 1100 W because the Lean Cuisine FAQ states all entrée times are based on 1100 W | Product line name differs between page title (Signature) and URL (Protein Kick); photograph the box | UPC not shown | AB66: https://www.hannaford.com/groceries/product/lean-cuisine-protein-kick-sesame-chicken-frozen-meal-9-oz-box/129833 https://www.goodnes.com/lean-cuisine/faq
A67: zw-206 | B67: Stouffer's | C67: Lasagna with Meat & Sauce (single serve, For One) | E67: frozen_tray | G67: 297 | H67: =IF(G67<>"",G67,IF(F67<>"",ROUND(F67*28.3495,0),"")) -> 297 | I67: 1 | J67: 297 | K67: 12 | L67: 0 | M67: =IF(H67="","",H67+L67) -> 297 | N67: =IF(OR(K67="",M67=""),"",IF(J67<>"",K67/J67*H67/M67,IF(I67<>"",K67*I67/M67,""))) -> 0.04040404 | O67: =IF(N67="","",IF(N67<FoodClasses!$C$2,"lean",IF(N67<FoodClasses!$C$3,"medium","fatty"))) -> medium | P67: frozen | Q67: pet_board_tray | R67: inferred | S67: Stouffer's single-serve trays are paper [S68]; this one goes into the oven, so it is taken as PET-coated board. | T67: 1100 | U67: complete | V67: no | W67: None given. Page says ovens vary and time may need adjusting. | X67: Do not vent film before first cook | Do not prepare in toaster oven | Do not reheat tray | Keep frozen | Y67: 375°F, film on and not vented, tray on baking sheet center rack, 40 min, stand 1 min. | Z67: Film-covered tray that is also used in the conventional oven. Stouffer's FAQ: single-serve trays moved from plastic to paper (pressed paper trays in select single-serve meals not yet recyclable); plastic trays contain 25% recycled plastic. Which tray this item uses is not stated. | AA67: Two-power-level directions (HIGH then 50%) are a useful case for the app's power-level logic | Kroger-family item code comes from search-result URLs for 'Classic Lasagna with Meat and Sauce' (not fetched); UPC not shown | goodnes.com page's canonical tag points to the Family Size product | AB67: https://www.goodnes.com/stouffers/products/lasagna-with-meat-sauce-for-one/ https://www.goodnes.com/stouffers/faq
A68: zw-207 | B68: Stouffer's | C68: French Bread Deluxe Pizza, 2 count | E68: oven_only | F68: 12.75 | H68: =IF(G68<>"",G68,IF(F68<>"",ROUND(F68*28.3495,0),"")) -> 361 | I68: 2 | K68: 21 | L68: 0 | M68: =IF(H68="","",H68+L68) -> 361 | N68: =IF(OR(K68="",M68=""),"",IF(J68<>"",K68/J68*H68/M68,IF(I68<>"",K68*I68/M68,""))) -> 0.11634349 | O68: =IF(N68="","",IF(N68<FoodClasses!$C$2,"lean",IF(N68<FoodClasses!$C$3,"medium","fatty"))) -> fatty | P68: frozen | Q68: paperboard_tray | R68: label | S68: Oven or air fryer finish. | T68: 1100 | U68: complete | V68: no | X68: Keep frozen | Y68: Oven only: 400°F, baking sheet center rack, 24 min, stand 1 min. | Z68: Paperboard box ('Push in. Pull out.') with pizzas in a wrap; no crisping tray or sleeve mentioned. Material not stated. | AA68: Microwave step alone does not finish cooking; the app should say an oven or air fryer is required | Toaster oven not addressed | UPC not shown | AB68: https://www.hannaford.com/groceries/product/stouffers-french-bread-deluxe-pizza-2-ct-frozen-12-75-oz-box/720
A69: zw-208 | B69: Velveeta | C69: Original Shells & Cheese Microwaveable Cups | E69: cup_bowl | F69: 2.39 | H69: =IF(G69<>"",G69,IF(F69<>"",ROUND(F69*28.3495,0),"")) -> 68 | I69: 1 | K69: 8 | L69: 110 | M69: =IF(H69="","",H69+L69) -> 178 | N69: =IF(OR(K69="",M69=""),"",IF(J69<>"",K69/J69*H69/M69,IF(I69<>"",K69*I69/M69,""))) -> 0.04494382 | O69: =IF(N69="","",IF(N69<FoodClasses!$C$2,"lean",IF(N69<FoodClasses!$C$3,"medium","fatty"))) -> medium | P69: shelf | Q69: pp_container | R69: unknown | S69: Microwavable cup; material not stated (Kraft trialled a fibre cup in 2021). Check the base. | U69: partial | V69: no | X69: Add water to fill line to help prevent risk of fire | Do not leave microwave unattended | Do not drain | Do not reuse cup | Cup and contents will be very hot | Z69: Single-serve microwavable cup with lid, fill line and cheese sauce pouch. Label: 'Starch blend in cup reduces risk of boil over and thickens sauce.' Material not stated. | AA69: No wattage or stand time on label transcription | Servings per container 8 for the 8-ct box (H-E-B 4-ct box lists 4) | H-E-B warning says 'POUCH AND CONTENTS WILL BE VERY HOT' while Hannaford says 'Cup and contents' | UPC not shown | Sold in multi-cup boxes; one cup is the product. | AB69: https://www.hannaford.com/groceries/product/velveeta-original-shells-cheese-pasta-microwaveable-cup-8-ct-19-1-oz-box/215301 https://www.heb.com/product-detail/velveeta-original-shells-and-cheese-cups/1256845
A70: zw-209 | B70: Kraft | C70: Triple Cheese Mac & Cheese Dinner Microwaveable Cups | E70: cup_bowl | F70: 2.05 | H70: =IF(G70<>"",G70,IF(F70<>"",ROUND(F70*28.3495,0),"")) -> 58 | I70: 1 | K70: 3.5 | L70: 110 | M70: =IF(H70="","",H70+L70) -> 168 | N70: =IF(OR(K70="",M70=""),"",IF(J70<>"",K70/J70*H70/M70,IF(I70<>"",K70*I70/M70,""))) -> 0.020833333 | O70: =IF(N70="","",IF(N70<FoodClasses!$C$2,"lean",IF(N70<FoodClasses!$C$3,"medium","fatty"))) -> lean | P70: shelf | Q70: pp_container | R70: unknown | S70: Microwavable cup; material not stated (Kraft trialled a fibre cup in 2021). Check the base. | U70: partial | V70: no | X70: Add water to fill line to help prevent risk of fire | Do not leave microwave unattended | Do not drain | Do not reuse cup | Cup and contents will be very hot | Z70: Single-serve microwavable cup with lid and fill line. Material not stated. Kraft tested a recyclable fiber-based microwavable cup in 2021 (see packaging_statements); whether the current cup is fiber-based is not confirmed. | AA70: No wattage or stand time on label transcription | UPC not shown | Sold in multi-cup boxes; one cup is the product. | AB70: https://www.hannaford.com/groceries/product/kraft-triple-cheese-mac-cheese-dinner-microwaveable-cup-4-ct-8-2-oz-pkg/196513
A71: zw-210 | B71: Annie's | C71: Organic White Cheddar Macaroni & Cheese Cups | E71: cup_bowl | F71: 2.01 | H71: =IF(G71<>"",G71,IF(F71<>"",ROUND(F71*28.3495,0),"")) -> 57 | I71: 1 | K71: 5 | L71: 110 | M71: =IF(H71="","",H71+L71) -> 167 | N71: =IF(OR(K71="",M71=""),"",IF(J71<>"",K71/J71*H71/M71,IF(I71<>"",K71*I71/M71,""))) -> 0.02994012 | O71: =IF(N71="","",IF(N71<FoodClasses!$C$2,"lean",IF(N71<FoodClasses!$C$3,"medium","fatty"))) -> lean | P71: shelf | Q71: pp_container | R71: unknown | S71: Microwavable cup; material not stated (Kraft trialled a fibre cup in 2021). Check the base. | U71: partial | V71: no | X71: Cup and pasta will be very hot | Z71: Single-serve microwavable cup with lid and fill line. Material not stated. | AA71: No wattage or stand time on label transcription | UPC not shown | Sold in multi-cup boxes; one cup is the product. | AB71: https://www.hannaford.com/groceries/product/annies-macaroni-cheese-white-cheddar-cups-organic-4-ct-8-04-oz-box/229390
A72: zw-211 | B72: Annie's | C72: Deluxe Microwavable Classic Cheddar Shells & Cheese Cups | E72: cup_bowl | F72: 2.6 | H72: =IF(G72<>"",G72,IF(F72<>"",ROUND(F72*28.3495,0),"")) -> 74 | I72: 1 | K72: 6 | L72: 110 | M72: =IF(H72="","",H72+L72) -> 184 | N72: =IF(OR(K72="",M72=""),"",IF(J72<>"",K72/J72*H72/M72,IF(I72<>"",K72*I72/M72,""))) -> 0.032608696 | O72: =IF(N72="","",IF(N72<FoodClasses!$C$2,"lean",IF(N72<FoodClasses!$C$3,"medium","fatty"))) -> medium | P72: shelf | Q72: pp_container | R72: unknown | S72: Microwavable cup; material not stated (Kraft trialled a fibre cup in 2021). Check the base. | U72: partial | V72: no | X72: Cup and pasta will be very hot | Z72: Single-serve microwavable cup with lid, fill line and cheese sauce packet. Material not stated. | AA72: No wattage or stand time | Two-stage heating with a stir between (3 min total) | UPC not shown | Listing gives the 4-cup box (10.4 oz); one cup is taken as 2.6 oz. | AB72: https://www.hannaford.com/groceries/product/annies-deluxe-microwavable-classic-cheddar-shells-cheese-cups-4-ct-10-4-oz-pkg/263764
A73: zw-212 | B73: Hormel | C73: Compleats Homestyle Chicken Alfredo | E73: cup_bowl | F73: 10 | H73: =IF(G73<>"",G73,IF(F73<>"",ROUND(F73*28.3495,0),"")) -> 283 | I73: 1 | K73: 18 | L73: 0 | M73: =IF(H73="","",H73+L73) -> 283 | N73: =IF(OR(K73="",M73=""),"",IF(J73<>"",K73/J73*H73/M73,IF(I73<>"",K73*I73/M73,""))) -> 0.06360424 | O73: =IF(N73="","",IF(N73<FoodClasses!$C$2,"lean",IF(N73<FoodClasses!$C$3,"medium","fatty"))) -> medium | P73: shelf | Q73: pp_container | R73: inferred | S73: Shelf-stable plastic microwave tray (retailer titles). | U73: partial | V73: no | X73: Not for use in conventional ovens | Contents and tray will be hot | No refrigeration needed until opened | Z73: Shelf-stable microwavable tray sealed with film. Walmart listing titles for other Compleats varieties call it a 'Plastic Tray' / 'Plastic Microwaveable Tray'; resin not stated. | AA73: No wattage or power level stated | Kroger-family item code from Fred Meyer/City Market search-result URLs (not fetched); UPC not shown | Servings per container blank on page; 1 assumed from 'serving size 1 tray' | AB73: https://www.hannaford.com/groceries/product/hormel-compleats-homestyle-chicken-alfredo-microwavable-10-oz-pkg/155818
A74: zw-213 | B74: Dinty Moore | C74: Beef Stew Microwavable (single tray) | E74: cup_bowl | F74: 9 | H74: =IF(G74<>"",G74,IF(F74<>"",ROUND(F74*28.3495,0),"")) -> 255 | I74: 1 | K74: 12 | L74: 0 | M74: =IF(H74="","",H74+L74) -> 255 | N74: =IF(OR(K74="",M74=""),"",IF(J74<>"",K74/J74*H74/M74,IF(I74<>"",K74*I74/M74,""))) -> 0.047058824 | O74: =IF(N74="","",IF(N74<FoodClasses!$C$2,"lean",IF(N74<FoodClasses!$C$3,"medium","fatty"))) -> medium | P74: shelf | Q74: pp_container | R74: inferred | S74: Shelf-stable plastic microwave tray (retailer titles). | U74: partial | V74: no | X74: Not for use in conventional ovens | Contents and tray will be hot | Z74: Shelf-stable microwavable tray sealed with film. Material not stated. | AA74: No wattage stated | Directions identical to Hormel Compleats wording | UPC not shown | AB74: https://www.hannaford.com/groceries/product/dinty-moore-beef-stew-microwavable-9-oz-pkg/155823
A75: zw-214 | B75: Campbell's | C75: Chunky Chili Mac, Microwavable Bowl | D75: 51000286298 | E75: cup_bowl | F75: 15.25 | H75: =IF(G75<>"",G75,IF(F75<>"",ROUND(F75*28.3495,0),"")) -> 432 | I75: 1 | K75: 12 | L75: 0 | M75: =IF(H75="","",H75+L75) -> 432 | N75: =IF(OR(K75="",M75=""),"",IF(J75<>"",K75/J75*H75/M75,IF(I75<>"",K75*I75/M75,""))) -> 0.027777778 | O75: =IF(N75="","",IF(N75<FoodClasses!$C$2,"lean",IF(N75<FoodClasses!$C$3,"medium","fatty"))) -> lean | P75: shelf | Q75: pp_container | R75: inferred | S75: Microwavable plastic bowl or cup; remove any metal lid first. | U75: partial | V75: no | W75: Label: microwave ovens vary, time is approximate; uneven heating may cause popping, bowl movement or splattering. | X75: Plastic cap may be hot | Z75: Microwavable bowl with peel-off cover and plastic cap. Material not stated. | AA75: No reference wattage stated | AB75: https://www.campbellsfoodservice.com/product/chili-mac-soup/
A76: zw-215 | B76: Campbell's | C76: Chunky Meat Lovers Mac, Microwavable Bowl | E76: cup_bowl | F76: 15.25 | H76: =IF(G76<>"",G76,IF(F76<>"",ROUND(F76*28.3495,0),"")) -> 432 | I76: 1 | K76: 17 | L76: 0 | M76: =IF(H76="","",H76+L76) -> 432 | N76: =IF(OR(K76="",M76=""),"",IF(J76<>"",K76/J76*H76/M76,IF(I76<>"",K76*I76/M76,""))) -> 0.039351852 | O76: =IF(N76="","",IF(N76<FoodClasses!$C$2,"lean",IF(N76<FoodClasses!$C$3,"medium","fatty"))) -> medium | P76: shelf | Q76: pp_container | R76: inferred | S76: Microwavable plastic bowl or cup; remove any metal lid first. | U76: partial | V76: no | W76: Label: microwave ovens vary, time is approximate; uneven heating may cause popping, bowl movement or splattering. | X76: Do not add water | Do not reuse or reheat bowl | Do not purchase if open or punctured | Caution: metal edges are sharp | Plastic cap may be hot | Z76: Microwavable bowl with peel-off cover and plastic cap. Label warns 'Metal edges are sharp', which suggests a metal component in the cover or rim that is removed before heating; material otherwise not stated. | AA76: No reference wattage stated | The 'metal edges' warning is worth confirming on the package, since the app should tell users the cover must be fully removed before microwaving | UPC not shown | AB76: https://www.foodlion.com/groceries/product/campbells-chunky-bowl-meat-lovers-mac-microwavable-15-25-oz-cup/406128
A77: zw-216 | B77: Amy's | C77: Amy's Bowls Organic Gluten Free Broccoli & Cheddar Bake | E77: frozen_tray | F77: 9.5 | H77: =IF(G77<>"",G77,IF(F77<>"",ROUND(F77*28.3495,0),"")) -> 269 | I77: 1 | K77: 21 | L77: 0 | M77: =IF(H77="","",H77+L77) -> 269 | N77: =IF(OR(K77="",M77=""),"",IF(J77<>"",K77/J77*H77/M77,IF(I77<>"",K77*I77/M77,""))) -> 0.078066914 | O77: =IF(N77="","",IF(N77<FoodClasses!$C$2,"lean",IF(N77<FoodClasses!$C$3,"medium","fatty"))) -> medium | P77: frozen | Q77: cpet_tray | R77: unknown | S77: Amy's bowl or tray goes into the conventional oven; material not stated. | U77: partial | V77: no | W77: None given. Label says ovens may vary. | X77: Toaster oven: remove overwrap and bowl and use an oven-safe dish | Y77: 375°F, remove overwrap, bowl on baking sheet, 35-40 min, sit 1 min. Toaster oven: transfer to oven-safe dish. | Z77: Bowl in plastic overwrap; the bowl goes in a conventional oven at 375°F but must be replaced by an oven-safe dish in a toaster oven. Material not stated. | AA77: No reference wattage | amys.com product pages not readable (previous batch) | UPC not shown | AB77: https://www.hannaford.com/groceries/product/amys-bowls-organic-gluten-free-broccoli-cheddar-bake-frozen-meal-9-5-oz-box/187013
A78: zw-217 | B78: Amy's | C78: Organic Gluten Free Cheese Enchilada Whole Meal | E78: frozen_tray | F78: 9 | H78: =IF(G78<>"",G78,IF(F78<>"",ROUND(F78*28.3495,0),"")) -> 255 | I78: 1 | K78: 16 | L78: 0 | M78: =IF(H78="","",H78+L78) -> 255 | N78: =IF(OR(K78="",M78=""),"",IF(J78<>"",K78/J78*H78/M78,IF(I78<>"",K78*I78/M78,""))) -> 0.062745098 | O78: =IF(N78="","",IF(N78<FoodClasses!$C$2,"lean",IF(N78<FoodClasses!$C$3,"medium","fatty"))) -> medium | P78: frozen | Q78: cpet_tray | R78: unknown | S78: Amy's bowl or tray goes into the conventional oven; material not stated. | U78: partial | V78: no | W78: None given. Label says ovens may vary. | X78: Toaster oven: remove overwrap and tray and use an oven-safe dish | Y78: 375°F, remove overwrap, cover tray with foil, on baking sheet, 45-50 min, sit 1 min. | Z78: Multi-compartment tray in plastic overwrap; tray is used in the conventional oven (foil-covered) but not the toaster oven. Material not stated. | AA78: No reference wattage | Uses MEDIUM then HIGH power levels | UPC not shown | AB78: https://www.hannaford.com/groceries/product/amys-organic-gluten-free-cheese-enchilada-whole-frozen-meal-9-oz-box/44430
A79: zw-218 | B79: Jimmy Dean | C79: Meat Lovers Breakfast Bowl | D79: 00077900706158 | E79: frozen_tray | F79: 7 | H79: =IF(G79<>"",G79,IF(F79<>"",ROUND(F79*28.3495,0),"")) -> 198 | I79: 1 | K79: 37 | L79: 0 | M79: =IF(H79="","",H79+L79) -> 198 | N79: =IF(OR(K79="",M79=""),"",IF(J79<>"",K79/J79*H79/M79,IF(I79<>"",K79*I79/M79,""))) -> 0.18686869 | O79: =IF(N79="","",IF(N79<FoodClasses!$C$2,"lean",IF(N79<FoodClasses!$C$3,"medium","fatty"))) -> fatty | P79: frozen | Q79: pp_container | R79: inferred | S79: Microwave-only tray or bowl; label forbids the conventional oven or gives no oven method. | T79: 1100 | U79: complete | V79: no | W79: Label: microwaves below 1100 watts may need extra time to reach proper temperature. | X79: Do not cook in toaster oven | Keep frozen until ready to use | Product will be hot | Z79: Film-covered bowl in carton. Material not stated. | AB79: https://www.hannaford.com/groceries/product/jimmy-dean-meat-lovers-breakfast-bowl-frozen-meal-7-oz-box/199280 https://sites.salsify.com/aa1704a5-eac3-4658-8b85-aa434cec8f75/d7e6ef5f-f7bf-46e8-9328-73a03b469161/product/00077900706158/Jimmy-Dean-Breakfast-Bowl-Meat-Lovers-Frozen-7-oz-Bowl/
A80: zw-219 | B80: Jimmy Dean | C80: Delights Turkey Sausage, Egg White & Cheese English Muffin Sandwiches, 4 count | E80: plate | F80: 5.1 | H80: =IF(G80<>"",G80,IF(F80<>"",ROUND(F80*28.3495,0),"")) -> 145 | I80: 1 | K80: 8 | L80: 0 | M80: =IF(H80="","",H80+L80) -> 145 | N80: =IF(OR(K80="",M80=""),"",IF(J80<>"",K80/J80*H80/M80,IF(I80<>"",K80*I80/M80,""))) -> 0.055172414 | O80: =IF(N80="","",IF(N80<FoodClasses!$C$2,"lean",IF(N80<FoodClasses!$C$3,"medium","fatty"))) -> medium | P80: frozen | Q80: ceramic | R80: label | S80: Label says to heat on a microwave-safe plate. | T80: 1100 | U80: complete | V80: no | W80: Label: heat times may need adjusting for other ovens; if needed add time in 5-second increments. | X80: Do not refrigerate longer than 3 days | Keep frozen until ready to use | Product will be hot | Y80: Not on the retailer page; label refers to jimmydean.com for conventional oven directions. | Z80: Paperboard box of individually wrapped sandwiches; wrapper removed before heating. Material not stated. | AA80: Times for 2 sandwiches not given | Uses a 30% defrost step before HIGH | UPC not shown | 4-pack (20.4 oz); the label time is for one sandwich. | AB80: https://www.hannaford.com/groceries/product/jimmy-dean-delights-turkey-sausage-english-muffin-sandwiches-4-ct-20-4-oz-box/153148
A81: zw-220 | B81: El Monterey | C81: Beef & Bean Burritos Family Pack, 8 count | E81: plate | F81: 4 | H81: =IF(G81<>"",G81,IF(F81<>"",ROUND(F81*28.3495,0),"")) -> 113 | I81: 1 | K81: 14 | L81: 0 | M81: =IF(H81="","",H81+L81) -> 113 | N81: =IF(OR(K81="",M81=""),"",IF(J81<>"",K81/J81*H81/M81,IF(I81<>"",K81*I81/M81,""))) -> 0.12389381 | O81: =IF(N81="","",IF(N81<FoodClasses!$C$2,"lean",IF(N81<FoodClasses!$C$3,"medium","fatty"))) -> fatty | P81: frozen | Q81: ceramic | R81: label | S81: Label says to heat on a microwave-safe plate. | T81: 1100 | U81: complete | V81: no | W81: None given. Label says ovens vary. | X81: Product may be hot | Keep frozen | Y81: Oven 375°F, 1 inch apart on baking sheet, uncovered, 25 min, stand 1 min. Air fryer 380°F, 2 burritos, 6 min, flip, 6 min, stand 1 min. | Z81: Bag/box of individually wrapped burritos. Material not stated. | AA81: Wrapper handling (remove or keep) not stated in the transcription; photograph the pack | Time for 2 burritos not given | UPC not shown | 8-pack (32 oz); the label time is for one burrito. | AB81: https://www.hannaford.com/groceries/product/el-monterey-beef-bean-burritos-family-pack-8-ct-frozen-32-oz-pkg/167792
A82: zw-221 | B82: Tyson | C82: Any'tizers Buffalo Style Boneless Chicken Bites | E82: plate | F82: 24 | H82: =IF(G82<>"",G82,IF(F82<>"",ROUND(F82*28.3495,0),"")) -> 680 | I82: 8 | K82: 8 | L82: 0 | M82: =IF(H82="","",H82+L82) -> 680 | N82: =IF(OR(K82="",M82=""),"",IF(J82<>"",K82/J82*H82/M82,IF(I82<>"",K82*I82/M82,""))) -> 0.094117647 | O82: =IF(N82="","",IF(N82<FoodClasses!$C$2,"lean",IF(N82<FoodClasses!$C$3,"medium","fatty"))) -> medium | P82: frozen | Q82: ceramic | R82: label | S82: Label says to heat on a microwave-safe plate. | U82: partial | V82: no | W82: None given. Label: appliances vary, heating times approximate. | X82: Do not overheat | Keep frozen | Y82: Preferred: oven 400°F, foil-lined sprayed baking sheet, top rack, 15-20 min, turn halfway. Air fryer 360°F single layer 11-12 min. | Z82: 24 oz bag of frozen pieces; user supplies the plate. Bag material not stated. | AA82: Microwave times come from a third-party delivery listing (Uber Eats/Gopuff); tyson.com shows a microwave section with no times | No reference wattage | Nutrition conflict: tyson.com 190 kcal / 8 g fat per serving vs H-E-B 170 kcal / 7 g per 3 oz; tyson.com values recorded | UPC not shown | AB82: https://www.ubereats.com/store/gopuff-liquor-%26-more/3L6FApafX7WInNpwwS42Bg/6f073d42-ca45-57a5-857c-a9d7fda78944/6f073d42-ca45-57a5-857c-a9d7fda78944/55cfed84-12c5-517d-a10f-2cd571be1e23 https://www.tyson.com/products/anytizers-boneless-chicken-bites-buffalo https://www.heb.com/product-detail/tyson-any-tizers-frozen-buffalo-style-boneless-chicken-bites/1209812
A83: zw-222 | B83: Smart Ones | C83: Three Cheese Ziti Marinara | E83: frozen_tray | F83: 9 | H83: =IF(G83<>"",G83,IF(F83<>"",ROUND(F83*28.3495,0),"")) -> 255 | I83: 1 | K83: 9 | L83: 0 | M83: =IF(H83="","",H83+L83) -> 255 | N83: =IF(OR(K83="",M83=""),"",IF(J83<>"",K83/J83*H83/M83,IF(I83<>"",K83*I83/M83,""))) -> 0.035294118 | O83: =IF(N83="","",IF(N83<FoodClasses!$C$2,"lean",IF(N83<FoodClasses!$C$3,"medium","fatty"))) -> medium | P83: frozen | Q83: pp_container | R83: inferred | S83: Microwave-only tray or bowl; label forbids the conventional oven or gives no oven method. | T83: 1100 | U83: complete | V83: no | W83: None given. Label: adjust for variations in microwave ovens. | X83: Microwave oven only | Do not prepare in conventional or toaster oven | Do not refreeze | Do not reuse tray | Product and packaging will be hot | Z83: Film-covered tray in carton, microwave only. Material not stated. | AA83: Description says 8 g fat, Nutrition Facts panel says 9 g; panel value recorded | A Canadian Food Basics URL carries 057000036447 for a similar product; not used because it is a different market | UPC not shown | AB83: https://www.hannaford.com/groceries/product/smart-ones-three-cheese-ziti-marinara-12g-protein-frozen-meal-9-oz-box/84637
A84: zw-301 | B84: Ben's Original | C84: Ready Rice Original Long Grain White | D84: 054800423330 | E84: pouch | F84: 8.8 | H84: =IF(G84<>"",G84,IF(F84<>"",ROUND(F84*28.3495,0),"")) -> 249 | K84: 3 | L84: 0 | M84: =IF(H84="","",H84+L84) -> 249 | N84: =IF(OR(K84="",M84=""),"",IF(J84<>"",K84/J84*H84/M84,IF(I84<>"",K84*I84/M84,""))) | O84: =IF(N84="","",IF(N84<FoodClasses!$C$2,"lean",IF(N84<FoodClasses!$C$3,"medium","fatty"))) | P84: shelf | Q84: pouch | R84: label | S84: Microwave or boil-in pouch. | U84: partial | V84: no | W84: None given. Label says microwave times may vary. | Z84: BPA-free microwavable rice pouch, heated in the pouch after tearing a 2-inch vent; has a cool-touch area. Layers not stated. | AA84: steps are a retailer label transcription (Hannaford) but no wattage is printed, so marked partial | per-cup values from Hannaford, per-pouch values (250 g) from ShopRite; servings per container not shown | UPC from ShopRite item ID 00054800423330 | AB84: https://preview.hannaford.com/groceries/rice-pasta-beans/rice/white-rice/bens-original-90-second-microwave-ready-rice-long-grain-white-original-88-oz-pkg.html https://shoprite.com/product/bens-original-ready-rice-original-long-grain-white-rice-easy-dinner-side-88-ounce-pouch-id-00054800423330
A85: zw-302 | B85: Ben's Original | C85: Ready Rice Whole Grain Brown | E85: pouch | F85: 8.8 | H85: =IF(G85<>"",G85,IF(F85<>"",ROUND(F85*28.3495,0),"")) -> 249 | J85: 140 | K85: 3 | L85: 0 | M85: =IF(H85="","",H85+L85) -> 249 | N85: =IF(OR(K85="",M85=""),"",IF(J85<>"",K85/J85*H85/M85,IF(I85<>"",K85*I85/M85,""))) -> 0.021428571 | O85: =IF(N85="","",IF(N85<FoodClasses!$C$2,"lean",IF(N85<FoodClasses!$C$3,"medium","fatty"))) -> lean | P85: shelf | Q85: pouch | R85: label | S85: Microwave or boil-in pouch. | U85: partial | V85: no | W85: None given. Label says microwave times may vary. | Z85: BPA-free microwave rice pouch (H-E-B copy: 'Ready Rice comes in a BPA-free microwave rice pouch'). Caution: steam from pouch will be hot. Layers not stated. | AA85: no wattage printed per transcription | UPC not shown on readable pages | H-E-B shows '0 servings per container' (display error), left null | AB85: https://preview.hannaford.com/groceries/rice-pasta-beans/rice/brown-rice/bens-original-90-second-microwave-ready-rice-whole-grain-brown-88-oz-pkg.html https://heb.com/product-detail/uncle-ben-s-ready-rice-whole-grain-brown-rice/592800
A86: zw-303 | B86: Ben's Original | C86: Ready Rice Garden Vegetable Flavored Rice | E86: pouch | F86: 8.8 | H86: =IF(G86<>"",G86,IF(F86<>"",ROUND(F86*28.3495,0),"")) -> 249 | J86: 145 | K86: 3 | L86: 0 | M86: =IF(H86="","",H86+L86) -> 249 | N86: =IF(OR(K86="",M86=""),"",IF(J86<>"",K86/J86*H86/M86,IF(I86<>"",K86*I86/M86,""))) -> 0.020689655 | O86: =IF(N86="","",IF(N86<FoodClasses!$C$2,"lean",IF(N86<FoodClasses!$C$3,"medium","fatty"))) -> lean | P86: shelf | Q86: pouch | R86: label | S86: Microwave or boil-in pouch. | U86: partial | V86: no | Z86: BPA-free microwavable rice pouch. Layers not stated. | AA86: squeeze and tear-to-vent steps not shown on H-E-B page; other Ready Rice labels (zw-301, zw-302) have them | UPC not shown | AB86: https://heb.com/product-detail/ben-s-original-ready-rice-garden-vegetable/902860
A87: zw-304 | B87: Minute | C87: Ready to Serve White Rice Cups, 2 Count | E87: cup_bowl | F87: 8.8 | H87: =IF(G87<>"",G87,IF(F87<>"",ROUND(F87*28.3495,0),"")) -> 249 | I87: 2 | K87: 2.5 | L87: 0 | M87: =IF(H87="","",H87+L87) -> 249 | N87: =IF(OR(K87="",M87=""),"",IF(J87<>"",K87/J87*H87/M87,IF(I87<>"",K87*I87/M87,""))) -> 0.020080321 | O87: =IF(N87="","",IF(N87<FoodClasses!$C$2,"lean",IF(N87<FoodClasses!$C$3,"medium","fatty"))) -> lean | P87: shelf | Q87: pp_container | R87: label | S87: Minute Rice cups are plastic #5 and BPA free [S70]. | U87: partial | V87: no | W87: None given. Label says microwave ovens and cooking times may vary. | Z87: Single-serve plastic cup with peel-off film lid, in a paper sleeve. Minute FAQ: cups are recyclable (plastic #5) and BPA free. H-E-B copy: '100% recyclable BPA-free cups'. | AA87: no wattage stated | UPC not shown on readable pages | film is removed completely before heating (not vented) | AB87: https://www.safeway.com/shop/pd/minute-ready-to-serve-white-rice-2-count-8-8-oz/960113411 https://www.heb.com/product-detail/minute-ready-to-serve-white-rice-2-ct/1025500 https://minuterice.com/faqs/other/ https://www.orderroombox.com/product/minute-rice-white-rice/
A88: zw-305 | B88: Minute | C88: Ready to Serve Chicken & Herb Seasoned Rice Cups, 2 Count | E88: cup_bowl | H88: =IF(G88<>"",G88,IF(F88<>"",ROUND(F88*28.3495,0),"")) | I88: 2 | L88: 0 | M88: =IF(H88="","",H88+L88) | N88: =IF(OR(K88="",M88=""),"",IF(J88<>"",K88/J88*H88/M88,IF(I88<>"",K88*I88/M88,""))) | O88: =IF(N88="","",IF(N88<FoodClasses!$C$2,"lean",IF(N88<FoodClasses!$C$3,"medium","fatty"))) | P88: shelf | Q88: pp_container | R88: label | S88: Minute Rice cups are plastic #5 and BPA free [S70]. | U88: partial | V88: no | Z88: BPA-free plastic cups recyclable via store drop-off (per H-E-B copy); paper sleeves made from 100% recycled material, curbside recyclable. Brand FAQ says Minute cups are plastic #5. | AA88: only 'heats up in 1 minute' found; film handling and 2-cup time not shown (White Rice cup: remove film completely, 2 cups 1 1/2 min) | total fat not listed on H-E-B page | net weight shown only as 2 x 4.4 oz cups | AB88: https://www.heb.com/product-detail/1137491 https://minuterice.com/faqs/other/
A89: zw-306 | B89: Seeds of Change | C89: Organic Quinoa & Brown Rice with Garlic | E89: pouch | F89: 8.5 | H89: =IF(G89<>"",G89,IF(F89<>"",ROUND(F89*28.3495,0),"")) -> 241 | I89: 2 | K89: 4.5 | L89: 0 | M89: =IF(H89="","",H89+L89) -> 241 | N89: =IF(OR(K89="",M89=""),"",IF(J89<>"",K89/J89*H89/M89,IF(I89<>"",K89*I89/M89,""))) -> 0.037344398 | O89: =IF(N89="","",IF(N89<FoodClasses!$C$2,"lean",IF(N89<FoodClasses!$C$3,"medium","fatty"))) -> medium | P89: shelf | Q89: pouch | R89: label | S89: Microwave or boil-in pouch. | U89: partial | V89: no | Z89: Ready-to-heat microwave pouch, torn 2 inches to vent before heating. Material not stated on this product's pages. | AA89: nutrition conflict: Instacart 240 kcal / 4.5 g per 150 g, about 2 servings; H-E-B 280 kcal / 4.5 g per 1 cup (150 g) and 440 kcal / 8 g per pouch; check package | no wattage stated | BPA-free claim appears on sister product zw-307 but not on this product's pages | AB89: https://milams.instacart.com/store/milams/products/24380-seeds-of-change-organic-quinoa-brown-rice-8-5-oz https://heb.com/product-detail/seeds-of-change-quinoa-brown-rice-with-garlic/1180230
A90: zw-307 | B90: Seeds of Change | C90: Organic Brown Basmati Rice | D90: 748404287930 | E90: pouch | F90: 8.5 | H90: =IF(G90<>"",G90,IF(F90<>"",ROUND(F90*28.3495,0),"")) -> 241 | J90: 240 | K90: 7 | L90: 0 | M90: =IF(H90="","",H90+L90) -> 241 | N90: =IF(OR(K90="",M90=""),"",IF(J90<>"",K90/J90*H90/M90,IF(I90<>"",K90*I90/M90,""))) -> 0.029166667 | O90: =IF(N90="","",IF(N90<FoodClasses!$C$2,"lean",IF(N90<FoodClasses!$C$3,"medium","fatty"))) -> lean | P90: shelf | Q90: pouch | R90: label | S90: Microwave or boil-in pouch. | U90: partial | V90: no | Z90: BPA-free microwave pouch (ShopRite copy: 'BPA free pouch'). Layers not stated. | AA90: tear/vent step not shown on ShopRite copy; sister product zw-306 says tear 2 inches to vent | no wattage stated | AB90: https://www.shoprite.com/product/seeds-of-change-organic-brown-basmati-rice-85-oz-00748404287930
A91: zw-308 | B91: Success | C91: Boil-in-Bag White Rice, 4 Bags | E91: pouch | F91: 14 | H91: =IF(G91<>"",G91,IF(F91<>"",ROUND(F91*28.3495,0),"")) -> 397 | I91: 8 | K91: 0 | L91: 0 | M91: =IF(H91="","",H91+L91) -> 397 | N91: =IF(OR(K91="",M91=""),"",IF(J91<>"",K91/J91*H91/M91,IF(I91<>"",K91*I91/M91,""))) -> 0 | O91: =IF(N91="","",IF(N91<FoodClasses!$C$2,"lean",IF(N91<FoodClasses!$C$3,"medium","fatty"))) -> lean | P91: shelf | Q91: pouch | R91: label | S91: Microwave or boil-in pouch. | U91: partial | V91: no | W91: None given. Brand says microwave ovens vary and times are approximate. | X91: We do not recommend using the microwave to cook multiple bags | Z91: Perforated boil-in-bag inside a carton; cooked submerged in water in a separate bowl, not heated dry. Brand FAQ: 'BPA-Free and FDA-approved for food contact'. Retailer copy: 'Recycle both the box and the bag'. Bag polymer not stated. | AA91: category 'pouch' used for a boil-in-bag that is microwaved under water in a bowl; the app should not treat it like a dry-heat pouch | brand FAQ gives 15 min instead of 10 for Basmati, Jasmine and Quinoa bags | nutrition conflict: H-E-B 180 kcal per 1/2 bag (8 servings); Instacart 210 kcal per 0.5 cup (7 servings); check package | no wattage stated | UPC not shown | AB91: https://successrice.com/faqs/cooking/ https://delivery.publix.com/store/publix/products/22027-success-ten-minute-boil-in-bag-white-rice-3-5-oz https://www.orderroombox.com/product/success-ten-minute-boil-in-bag-white-rice/ https://heb.com/product-detail/success-boil-in-bag-white-rice/33265
A92: zw-309 | B92: Idahoan | C92: Buttery Homestyle Mashed Potatoes Cups, 4 Count | E92: cup_bowl | F92: 1.5 | H92: =IF(G92<>"",G92,IF(F92<>"",ROUND(F92*28.3495,0),"")) -> 43 | I92: 1 | K92: 4 | L92: 177 | M92: =IF(H92="","",H92+L92) -> 220 | N92: =IF(OR(K92="",M92=""),"",IF(J92<>"",K92/J92*H92/M92,IF(I92<>"",K92*I92/M92,""))) -> 0.018181818 | O92: =IF(N92="","",IF(N92<FoodClasses!$C$2,"lean",IF(N92<FoodClasses!$C$3,"medium","fatty"))) -> lean | P92: shelf | Q92: pp_container | R92: unknown | S92: Microwavable cup or bowl; material not stated. Check the base. | T92: 1100 | U92: complete | V92: no | W92: None given. | X92: Do not reuse cup | Z92: Single-serve cup with removable lid and inside fill line; label warns 'Cup & contents will be very hot!' and 'Do not reuse cup'. Material not stated. | AA92: serving size '1 cup' appears to mean one prepared cup container; check package | UPC not shown (brand page store-locator link contains 10029700341411, not labeled as a UPC) | Listing gives the 4-cup box (6 oz); one cup is 1.5 oz. | AB92: https://preview.hannaford.com/groceries/rice-pasta-beans/packaged-meals-sides/instant-potatoes/idahoan-buttery-homestyle-mashed-potatoes-cups-microwave-4-ct-6-oz-pkg.html https://idahoan.com/products/buttery-homestyle-cup https://idahoan.com/collections/cups
A93: zw-310 | B93: Idahoan | C93: Four Cheese Mashed Potatoes Cup | E93: cup_bowl | F93: 1.5 | H93: =IF(G93<>"",G93,IF(F93<>"",ROUND(F93*28.3495,0),"")) -> 43 | L93: 177 | M93: =IF(H93="","",H93+L93) -> 220 | N93: =IF(OR(K93="",M93=""),"",IF(J93<>"",K93/J93*H93/M93,IF(I93<>"",K93*I93/M93,""))) | O93: =IF(N93="","",IF(N93<FoodClasses!$C$2,"lean",IF(N93<FoodClasses!$C$3,"medium","fatty"))) | P93: shelf | Q93: pp_container | R93: unknown | S93: Microwavable cup or bowl; material not stated. Check the base. | U93: partial | V93: no | Z93: Single-serve cup with removable lid and inside fill line; 'Cup and contents will be very hot!'. Material not stated. | AA93: wattage not on brand page; the Buttery Homestyle cup label (zw-309) states 1100 W | nutrition panel not in page text | UPC not shown (store-locator link contains 029700341459, not labeled as a UPC) | AB93: https://idahoan.com/products/four-cheese-cup https://idahoan.com/collections/cups
A94: zw-311 | B94: Bob Evans | C94: Original Mashed Potatoes (refrigerated) | D94: 075900005264 | E94: frozen_tray | F94: 24 | H94: =IF(G94<>"",G94,IF(F94<>"",ROUND(F94*28.3495,0),"")) -> 680 | J94: 140 | K94: 7 | L94: 0 | M94: =IF(H94="","",H94+L94) -> 680 | N94: =IF(OR(K94="",M94=""),"",IF(J94<>"",K94/J94*H94/M94,IF(I94<>"",K94*I94/M94,""))) -> 0.05 | O94: =IF(N94="","",IF(N94<FoodClasses!$C$2,"lean",IF(N94<FoodClasses!$C$3,"medium","fatty"))) -> medium | P94: chilled | Q94: pp_container | R94: inferred | S94: Refrigerated film-sealed plastic tray. | U94: partial | V94: no | W94: None given. Label says settings vary by microwave. | Z94: Refrigerated film-sealed tray inside a paperboard ('board') overwrap; film is vented and then pulled back to stir. Tray material not stated. | AA94: refrigerated (keep refrigerated), not frozen; 'frozen_tray' used because it is a film-sealed tray | label target temperature is 160°F, not the 165°F used on frozen meals | no wattage stated | servings per container given only as 'Serves 4-5' | AB94: https://www.ubereats.com/store/albertsons-3145-s-alma-school-rd/UeGX8RQvWWW0sUqfrFBSKA/33ee60f3-409f-541f-901b-5257775ad45d/7831870f-bd8a-4a2d-8db9-d1c7942d26c0/5a3a55c4-a471-54a6-9d0b-b74104e71a76 https://www.shoprite.com/product/bob-evans-original-mashed-potatoes-24-oz-id-00075900005264 https://www.wegmans.com/shop/product/970214-Original-Mashed-Potatoes
A95: zw-312 | B95: Quaker | C95: Instant Oatmeal Cups Maple & Brown Sugar | E95: cup_bowl | H95: =IF(G95<>"",G95,IF(F95<>"",ROUND(F95*28.3495,0),"")) | L95: 120 | M95: =IF(H95="","",H95+L95) | N95: =IF(OR(K95="",M95=""),"",IF(J95<>"",K95/J95*H95/M95,IF(I95<>"",K95*I95/M95,""))) | O95: =IF(N95="","",IF(N95<FoodClasses!$C$2,"lean",IF(N95<FoodClasses!$C$3,"medium","fatty"))) | P95: shelf | Q95: pp_container | R95: unknown | S95: Microwavable cup or bowl; material not stated. Check the base. | U95: partial | V95: no | W95: None given. Brand says microwave ovens vary in power and time may need adjusting. | Z95: Single-serve cup with removable lid and inside fill line; brand says extra space is built into the cup to prevent boil-over. Caution: cup and contents may be hot. Material not stated. | AA95: net weight, UPC and nutrition not in page text | the SmartLabel link on the brand page resolved to a different product (Quaker Fiber Maple & Brown Sugar packets, UPC 030000261903), so it was not used | no wattage stated | AB95: https://quakeroats.com/products/hot-cereals/instant-oatmeal-cups/maple-and-brown-sugar
A96: zw-313 | B96: Nissin | C96: Cup Noodles Beef Flavor | E96: paper_cup | F96: 2.25 | H96: =IF(G96<>"",G96,IF(F96<>"",ROUND(F96*28.3495,0),"")) -> 64 | I96: 1 | K96: 11 | L96: 300 | M96: =IF(H96="","",H96+L96) -> 364 | N96: =IF(OR(K96="",M96=""),"",IF(J96<>"",K96/J96*H96/M96,IF(I96<>"",K96*I96/M96,""))) -> 0.03021978 | O96: =IF(N96="","",IF(N96<FoodClasses!$C$2,"lean",IF(N96<FoodClasses!$C$3,"medium","fatty"))) -> medium | P96: shelf | Q96: paper_cup | R96: label | S96: Double-wall paper cup since 2024. | U96: partial | V96: no | Z96: Double-wall fiber-based paper cup (Graphic Packaging) introduced in early 2024 for all 16-oz-size Cup Noodles flavors; 40% recycled fiber; sleeve of 100% recycled paper; no plastic overwrap; polystyrene-free. Inner coating not stated. | AA96: 2:15 microwave time is the brand's general statement for the paper cup; Beef lid directions (water volume, stand, stir, wattage) not readable online | net weight from retailer listing title (2.25 oz) | a 2015 Nissin launch also called Cup Noodles 'microwavable' (2 1/2 min); cups in stores may differ by vintage, so check the cup | category paper_cup; zw-017 (Chicken) uses cup_bowl for the same cup and could be recategorized | AB96: https://heb.com/product-detail/nissin-beef-cup-noodles-value-pack/2224358 https://www.packworld.com/design/materials-containers/article/22877972/nissin-foods-cup-noodles-moves-to-paper-cup https://www.nissinfoods.com/?p=1939 https://giantfoodstores.com/groceries/product/nissin-cup-noodles-beef-flavor-ramen-soup-2-25-oz-cup/30574
A97: zw-314 | B97: Maruchan | C97: Bowl Hot & Spicy Chicken Flavor Ramen Noodle Soup | E97: cup_bowl | F97: 3.32 | H97: =IF(G97<>"",G97,IF(F97<>"",ROUND(F97*28.3495,0),"")) -> 94 | L97: 400 | M97: =IF(H97="","",H97+L97) -> 494 | N97: =IF(OR(K97="",M97=""),"",IF(J97<>"",K97/J97*H97/M97,IF(I97<>"",K97*I97/M97,""))) | O97: =IF(N97="","",IF(N97<FoodClasses!$C$2,"lean",IF(N97<FoodClasses!$C$3,"medium","fatty"))) | P97: shelf | Q97: pp_container | R97: unknown | S97: Microwavable cup or bowl; material not stated. Check the base. | U97: partial | V97: no | Z97: Microwavable bowl with peel lid and inside fill line. Material not stated. | AA97: directions come from a 2022 product review that transcribed the package, not a retailer or brand page | net weight from retailer listing title (3.32 oz) | contrast: Maruchan Instant Lunch cup (zw-016) says do not microwave; the Bowl line is microwaved | Maruchan Bowl Chicken Flavor (3.31 oz) directions were not readable online | AB97: https://www.theramenrater.com/2022/10/16/4285-maruchan-ramen-bowl-hot-spicy-chicken-flavor-ramen-noodle-soup-united-states/ https://foodlion.com/groceries/product/maruchan-hot-spicy-chicken-flavor-ramen-noodle-soup-bowl-3-32-oz-pkg/199315
A98: zw-315 | B98: Campbell's | C98: Soup on the Go Tomato Sipping Soup, Microwavable Cup | E98: cup_bowl | F98: 11.1 | H98: =IF(G98<>"",G98,IF(F98<>"",ROUND(F98*28.3495,0),"")) -> 315 | K98: 0.5 | L98: 0 | M98: =IF(H98="","",H98+L98) -> 315 | N98: =IF(OR(K98="",M98=""),"",IF(J98<>"",K98/J98*H98/M98,IF(I98<>"",K98*I98/M98,""))) | O98: =IF(N98="","",IF(N98<FoodClasses!$C$2,"lean",IF(N98<FoodClasses!$C$3,"medium","fatty"))) | P98: shelf | Q98: pp_container | R98: inferred | S98: Microwavable plastic bowl or cup; remove any metal lid first. | U98: partial | V98: no | W98: None given. Label says microwaves vary and time is approximate. | Z98: Sipping cup with red cap and peel-off tab under the cap; label warns 'Metal edges are sharp' after peeling. Cup body material not stated. | AA98: the 'metal edges' caution suggests a metal component at the opening; the label still says to microwave after the tab is removed, so photograph the cup before the app gives any metal warning | serving size and calories not in page text | no wattage stated | UPC not shown | AB98: https://www.ubereats.com/store/meijer-15-caberfae-hwys/_0IgFIy0VAS7aJ6ZCnin6w/7db7887d-ebe8-530f-b42e-cb36f9ea07bd/2a728ca5-308a-55c1-977e-6ead17604b74/543cd83e-ca79-5251-92ec-2a6c9e96df06
A99: zw-316 | B99: Campbell's | C99: Soup on the Go Chicken & Mini Round Noodles, Microwavable Cup | D99: 051000149824 | E99: cup_bowl | F99: 10.75 | H99: =IF(G99<>"",G99,IF(F99<>"",ROUND(F99*28.3495,0),"")) -> 305 | I99: 1 | L99: 0 | M99: =IF(H99="","",H99+L99) -> 305 | N99: =IF(OR(K99="",M99=""),"",IF(J99<>"",K99/J99*H99/M99,IF(I99<>"",K99*I99/M99,""))) | O99: =IF(N99="","",IF(N99<FoodClasses!$C$2,"lean",IF(N99<FoodClasses!$C$3,"medium","fatty"))) | P99: shelf | Q99: pp_container | R99: inferred | S99: Microwavable plastic bowl or cup; remove any metal lid first. | U99: partial | V99: no | Z99: Sipping cup with cap and removable tab; listing references how2recycle.info. Material not stated. | AA99: directions from a reseller description, not a label transcription; the Tomato cup label (zw-315) adds shake, peel-toward-you and stir steps and a sharp-metal-edge caution | calories from '60 calories per container' claim; total fat not in page text | ACME lists 10.8 oz, reseller lists 10.75 oz | AB99: https://www.ontimesupplies.com/grr35100007-soup-on-the-go-chicken-with-mini-noodles-1075-oz-cup-8-carton-ships-in-1-3-business-days.html https://lborderacme.rmrdevelopment.com/product/00051000149824/campbells-soup-chicken-mini-round-noodles
A100: zw-317 | B100: Pop Secret | C100: Butter Microwave Popcorn | E100: popcorn_bag | H100: =IF(G100<>"",G100,IF(F100<>"",ROUND(F100*28.3495,0),"")) | L100: 0 | M100: =IF(H100="","",H100+L100) | N100: =IF(OR(K100="",M100=""),"",IF(J100<>"",K100/J100*H100/M100,IF(I100<>"",K100*I100/M100,""))) | O100: =IF(N100="","",IF(N100<FoodClasses!$C$2,"lean",IF(N100<FoodClasses!$C$3,"medium","fatty"))) | P100: shelf | Q100: popcorn_bag | R100: label | S100: Microwave popcorn bag. | U100: partial | V100: no | W100: None given. Brand says microwave power varies. | X100: Never use the popcorn button | Don't wander off | Z100: Microwave popcorn bag with 'THIS SIDE UP' marking. Bag material, susceptor and PFAS status not stated on brand pages or FAQ. | AA100: 2 1/2 min is a timer setting with an audio stop cue, not a fixed cook time | net weight not in page text (image file names suggest 3.2 oz bags in 6-count boxes, not confirmed) | nutrition values not in page text | no wattage stated | UPC not shown | AB100: https://popsecret.com/products/butter https://popsecret.com/pages/faq
...

Sheet RecipeSteps
A1: Product ID | B1: Step | C1: Kind | D1: Label text (paraphrased) | E1: Time (s) | F1: Time max (s)
A2: zw-001 | B2: 1 | C2: cook | D2: cook on HIGH, no need to vent film | E2: 240
A3: zw-001 | B3: 2 | C3: action | D3: stir and replace film
A4: zw-001 | B4: 3 | C4: cook | D4: cook on HIGH | E4: 120 | F4: 180
A5: zw-001 | B5: 4 | C5: action | D5: check food is cooked thoroughly (165°F)
A6: zw-001 | B6: 5 | C6: stand | D6: stand | E6: 60
A7: zw-002 | B7: 1 | C7: cook | D7: cook on HIGH | E7: 180
A8: zw-002 | B8: 2 | C8: action | D8: rotate chicken, stir sauce into rice, replace film
A9: zw-002 | B9: 3 | C9: cook | D9: cook on HIGH | E9: 150 | F9: 180
A10: zw-002 | B10: 4 | C10: action | D10: check food is cooked thoroughly (165°F)
A11: zw-002 | B11: 5 | C11: stand | D11: stand | E11: 120
A12: zw-003 | B12: 1 | C12: cook | D12: cook on HIGH, no need to vent film | E12: 240
A13: zw-003 | B13: 2 | C13: action | D13: stir and re-cover
A14: zw-003 | B14: 3 | C14: cook | D14: cook on HIGH | E14: 60 | F14: 120
A15: zw-003 | B15: 4 | C15: action | D15: check food is cooked thoroughly (165°F), remove carefully
A16: zw-004 | B16: 1 | C16: action | D16: peel back one corner of film to vent
A17: zw-004 | B17: 2 | C17: cook | D17: cook on HIGH | E17: 300
A18: zw-004 | B18: 3 | C18: action | D18: stir and re-cover
A19: zw-004 | B19: 4 | C19: cook | D19: cook on HIGH | E19: 60 | F19: 120
A20: zw-004 | B20: 5 | C20: action | D20: check food is cooked thoroughly (165°F)
A21: zw-004 | B21: 6 | C21: stand | D21: stand, then stir | E21: 120
A22: zw-005 | B22: 1 | C22: action | D22: leave film on, do not vent
A23: zw-005 | B23: 2 | C23: cook | D23: cook on HIGH | E23: 450
A24: zw-005 | B24: 3 | C24: stand | D24: stand | E24: 60
A25: zw-006 | B25: 1 | C25: cook | D25: cook frozen meal in microwave | E25: 330
A26: zw-007 | B26: 1 | C26: action | D26: cut film to vent
A27: zw-007 | B27: 2 | C27: cook | D27: cook on HIGH | E27: 210
A28: zw-007 | B28: 3 | C28: action | D28: stir and re-cover
A29: zw-007 | B29: 4 | C29: cook | D29: cook on HIGH | E29: 90
A30: zw-007 | B30: 5 | C30: stand | D30: stand (165°F internal) | E30: 60
A31: zw-008 | B31: 1 | C31: action | D31: remove film from dessert compartment
A32: zw-008 | B32: 2 | C32: action | D32: slit film over chicken and ham
A33: zw-008 | B33: 3 | C33: cook | D33: cook on HIGH | E33: 270
A34: zw-008 | B34: 4 | C34: action | D34: stir potatoes, rearrange ham, re-cover
A35: zw-008 | B35: 5 | C35: cook | D35: cook on HIGH | E35: 150 | F35: 180
A36: zw-008 | B36: 6 | C36: action | D36: check food is cooked thoroughly (165°F)
A37: zw-008 | B37: 7 | C37: stand | D37: stand, then stir potatoes | E37: 60
A38: zw-009 | B38: 1 | C38: cook | D38: cook on HIGH, no need to vent film | E38: 270 | F38: 330
A39: zw-009 | B39: 2 | C39: stand | D39: stand in microwave | E39: 60
A40: zw-009 | B40: 3 | C40: action | D40: check food is hot throughout (165°F), stir
A41: zw-010 | B41: 1 | C41: cook | D41: cook on HIGH, no need to vent film | E41: 270 | F41: 360
A42: zw-010 | B42: 2 | C42: action | D42: check food is cooked thoroughly (165°F)
A43: zw-010 | B43: 3 | C43: stand | D43: stand | E43: 60
A44: zw-011 | B44: 1 | C44: cook | D44: microwave | E44: 240 | F44: 270
A45: zw-011 | B45: 2 | C45: action | D45: stir steamed food into sauce bowl
A46: zw-011 | B46: 3 | C46: action | D46: check food is cooked thoroughly
A47: zw-013 | B47: 1 | C47: action | D47: open carton at push tab, tear off top completely; cook in carton
A48: zw-013 | B48: 2 | C48: action | D48: optional: slit top crust for softer crust
A49: zw-013 | B49: 3 | C49: cook | D49: cook on HIGH | E49: 300 | F49: 390
A50: zw-013 | B50: 4 | C50: stand | D50: stand to finish cooking | E50: 300
A51: zw-013 | B51: 5 | C51: action | D51: check food is cooked thoroughly (165°F)
A52: zw-014 | B52: 1 | C52: action | D52: open carton at push tab, tear off top completely; cook in carton
A53: zw-014 | B53: 2 | C53: action | D53: slit top crust
A54: zw-014 | B54: 3 | C54: cook | D54: cook on HIGH | E54: 540 | F54: 600
A55: zw-014 | B55: 4 | C55: stand | D55: stand | E55: 300
A56: zw-014 | B56: 5 | C56: action | D56: check food is cooked thoroughly (165°F)
A57: zw-015 | B57: 1 | C57: action | D57: add water to fill line in cup
A58: zw-015 | B58: 2 | C58: cook | D58: microwave | E58: 210
A59: zw-015 | B59: 3 | C59: action | D59: stir in cheese sauce mix
A60: zw-017 | B60: 1 | C60: action | D60: add water to fill line (details on lid)
A61: zw-017 | B61: 2 | C61: cook | D61: microwave | E61: 135
A62: zw-018 | B62: 1 | C62: action | D62: remove plastic cap, peel off and discard cover, replace plastic cap
A63: zw-018 | B63: 2 | C63: cook | D63: cook on HIGH | E63: 90
A64: zw-018 | B64: 3 | C64: stand | D64: leave in microwave to stand | E64: 60
A65: zw-018 | B65: 4 | C65: cook | D65: optional: heat longer for warmer soup | E65: 30
A66: zw-018 | B66: 5 | C66: action | D66: hold bowl by sides, stir
A67: zw-020 | B67: 1 | C67: action | D67: puncture film in several places or peel back about 1/4 inch
A68: zw-020 | B68: 2 | C68: cook | D68: heat on HIGH or until hot | E68: 60
A69: zw-020 | B69: 3 | C69: stand | D69: optional stand | E69: 60
A70: zw-020 | B70: 4 | C70: action | D70: peel film back carefully
A71: zw-023 | B71: 1 | C71: action | D71: place frozen bag flat, 'this side up' facing up; do not puncture; remove metal rack
A72: zw-023 | B72: 2 | C72: action | D72: cook on HIGH for wattage-specific time (see variants)
A73: zw-023 | B73: 3 | C73: stand | D73: stand | E73: 60 | F73: 120
A74: zw-023 | B74: 4 | C74: action | D74: hold by blue corner tabs, tear at notch, pour, stir
A75: zw-024 | B75: 1 | C75: action | D75: place frozen bag flat, 'this side up' facing up; do not pierce; remove metal rack
A76: zw-024 | B76: 2 | C76: action | D76: cook on HIGH for wattage-specific time (see variants)
A77: zw-024 | B77: 3 | C77: stand | D77: stand | E77: 60 | F77: 120
A78: zw-024 | B78: 4 | C78: action | D78: hold by blue corner tabs, tear at notch, pour, stir
A79: zw-025 | B79: 1 | C79: action | D79: place frozen bag flat, 'this side up' facing up; do not pierce; remove metal rack
A80: zw-025 | B80: 2 | C80: cook | D80: cook on HIGH (bag puffs, vent may whistle) | E80: 300 | F80: 360
A81: zw-025 | B81: 3 | C81: stand | D81: stand | E81: 60
A82: zw-025 | B82: 4 | C82: action | D82: lift by marked corners, tear at notch, pour, stir
A83: zw-026 | B83: 1 | C83: action | D83: place unopened bag standing up in center of microwave
A84: zw-026 | B84: 2 | C84: cook | D84: cook on HIGH until hot | E84: 330 | F84: 360
A85: zw-026 | B85: 3 | C85: stand | D85: stand in microwave | E85: 60
A86: zw-026 | B86: 4 | C86: action | D86: remove bag carefully
A87: zw-027 | B87: 1 | C87: action | D87: place unopened bag standing up in center of microwave
A88: zw-027 | B88: 2 | C88: cook | D88: cook on HIGH until hot | E88: 330 | F88: 360
A89: zw-027 | B89: 3 | C89: stand | D89: stand in microwave | E89: 60
A90: zw-027 | B90: 4 | C90: action | D90: remove bag carefully
A91: zw-028 | B91: 1 | C91: action | D91: place unopened bag standing up on a microwavable dinner plate
A92: zw-028 | B92: 2 | C92: action | D92: cook on HIGH for wattage-specific time (see variants)
A93: zw-028 | B93: 3 | C93: stand | D93: stand in microwave | E93: 60
A94: zw-028 | B94: 4 | C94: action | D94: remove plate and bag, tear at notch, empty into dish, stir
A95: zw-029 | B95: 1 | C95: cook | D95: microwave pouch | E95: 90
A96: zw-030 | B96: 1 | C96: cook | D96: microwave pouch | E96: 90
A97: zw-033 | B97: 1 | C97: action | D97: Quick-Bake only: preheat oven to 375°F
A98: zw-033 | B98: 2 | C98: cook | D98: microwave on HIGH (partial cook) | E98: 480
A99: zw-033 | B99: 3 | C99: oven | D99: peel back film corner, transfer to baking sheet, finish in oven | E99: 1500 | F99: 1800
A100: zw-033 | B100: 4 | C100: stand | D100: check food is cooked thoroughly (165°F), stand | E100: 300
...

Sheet WattTables
A1: Product ID | B1: Watt | C1: Time (s) | D1: Time max (s)
A2: zw-023 | B2: 1200 | C2: 330
A3: zw-023 | B3: 1000 | C3: 360
A4: zw-023 | B4: 800 | C4: 420
A5: zw-024 | B5: 1200 | C5: 300
A6: zw-024 | B6: 1000 | C6: 330
A7: zw-024 | B7: 800 | C7: 360
A8: zw-026 | B8: 1000 | C8: 330 | D8: 360
A9: zw-026 | B9: 700 | C9: 420
A10: zw-027 | B10: 1000 | C10: 330 | D10: 360
A11: zw-027 | B11: 700 | C11: 420
A12: zw-028 | B12: 1200 | C12: 300 | D12: 330
A13: zw-028 | B13: 1000 | C13: 420 | D13: 450
A14: zw-028 | B14: 700 | C14: 510 | D14: 540
A15: zw-121 | B15: 1200 | C15: 330
A16: zw-121 | B16: 1000 | C16: 360
A17: zw-121 | B17: 800 | C17: 450
A18: zw-126 | B18: 1200 | C18: 270 | D18: 300
A19: zw-126 | B19: 1000 | C19: 360 | D19: 390
A20: zw-126 | B20: 700 | C20: 420 | D20: 450
A21: zw-320 | B21: 1200 | C21: 270
A22: zw-320 | B22: 1000 | C22: 300
A23: zw-320 | B23: 800 | C23: 360
A24: zw-321 | B24: 1200 | C24: 300
A25: zw-321 | B25: 1000 | C25: 330
A26: zw-321 | B26: 800 | C26: 360
A27: zw-322 | B27: 1200 | C27: 480
A28: zw-322 | B28: 1000 | C28: 540
A29: zw-322 | B29: 800 | C29: 600
A30: zw-323 | B30: 1200 | C30: 180 | D30: 240
A31: zw-323 | B31: 1000 | C31: 240 | D31: 270
A32: zw-323 | B32: 700 | C32: 300
A33: zw-324 | B33: 1200 | C33: 270 | D33: 330
A34: zw-324 | B34: 1000 | C34: 300 | D34: 360
A35: zw-324 | B35: 700 | C35: 360 | D35: 420
A36: zw-325 | B36: 1200 | C36: 180 | D36: 210
A37: zw-325 | B37: 1000 | C37: 240
A38: zw-325 | B38: 700 | C38: 300 | D38: 330

Sheet Literature
A1: Container | B1: Material | C1: Food or simulant | D1: Heating | E1: Substance | F1: Measured | G1: Unit | H1: Source
A2: 5 new PP household containers (480-1200 mL), filled 90% with water | B2: PP | C2: ultrapure water | D2: domestic microwave: 700 W for 1/3/5/7 min; 350 W for 1/3/5/7 min; 210 W for 10/15/20/30 min | E2: DBP | F2: <LOQ to 2.0 (max in 1200 mL container D) | G2: ug/L | H2: Moreira, Andre, Cardeal 2014, IJERPH 11:507-526, doi:10.3390/ijerph110100507, https://www.mdpi.com/1660-4601/11/1/507/html (LOD 0.08, LOQ 0.2 ug/L)
A3: 5 PP household containers used ~1 year (300-1200 mL), filled 90% with water | B3: PP (aged) | C3: ultrapure water | D3: same as above (700/350/210 W, 1-30 min) | E3: DBP | F3: <LOQ to 7.5 | G3: ug/L | H3: Moreira et al. 2014, https://www.mdpi.com/1660-4601/11/1/507/html ; per-condition values only in figures (not extracted)
A4: 10 PP containers (new and used) | B4: PP | C4: ultrapure water | D4: 700/350/210 W, 1-30 min | E4: BBP | F4: not detected | G4: ug/L (LOD 0.31, LOQ 0.5) | H4: Moreira et al. 2014, https://www.mdpi.com/1660-4601/11/1/507/html
A5: PP baby-food containers and PE reusable pouch | B5: PP; PE | C5: deionised water; 3% acetic acid | D5: microwave 3 min (1000 W full power per press coverage; power not in abstract: UNVERIFIED) | E5: microplastic and nanoplastic particles (context only, not a chemical migrant) | F5: up to 4.22 million microplastics and 2.11 billion nanoplastics per cm2 | G5: particles per cm2 of container surface | H5: Hussain KA et al. 2023, Environ Sci Technol 57:9782-9792, doi:10.1021/acs.est.3c01942, https://digitalcommons.unl.edu/civilengfacpub/298
A6: CPET ovenable ready-meal tray, lasagna with meat | B6: CPET (Sb 290-318 mg/kg) | C6: lasagna (meat) | D6: CONVENTIONAL OVEN 200 C, 30 min (not microwave) | E6: Sb | F6: raw 1.7 -> cooked 9.4 (3.0 ug migrated measured; 4.0 ug modelled) | G6: ug/kg fresh weight | H6: Haldimann et al. 2013, doi:10.1080/19440049.2012.751631, https://pmc.ncbi.nlm.nih.gov/articles/PMC3613973/
A7: CPET ovenable tray, pasta gratin | B7: CPET | C7: pasta gratin | D7: conventional oven 200 C, 30 min | E7: Sb | F7: raw 2.2 -> cooked 13.7 (2.0 ug measured; 2.4 ug modelled) | G7: ug/kg fresh weight | H7: Haldimann et al. 2013, https://pmc.ncbi.nlm.nih.gov/articles/PMC3613973/
A8: CPET ovenable tray, cannelloni bolognese | B8: CPET | C8: cannelloni (bolognese) | D8: conventional oven 200 C, 30 min | E8: Sb | F8: raw 2.8 -> cooked 13.6 (1.8 ug measured; 2.2 ug modelled) | G8: ug/kg fresh weight | H8: Haldimann et al. 2013, https://pmc.ncbi.nlm.nih.gov/articles/PMC3613973/
A9: CPET ovenable tray, cannelloni | B9: CPET | C9: cannelloni | D9: conventional oven 200 C, 30 min | E9: Sb | F9: raw 3.7 -> cooked 14.9 (4.7 ug measured; 4.7 ug modelled) | G9: ug/kg fresh weight | H9: Haldimann et al. 2013, https://pmc.ncbi.nlm.nih.gov/articles/PMC3613973/
A10: CPET ovenable tray, fish fillets provencal | B10: CPET | C10: fish fillets (provencal) | D10: conventional oven 200 C, 30 min | E10: Sb | F10: raw 3.0 -> cooked 9.1 (3.6 ug measured; 3.4 ug modelled) | G10: ug/kg fresh weight | H10: Haldimann et al. 2013, https://pmc.ncbi.nlm.nih.gov/articles/PMC3613973/
A11: CPET ovenable tray, pasta with meat | B11: CPET | C11: pasta (meat) | D11: conventional oven 200 C, 30 min | E11: Sb | F11: raw 2.6 -> cooked 13.8 (2.1 ug measured; 2.8 ug modelled) | G11: ug/kg fresh weight | H11: Haldimann et al. 2013, https://pmc.ncbi.nlm.nih.gov/articles/PMC3613973/
A12: CPET tray strips | B12: CPET | C12: 3% acetic acid | D12: 24 h at 120 / 135 / 150 C (simulant test, not microwave) | E12: Sb | F12: 6.8 / 18.6 / 62.0 % of Sb in polymer migrated; D = 3.0e-11 / 2.4e-10 / 3.3e-9 cm2/s; Ea = 188 +/- 36 kJ/mol; D0 = 3.6e14 cm2/s | G12: % of initial Sb; cm2/s | H12: Haldimann et al. 2013, https://pmc.ncbi.nlm.nih.gov/articles/PMC3613973/
A13: PS dish (n=3), 380 mL water, 337 cm2 | B13: PS | C13: distilled water | D13: 40 C, 10 days (NOT microwave; EU 'extreme conditions') | E13: DEHP (also DMP 19, DBP <LOD, BBP <LOD, DEHA 40, NP 184, OP 39 ng/L) | F13: 701 +/- 479 (range 323-1239) | G13: ng/L | H13: Fasano E et al. 2012, Food Control 27:132-138, doi:10.1016/j.foodcont.2012.03.005, https://www.iris.unina.it/retrieve/handle/11588/469035/52932/Migration%20of%20phthalates%2C.pdf

Sheet Validation
A1: Case | B1: Quantity | C1: Unit | D1: Measured | E1: Predicted | F1: Note | G1: Predicted / measured
A2: V2 | B2: D antimony in CPET at 120 C | C2: cm2/s | D2: 3e-11 | E2: 3.7910598e-11 | F2: Arrhenius fit D0 3.6e14 cm2/s, Ea 188 kJ/mol against the D reported for each temperature [S02]. | G2: =IF(AND(ISNUMBER(D2),ISNUMBER(E2)),IF(D2<>0,E2/D2,""),"") -> 1.2636866
A3: V1 | B3: Sb released in 24 h at 120 C (fitted D) | C3: % of total Sb | D3: 6.8 | E3: 6.31 | F3: Strips in 3 % acetic acid, large simulant volume (alpha = 1e6), 62 % of Sb diffusible [S02]. | G3: =IF(AND(ISNUMBER(D3),ISNUMBER(E3)),IF(D3<>0,E3/D3,""),"") -> 0.92794118
A4: V1 | B4: Sb released in 24 h at 120 C (reported D) | C4: % of total Sb | D4: 6.8 | E4: 5.41 | F4: Strips in 3 % acetic acid, large simulant volume (alpha = 1e6), 62 % of Sb diffusible [S02]. | G4: =IF(AND(ISNUMBER(D4),ISNUMBER(E4)),IF(D4<>0,E4/D4,""),"") -> 0.79558824
A5: V2 | B5: D antimony in CPET at 135 C | C5: cm2/s | D5: 2.4e-10 | E5: 3.1384494e-10 | F5: Arrhenius fit D0 3.6e14 cm2/s, Ea 188 kJ/mol against the D reported for each temperature [S02]. | G5: =IF(AND(ISNUMBER(D5),ISNUMBER(E5)),IF(D5<>0,E5/D5,""),"") -> 1.3076873
A6: V1 | B6: Sb released in 24 h at 135 C (fitted D) | C6: % of total Sb | D6: 18.6 | E6: 23.5 | F6: Strips in 3 % acetic acid, large simulant volume (alpha = 1e6), 62 % of Sb diffusible [S02]. | G6: =IF(AND(ISNUMBER(D6),ISNUMBER(E6)),IF(D6<>0,E6/D6,""),"") -> 1.2634409
A7: V1 | B7: Sb released in 24 h at 135 C (reported D) | C7: % of total Sb | D7: 18.6 | E7: 20.55 | F7: Strips in 3 % acetic acid, large simulant volume (alpha = 1e6), 62 % of Sb diffusible [S02]. | G7: =IF(AND(ISNUMBER(D7),ISNUMBER(E7)),IF(D7<>0,E7/D7,""),"") -> 1.1048387
A8: V2 | B8: D antimony in CPET at 150 C | C8: cm2/s | D8: 3.3e-09 | E8: 2.2366064e-09 | F8: Arrhenius fit D0 3.6e14 cm2/s, Ea 188 kJ/mol against the D reported for each temperature [S02]. | G8: =IF(AND(ISNUMBER(D8),ISNUMBER(E8)),IF(D8<>0,E8/D8,""),"") -> 0.6777595
A9: V1 | B9: Sb released in 24 h at 150 C (fitted D) | C9: % of total Sb | D9: 62 | E9: 55.09 | F9: Strips in 3 % acetic acid, large simulant volume (alpha = 1e6), 62 % of Sb diffusible [S02]. | G9: =IF(AND(ISNUMBER(D9),ISNUMBER(E9)),IF(D9<>0,E9/D9,""),"") -> 0.88854839
A10: V1 | B10: Sb released in 24 h at 150 C (reported D) | C10: % of total Sb | D10: 62 | E10: 59.31 | F10: Strips in 3 % acetic acid, large simulant volume (alpha = 1e6), 62 % of Sb diffusible [S02]. | G10: =IF(AND(ISNUMBER(D10),ISNUMBER(E10)),IF(D10<>0,E10/D10,""),"") -> 0.9566129
A11: V3 | B11: D antimony at 100 C, Piringer PET upper bound vs Arrhenius fit | C11: cm2/s | D11: 1.7378834e-12 | E11: 3.1213907e-09 | F11: Piringer is 1796 times higher. It is built for organic migrants, so the engine uses the measured Arrhenius fit for antimony. | G11: =IF(AND(ISNUMBER(D11),ISNUMBER(E11)),IF(D11<>0,E11/D11,""),"") -> 1796.0876
A12: V4 | B12: DBP in water after 7 min at 700 W, wall 0.6 mm, content central | C12: ug/L | D12: <0.2 to 2.0 | E12: 0.849 | F12: Water ends near 79 C in the model. Partition regression for water (EtOH-eq 0) gives log K 2.49. DBP content of the tested containers was not reported, so the 0-2.83 mg/kg range from S03/S04 is used. Measured range for new containers [S05]. | G12: =IF(AND(ISNUMBER(D12),ISNUMBER(E12)),IF(D12<>0,E12/D12,""),"")
A13: V4 | B13: DBP in water after 7 min at 700 W, wall 0.6 mm, content high | C13: ug/L | D13: <0.2 to 2.0 | E13: 1.698 | F13: Water ends near 79 C in the model. Partition regression for water (EtOH-eq 0) gives log K 2.49. DBP content of the tested containers was not reported, so the 0-2.83 mg/kg range from S03/S04 is used. Measured range for new containers [S05]. | G13: =IF(AND(ISNUMBER(D13),ISNUMBER(E13)),IF(D13<>0,E13/D13,""),"")
A14: V4 | B14: DBP in water after 7 min at 700 W, wall 1.2 mm, content central | C14: ug/L | D14: <0.2 to 2.0 | E14: 0.849 | F14: Water ends near 79 C in the model. Partition regression for water (EtOH-eq 0) gives log K 2.49. DBP content of the tested containers was not reported, so the 0-2.83 mg/kg range from S03/S04 is used. Measured range for new containers [S05]. | G14: =IF(AND(ISNUMBER(D14),ISNUMBER(E14)),IF(D14<>0,E14/D14,""),"")
A15: V4 | B15: DBP in water after 7 min at 700 W, wall 1.2 mm, content high | C15: ug/L | D15: <0.2 to 2.0 | E15: 1.698 | F15: Water ends near 79 C in the model. Partition regression for water (EtOH-eq 0) gives log K 2.49. DBP content of the tested containers was not reported, so the 0-2.83 mg/kg range from S03/S04 is used. Measured range for new containers [S05]. | G15: =IF(AND(ISNUMBER(D15),ISNUMBER(E15)),IF(D15<>0,E15/D15,""),"")
A16: V5 | B16: Absorbed fraction of rated power implied by 61 complete label recipes (median) | C16: - | D16: 0.6 | E16: 0.543 | F16: Range 0.38-1.05. Measured column is the 1 L water reference (about 0.6 in the Panasonic check [S50]; about 1.0 in S42). Small 250-450 g loads couple less than 1 L water [S26], so a value somewhat below 0.6 is expected. A value far outside 0.3-1.0 would mean the heating model disagrees with how labels were written. | G16: =IF(AND(ISNUMBER(D16),ISNUMBER(E16)),IF(D16<>0,E16/D16,""),"") -> 0.905
A17: V6 | B17: Steam bag film temperature after 4 min (zw-023, 1100 W): generic wall model | C17: C | D17: 95 to 102 | E17: 45.7 | F17: Patent example, oven power not stated [S55]. The generic model (food average 35 C plus a wall excess) misses the steam that forms inside the bag. | G17: =IF(AND(ISNUMBER(D17),ISNUMBER(E17)),IF(D17<>0,E17/D17,""),"")
A18: V6 | B18: Steam bag film temperature after 4 min (zw-023, 1100 W): steam contact mode | C18: C | D18: 95 to 102 | E18: 100 | F18: After this check the engine puts the film of steam bags at 100 C once 60 % of the label energy is delivered (steam_onset_fraction). | G18: =IF(AND(ISNUMBER(D18),ISNUMBER(E18)),IF(D18<>0,E18/D18,""),"")
A19: V7 | B19: log Kpf RMSE, published regression, all 1,881 rows | C19: log10 units | E19: 0.761 | F19: R2 0.922, n 1881, mean error -0.03. ml/train_kpf.py [S76]. | G19: =IF(AND(ISNUMBER(D19),ISNUMBER(E19)),IF(D19<>0,E19/D19,""),"")
A20: V7 | B20: log Kpf RMSE, refitted regression, whole studies held out | C20: log10 units | E20: 1.108 | F20: R2 0.767, n 366, mean error -0.28. ml/train_kpf.py [S76]. | G20: =IF(AND(ISNUMBER(D20),ISNUMBER(E20)),IF(D20<>0,E20/D20,""),"")
A21: V7 | B21: log Kpf RMSE, refitted regression, chemicals held out | C21: log10 units | E21: 0.788 | F21: R2 0.917, n 1881, mean error -0.00. ml/train_kpf.py [S76]. | G21: =IF(AND(ISNUMBER(D21),ISNUMBER(E21)),IF(D21<>0,E21/D21,""),"")
A22: V7 | B22: log Kpf RMSE, published regression, PP rows | C22: log10 units | E22: 0.752 | F22: R2 0.777, n 56, mean error -0.02. ml/train_kpf.py [S76]. | G22: =IF(AND(ISNUMBER(D22),ISNUMBER(E22)),IF(D22<>0,E22/D22,""),"")
A23: V7 | B23: log Kpf of DEHP in PP, lean food (EtOH-eq 35 %), 100 C | C23: log10 | D23: 3 | E23: 3.28 | F23: Measured column holds the v0.2 rule (JRC default K = 1000 for every lipophilic migrant in watery food). The regression agrees for DEHP. | G23: =IF(AND(ISNUMBER(D23),ISNUMBER(E23)),IF(D23<>0,E23/D23,""),"") -> 1.0933333
A24: V7 | B24: log Kpf of DBP in PP, lean food (EtOH-eq 35 %), 100 C | C24: log10 | D24: 3 | E24: 0.76 | F24: For DBP the regression gives a much lower K than the old default, so more DBP is predicted to move into watery food. | G24: =IF(AND(ISNUMBER(D24),ISNUMBER(E24)),IF(D24<>0,E24/D24,""),"") -> 0.25333333
A25: V8 | B25: D of DEHP in PP at 100 C: Huang 2017 (measured column) vs Piringer upper bound (predicted column) | C25: cm2/s | D25: 5.21e-08 | E25: 1.15e-07 | F25: Piringer / Huang = 2.2. The engine uses the log midpoint (7.74e-08) and samples between the two. Huang 2017 SE is 1.17 log units [S78]. | G25: =IF(AND(ISNUMBER(D25),ISNUMBER(E25)),IF(D25<>0,E25/D25,""),"") -> 2.2072937
A26: V8 | B26: D of DBP in PP at 100 C: Huang 2017 (measured column) vs Piringer upper bound (predicted column) | C26: cm2/s | D26: 1.21e-07 | E26: 3.54e-07 | F26: Piringer / Huang = 2.9. The engine uses the log midpoint (2.07e-07) and samples between the two. Huang 2017 SE is 1.17 log units [S78]. | G26: =IF(AND(ISNUMBER(D26),ISNUMBER(E26)),IF(D26<>0,E26/D26,""),"") -> 2.9256198
A27: V8 | B27: D of I168 in PP at 100 C: Huang 2017 (measured column) vs Piringer upper bound (predicted column) | C27: cm2/s | D27: 1.48e-08 | E27: 1.38e-08 | F27: Piringer / Huang = 0.9. The engine uses the log midpoint (1.43e-08) and samples between the two. Huang 2017 SE is 1.17 log units [S78]. | G27: =IF(AND(ISNUMBER(D27),ISNUMBER(E27)),IF(D27<>0,E27/D27,""),"") -> 0.93243243

Sheet Models
A1: Model | B1: Item | C1: Value | D1: Sources
A2: Vision model | B2: Backbone | C2: MobileNetV2 1.0 224, ImageNet weights, frozen | D2: S48
A3: Vision model | B3: Training data | C3: TrashNet, 6 classes, 1769/379/379 photos (train/val/test) | D3: S47
A4: Vision model | B4: Head | C4: mlp (validation accuracy linear 0.860, mlp 0.889)
A5: Vision model | B5: Test accuracy | C5: 0.8206
A6: Vision model | B6: Test macro F1 | C6: 0.7947
A7: Vision model | B7: Per-class F1 | C7: cardboard 0.839, glass 0.81, metal 0.79, paper 0.883, plastic 0.824, trash 0.622
A8: Vision model | B8: TFLite size (MB) | C8: 2.86
A9: Vision model | B9: TFLite vs Keras | C9: embedding cosine min 0.9777, top-1 agreement 58/60
A10: Vision model | B10: Split | C10: by object id (file prefix before _), seed 7, 70/15/15
A11: Product look-up | B11: Top-1 on re-photographed objects | C11: 0.9933 | D11: S47
A12: Product look-up | B12: Top-5 | C12: 0.9983
A13: Product look-up | B13: Cosine, same object (median / 5th pct) | C13: 0.842 / 0.726
A14: Product look-up | B14: Cosine, object not in gallery (median / 95th pct) | C14: 0.640 / 0.742
A15: Product look-up | B15: Accept threshold (95th pct of unknown) | C15: 0.7416
A16: Product look-up | B16: Share of correct matches above threshold | C16: 0.9312
A17: Product look-up | B17: Note | C17: Gallery and unknown photos are TrashNet images (MIT). Replace with product photos once the student has them.
A18: Partition coefficient model | B18: Data | C18: 1881 measured log Kpf/Kmw, 233 chemicals, 19 materials, 2-40 C, EtOH-eq 0-100 % | D18: S76
A19: Partition coefficient model | B19: Used in the app | C19: Published Huang and Jolliet 2019 material-specific regression (KpfModel sheet) | D19: S76
A20: Partition coefficient model | B20: Published regression, all rows | C20: RMSE 0.76, R2 0.922, n 1881 | D20: S76
A21: Partition coefficient model | B21: Refitted regression, whole studies held out | C21: RMSE 1.11, R2 0.767, n 366
A22: Partition coefficient model | B22: Monotone gradient boosting, whole studies held out | C22: RMSE 1.10, R2 0.769, n 366
A23: Partition coefficient model | B23: Refitted regression, chemicals held out (5-fold) | C23: RMSE 0.79, R2 0.917, n 1881
A24: Partition coefficient model | B24: Monotone gradient boosting, chemicals held out (5-fold) | C24: RMSE 0.75, R2 0.925, n 1881
A25: Partition coefficient model | B25: Vaferi 2025 GBR as printed (random split, mostly in-sample) | C25: RMSE 0.24, R2 0.992, n 1847 | D25: S79
A26: Partition coefficient model | B26: PP rows (homopolymer and copolymer), published regression | C26: RMSE 0.75, R2 0.777, n 56 | D26: S76
A27: Partition coefficient model | B27: Why the regression | C27: Gradient boosting was only 5 % better on held-out chemicals and equal on held-out studies, and it cannot extrapolate to 100 C or to log Kow above the data. The regression extrapolates in a stated, checkable way.

Sheet Student_Checklist
A1: Task | B1: Replaces | C1: Why | D1: Done (y/n) | E1: Result
A2: Measure tray and cup wall thickness with calipers (5 products, 3 spots each). | B2: containers.thickness_cm | C2: Replaces the 0.3-0.6 mm assumption.
A3: Measure the inner contact area of 5 containers with a ruler (base plus wetted wall). | B3: containers.area_ref_cm2 | C3: Replaces the geometric estimate.
A4: Photograph the resin code and 'oven safe' marks of every seed product. | B4: products.container_key | C4: Turns 'inferred' rows into 'label' rows.
A5: Run the 300 g water test in each family microwave (start and end temperature, 2 min). | B5: appliance power | C5: Gives the real power of each oven.
A6: Check a few meals with a food thermometer after the label time (center and edge). | B6: T_target_avg_C, edge_excess_C | C6: Tests the temperature model.
A7: Run ml/train_kpf.py and explain the model comparison; look for food-simulant studies (e.g. FACET, Seiler 2014) to check the EtOH-eq range of each fat class. | B7: food_classes etoh_low/high | C7: The EtOH-eq ranges are anchored to EU simulants and two dataset foods only.
A8: Ask a teacher to review the phthalate content ranges (S03, S04). | B8: contents | C8: Only two studies exist for PP.
A9: Photograph the base of every container (resin code, 'dual ovenable', 'microwave safe') and run the OCR cue reader on it. | B9: products.container_key, container_cues | C9: Turns 'unknown' and 'inferred' containers into labelled ones and tests the CPET/PP reader.
A10: Put a food thermometer probe against the film of a steam bag right after cooking (3 products). | B10: steam_onset_fraction | C10: Checks validation V6 with your own data.
A11: Photograph 15 or more CPET trays and 15 or more PP trays (several photos each) for the Colab notebook. | B11: vision model | C11: Lets the photo model separate CPET from PP when no marking is readable.
